Workbook

Sheet Schedule
A1: Project NorthStar - SAP S/4HANA 2023 SPS06 upgrade schedule
A2: ="As of "&TEXT(AsOf,"ddd d mmm yyyy")&" | Update the Status column daily (drop-down). Phase rows roll up by themselves. | CONFIDENTIAL AND PROPRIETARY TO INTERNATIONAL" -> As of Sun 18 Oct 2026 | Update the Status column daily (drop-down). Phase rows roll up by themselves. | CONFIDENTIAL AND PROPRIETARY TO INTERNATIONAL
L3: 46307 | S3: 46314 | Z3: 46321 | AG3: 46328 | AN3: 46335 | AU3: 46342 | BB3: 46349 | BI3: 46356 | BP3: 46363 | BW3: 46370 | CD3: 46377 | CK3: 46384
A4: ID | B4: Task | C4: Team | D4: Days | E4: Start | F4: Finish | G4: Status | H4: % Complete | I4: Predecessors | J4: Detail tasks | K4: Type | L4: 46307 | M4: 46308 | N4: 46309 | O4: 46310 | P4: 46311 | Q4: 46312 | R4: 46313 | S4: 46314 | T4: 46315 | U4: 46316 | V4: 46317 | W4: 46318 | X4: 46319 | Y4: 46320 | Z4: 46321 | AA4: 46322 | AB4: 46323 | AC4: 46324 | AD4: 46325 | AE4: 46326 | AF4: 46327 | AG4: 46328 | AH4: 46329 | AI4: 46330 | AJ4: 46331 | AK4: 46332 | AL4: 46333 | AM4: 46334 | AN4: 46335 | AO4: 46336 | AP4: 46337 | AQ4: 46338 | AR4: 46339 | AS4: 46340 | AT4: 46341 | AU4: 46342 | AV4: 46343 | AW4: 46344 | AX4: 46345 | AY4: 46346 | AZ4: 46347 | BA4: 46348 | BB4: 46349 | BC4: 46350 | BD4: 46351 | BE4: 46352 | BF4: 46353 | BG4: 46354 | BH4: 46355 | BI4: 46356 | BJ4: 46357 | BK4: 46358 | BL4: 46359 | BM4: 46360 | BN4: 46361 | BO4: 46362 | BP4: 46363 | BQ4: 46364 | BR4: 46365 | BS4: 46366 | BT4: 46367 | BU4: 46368 | BV4: 46369 | BW4: 46370 | BX4: 46371 | BY4: 46372 | BZ4: 46373 | CA4: 46374 | CB4: 46375 | CC4: 46376 | CD4: 46377 | CE4: 46378 | CF4: 46379 | CG4: 46380 | CH4: 46381 | CI4: 46382 | CJ4: 46383 | CK4: 46384 | CL4: 46385 | CM4: 46386 | CN4: 46387 | CO4: 46388 | CP4: 46389 | CQ4: 46390
A5: 0 | B5: Start-up | D5: =IF(OR(E5="",F5=""),"",F5-E5+1) -> 14 | E5: =MIN(E6:E9) -> 46297 | F5: =MAX(F6:F9) -> 46310 | G5: =IF(COUNTIF(G6:G9,"Blocked")>0,"Blocked",IF(COUNTIF(G6:G9,"At Risk")>0,"At Risk",IF(COUNTIF(G6:G9,"Complete")=ROWS(G6:G9),"Complete",IF(COUNTIF(G6:G9,"Not Started")=ROWS(G6:G9),"Not Started","On Track")))) -> Complete | H5: =IFERROR(SUMPRODUCT(D6:D9,H6:H9)/SUM(D6:D9),0) -> 1 | K5: Summary
A6: 0.1 | B6: Triage SAP side-effect notes | C6: PwC Tech | D6: =IF(K6="Milestone",0,F6-E6+1) -> 5 | E6: 46297 | F6: 46301 | G6: Complete | H6: =IF(G6="Complete",1,IF(OR(G6="Not Started",K6="Milestone",AsOf<E6),0,MIN(0.9,MAX(0,(AsOf-E6+1)/(F6-E6+1))))) -> 1 | J6: H.4 | K6: Task
A7: 0.2 | B7: Plan XS4 stack and request update | C7: INTL Basis | D7: =IF(K7="Milestone",0,F7-E7+1) -> 2 | E7: 46298 | F7: 46299 | G7: Complete | H7: =IF(G7="Complete",1,IF(OR(G7="Not Started",K7="Milestone",AsOf<E7),0,MIN(0.9,MAX(0,(AsOf-E7+1)/(F7-E7+1))))) -> 1 | J7: H.1, H.2 | K7: Task
A8: 0.3 | B8: Close first XS4 update run (SUM reset) | C8: SAP ECS | D8: =IF(K8="Milestone",0,F8-E8+1) -> 8 | E8: 46302 | F8: 46309 | G8: Complete | H8: =IF(G8="Complete",1,IF(OR(G8="Not Started",K8="Milestone",AsOf<E8),0,MIN(0.9,MAX(0,(AsOf-E8+1)/(F8-E8+1))))) -> 1 | I8: 0.2 | J8: H.3 | K8: Task
A9: 0.4 | B9: ◆ Approach set: Sandbox = copy of DS4 | C9: INTL Basis | D9: =IF(K9="Milestone",0,F9-E9+1) -> 0 | E9: 46310 | F9: 46310 | G9: Complete | H9: =IF(G9="Complete",1,IF(OR(G9="Not Started",K9="Milestone",AsOf<E9),0,MIN(0.9,MAX(0,(AsOf-E9+1)/(F9-E9+1))))) -> 1 | I9: 0.3 | J9: H.5 | K9: Milestone | L9: =IF(L$4=$E9,"◆","") | M9: =IF(M$4=$E9,"◆","") | N9: =IF(N$4=$E9,"◆","") | O9: =IF(O$4=$E9,"◆","") -> ◆ | P9: =IF(P$4=$E9,"◆","") | Q9: =IF(Q$4=$E9,"◆","") | R9: =IF(R$4=$E9,"◆","") | S9: =IF(S$4=$E9,"◆","") | ... CQ9: =IF(CQ$4=$E9,"◆","")
A10: 1 | B10: Prepare Sandbox | D10: =IF(OR(E10="",F10=""),"",F10-E10+1) -> 14 | E10: =MIN(E11:E29) -> 46310 | F10: =MAX(F11:F29) -> 46323 | G10: =IF(COUNTIF(G11:G29,"Blocked")>0,"Blocked",IF(COUNTIF(G11:G29,"At Risk")>0,"At Risk",IF(COUNTIF(G11:G29,"Complete")=ROWS(G11:G29),"Complete",IF(COUNTIF(G11:G29,"Not Started")=ROWS(G11:G29),"Not Started","On Track")))) -> On Track | H10: =IFERROR(SUMPRODUCT(D11:D29,H11:H29)/SUM(D11:D29),0) -> 0.17283951 | K10: Summary
A11: 1.1 | B11: Align plan with PwC Tech | C11: PwC Tech | D11: =IF(K11="Milestone",0,F11-E11+1) -> 2 | E11: 46310 | F11: 46311 | G11: Complete | H11: =IF(G11="Complete",1,IF(OR(G11="Not Started",K11="Milestone",AsOf<E11),0,MIN(0.9,MAX(0,(AsOf-E11+1)/(F11-E11+1))))) -> 1 | I11: 0.4 | J11: 0.01a | K11: Task
A12: 1.2 | B12: Review plan (functional streams) | C12: PwC Functional | D12: =IF(K12="Milestone",0,F12-E12+1) -> 4 | E12: 46311 | F12: 46314 | G12: On Track | H12: =IF(G12="Complete",1,IF(OR(G12="Not Started",K12="Milestone",AsOf<E12),0,MIN(0.9,MAX(0,(AsOf-E12+1)/(F12-E12+1))))) -> 0.75 | I12: 1.1 | J12: 0.01b | K12: Task
A13: 1.3 | B13: Implement SAP Notes in DS4 | C13: INTL Basis | D13: =IF(K13="Milestone",0,F13-E13+1) -> 2 | E13: 46310 | F13: 46311 | G13: Complete | H13: =IF(G13="Complete",1,IF(OR(G13="Not Started",K13="Milestone",AsOf<E13),0,MIN(0.9,MAX(0,(AsOf-E13+1)/(F13-E13+1))))) -> 1 | I13: 0.4 | J13: 0.02 | K13: Task
A14: 1.4 | B14: Request DS4 to XS4 copy from ECS | C14: INTL Basis | D14: =IF(K14="Milestone",0,F14-E14+1) -> 2 | E14: 46310 | F14: 46311 | G14: Complete | H14: =IF(G14="Complete",1,IF(OR(G14="Not Started",K14="Milestone",AsOf<E14),0,MIN(0.9,MAX(0,(AsOf-E14+1)/(F14-E14+1))))) -> 1 | I14: 0.4 | J14: 0.04a | K14: Task
A15: 1.5 | B15: Create Maintenance Planner plans | C15: INTL Basis | D15: =IF(K15="Milestone",0,F15-E15+1) -> 2 | E15: 46310 | F15: 46311 | G15: Complete | H15: =IF(G15="Complete",1,IF(OR(G15="Not Started",K15="Milestone",AsOf<E15),0,MIN(0.9,MAX(0,(AsOf-E15+1)/(F15-E15+1))))) -> 1 | J15: 0.05 | K15: Task
A16: 1.6 | B16: Run SI-check and pre-checks | C16: INTL Basis | D16: =IF(K16="Milestone",0,F16-E16+1) -> 7 | E16: 46311 | F16: 46317 | G16: On Track | H16: =IF(G16="Complete",1,IF(OR(G16="Not Started",K16="Milestone",AsOf<E16),0,MIN(0.9,MAX(0,(AsOf-E16+1)/(F16-E16+1))))) -> 0.42857143 | I16: 1.3 | J16: 0.03, 0.16 | K16: Task
A17: 1.7 | B17: Approve plan at Steering | C17: INTL PMO | D17: =IF(K17="Milestone",0,F17-E17+1) -> 1 | E17: 46315 | F17: 46315 | G17: Not Started | H17: =IF(G17="Complete",1,IF(OR(G17="Not Started",K17="Milestone",AsOf<E17),0,MIN(0.9,MAX(0,(AsOf-E17+1)/(F17-E17+1))))) -> 0 | I17: 1.2 | J17: 0.01 | K17: Task
A18: 1.8 | B18: Request remaining copies and upgrades | C18: INTL Basis | D18: =IF(K18="Milestone",0,F18-E18+1) -> 3 | E18: 46314 | F18: 46316 | G18: Not Started | H18: =IF(G18="Complete",1,IF(OR(G18="Not Started",K18="Milestone",AsOf<E18),0,MIN(0.9,MAX(0,(AsOf-E18+1)/(F18-E18+1))))) -> 0 | I18: 1.5 | J18: 0.04, 0.06 | K18: Task
A19: 1.9 | B19: Prepare copy isolation checklist | C19: INTL Basis | D19: =IF(K19="Milestone",0,F19-E19+1) -> 3 | E19: 46314 | F19: 46316 | G19: Not Started | H19: =IF(G19="Complete",1,IF(OR(G19="Not Started",K19="Milestone",AsOf<E19),0,MIN(0.9,MAX(0,(AsOf-E19+1)/(F19-E19+1))))) -> 0 | J19: 0.10 | K19: Task
A20: 1.10 | B20: Line up SAP support and on-call | C20: INTL Basis | D20: =IF(K20="Milestone",0,F20-E20+1) -> 5 | E20: 46314 | F20: 46318 | G20: Not Started | H20: =IF(G20="Complete",1,IF(OR(G20="Not Started",K20="Milestone",AsOf<E20),0,MIN(0.9,MAX(0,(AsOf-E20+1)/(F20-E20+1))))) -> 0 | I20: 1.2 | J20: 0.07, 0.08, 0.09 | K20: Task
A21: 1.11 | B21: Send vendor questions | C21: INTL Basis | D21: =IF(K21="Milestone",0,F21-E21+1) -> 10 | E21: 46314 | F21: 46323 | G21: Not Started | H21: =IF(G21="Complete",1,IF(OR(G21="Not Started",K21="Milestone",AsOf<E21),0,MIN(0.9,MAX(0,(AsOf-E21+1)/(F21-E21+1))))) -> 0 | J21: 0.11 | K21: Task
A22: 1.12 | B22: Check custom code (ATC) | C22: PwC Tech | D22: =IF(K22="Milestone",0,F22-E22+1) -> 5 | E22: 46314 | F22: 46318 | G22: Not Started | H22: =IF(G22="Complete",1,IF(OR(G22="Not Started",K22="Milestone",AsOf<E22),0,MIN(0.9,MAX(0,(AsOf-E22+1)/(F22-E22+1))))) -> 0 | J22: 0.13, 0.14 | K22: Task
A23: 1.13 | B23: Assess Fiori app impact | C23: PwC Tech | D23: =IF(K23="Milestone",0,F23-E23+1) -> 10 | E23: 46314 | F23: 46323 | G23: Not Started | H23: =IF(G23="Complete",1,IF(OR(G23="Not Started",K23="Milestone",AsOf<E23),0,MIN(0.9,MAX(0,(AsOf-E23+1)/(F23-E23+1))))) -> 0 | J23: 0.17, 0.18 | K23: Task
A24: 1.14 | B24: Create data-migration users (SDMI) | C24: INTL Security | D24: =IF(K24="Milestone",0,F24-E24+1) -> 5 | E24: 46314 | F24: 46318 | G24: Not Started | H24: =IF(G24="Complete",1,IF(OR(G24="Not Started",K24="Milestone",AsOf<E24),0,MIN(0.9,MAX(0,(AsOf-E24+1)/(F24-E24+1))))) -> 0 | J24: 0.15 | K24: Task
A25: 1.15 | B25: Prepare CFIN/SLT and GTS runbooks | C25: PwC Functional | D25: =IF(K25="Milestone",0,F25-E25+1) -> 10 | E25: 46314 | F25: 46323 | G25: Not Started | H25: =IF(G25="Complete",1,IF(OR(G25="Not Started",K25="Milestone",AsOf<E25),0,MIN(0.9,MAX(0,(AsOf-E25+1)/(F25-E25+1))))) -> 0 | J25: 0.19, 0.20 | K25: Task
A26: 1.16 | B26: Agree Mock3 rules with Syniti | C26: PwC Data Migration | D26: =IF(K26="Milestone",0,F26-E26+1) -> 2 | E26: 46314 | F26: 46315 | G26: Not Started | H26: =IF(G26="Complete",1,IF(OR(G26="Not Started",K26="Milestone",AsOf<E26),0,MIN(0.9,MAX(0,(AsOf-E26+1)/(F26-E26+1))))) -> 0 | J26: 0.21 | K26: Task
A27: 1.17 | B27: Publish transport rules | C27: INTL Basis | D27: =IF(K27="Milestone",0,F27-E27+1) -> 3 | E27: 46316 | F27: 46318 | G27: Not Started | H27: =IF(G27="Complete",1,IF(OR(G27="Not Started",K27="Milestone",AsOf<E27),0,MIN(0.9,MAX(0,(AsOf-E27+1)/(F27-E27+1))))) -> 0 | I27: 1.7 | J27: 0.12 | K27: Task
A28: 1.18 | B28: Tag regression scripts | C28: INTL Testing | D28: =IF(K28="Milestone",0,F28-E28+1) -> 5 | E28: 46314 | F28: 46318 | G28: Not Started | H28: =IF(G28="Complete",1,IF(OR(G28="Not Started",K28="Milestone",AsOf<E28),0,MIN(0.9,MAX(0,(AsOf-E28+1)/(F28-E28+1))))) -> 0 | J28: 0.22 | K28: Task
A29: 1.19 | B29: ◆ G0 Ready for Sandbox | C29: INTL PMO | D29: =IF(K29="Milestone",0,F29-E29+1) -> 0 | E29: 46317 | F29: 46317 | G29: Not Started | H29: =IF(G29="Complete",1,IF(OR(G29="Not Started",K29="Milestone",AsOf<E29),0,MIN(0.9,MAX(0,(AsOf-E29+1)/(F29-E29+1))))) -> 0 | I29: 1.3, 1.4, 1.5, 1.6, 1.7, 1.8, 1.9 | J29: G0 | K29: Milestone | L29: =IF(L$4=$E29,"◆","") | M29: =IF(M$4=$E29,"◆","") | N29: =IF(N$4=$E29,"◆","") | O29: =IF(O$4=$E29,"◆","") | P29: =IF(P$4=$E29,"◆","") | Q29: =IF(Q$4=$E29,"◆","") | R29: =IF(R$4=$E29,"◆","") | S29: =IF(S$4=$E29,"◆","") | ... CQ29: =IF(CQ$4=$E29,"◆","")
A30: 2 | B30: Sandbox XS4 | D30: =IF(OR(E30="",F30=""),"",F30-E30+1) -> 9 | E30: =MIN(E31:E41) -> 46316 | F30: =MAX(F31:F41) -> 46324 | G30: =IF(COUNTIF(G31:G41,"Blocked")>0,"Blocked",IF(COUNTIF(G31:G41,"At Risk")>0,"At Risk",IF(COUNTIF(G31:G41,"Complete")=ROWS(G31:G41),"Complete",IF(COUNTIF(G31:G41,"Not Started")=ROWS(G31:G41),"Not Started","On Track")))) -> Not Started | H30: =IFERROR(SUMPRODUCT(D31:D41,H31:H41)/SUM(D31:D41),0) -> 0 | K30: Summary
A31: 2.1 | B31: Copy DS4 to XS4 | C31: SAP ECS | D31: =IF(K31="Milestone",0,F31-E31+1) -> 2 | E31: 46316 | F31: 46317 | G31: Not Started | H31: =IF(G31="Complete",1,IF(OR(G31="Not Started",K31="Milestone",AsOf<E31),0,MIN(0.9,MAX(0,(AsOf-E31+1)/(F31-E31+1))))) -> 0 | I31: 1.3, 1.4 | J31: 1.01 | K31: Task
A32: 2.2 | B32: Isolate XS4 | C32: INTL Basis | D32: =IF(K32="Milestone",0,F32-E32+1) -> 1 | E32: 46317 | F32: 46317 | G32: Not Started | H32: =IF(G32="Complete",1,IF(OR(G32="Not Started",K32="Milestone",AsOf<E32),0,MIN(0.9,MAX(0,(AsOf-E32+1)/(F32-E32+1))))) -> 0 | I32: 2.1, 1.9 | J32: 1.02 | K32: Task
A33: 2.3 | B33: Check notes and resubmit SUM request | C33: INTL Basis | D33: =IF(K33="Milestone",0,F33-E33+1) -> 1 | E33: 46317 | F33: 46317 | G33: Not Started | H33: =IF(G33="Complete",1,IF(OR(G33="Not Started",K33="Milestone",AsOf<E33),0,MIN(0.9,MAX(0,(AsOf-E33+1)/(F33-E33+1))))) -> 0 | I33: 2.2 | J33: 1.03 | K33: Task
A34: 2.4 | B34: Upgrade XS4 (downtime Sat 24 Oct) | C34: SAP ECS | D34: =IF(K34="Milestone",0,F34-E34+1) -> 4 | E34: 46317 | F34: 46320 | G34: Not Started | H34: =IF(G34="Complete",1,IF(OR(G34="Not Started",K34="Milestone",AsOf<E34),0,MIN(0.9,MAX(0,(AsOf-E34+1)/(F34-E34+1))))) -> 0 | I34: 2.3, 1.19 | J34: 1.04 | K34: Task
A35: 2.5 | B35: Adjust custom code (SPDD/SPAU) | C35: PwC Tech | D35: =IF(K35="Milestone",0,F35-E35+1) -> 3 | E35: 46319 | F35: 46321 | G35: Not Started | H35: =IF(G35="Complete",1,IF(OR(G35="Not Started",K35="Milestone",AsOf<E35),0,MIN(0.9,MAX(0,(AsOf-E35+1)/(F35-E35+1))))) -> 0 | I35: 2.4SS | J35: 1.05 | K35: Task
A36: 2.6 | B36: Run technical and Fiori checks | C36: INTL Basis | D36: =IF(K36="Milestone",0,F36-E36+1) -> 2 | E36: 46320 | F36: 46321 | G36: Not Started | H36: =IF(G36="Complete",1,IF(OR(G36="Not Started",K36="Milestone",AsOf<E36),0,MIN(0.9,MAX(0,(AsOf-E36+1)/(F36-E36+1))))) -> 0 | I36: 2.4 | J36: 1.06, 1.07 | K36: Task
A37: 2.7 | B37: Update roles (SU25, GRC) | C37: INTL Security | D37: =IF(K37="Milestone",0,F37-E37+1) -> 2 | E37: 46321 | F37: 46322 | G37: Not Started | H37: =IF(G37="Complete",1,IF(OR(G37="Not Started",K37="Milestone",AsOf<E37),0,MIN(0.9,MAX(0,(AsOf-E37+1)/(F37-E37+1))))) -> 0 | I37: 2.6 | J37: 1.08 | K37: Task
A38: 2.8 | B38: Trial SAP note bundle | C38: PwC Tech | D38: =IF(K38="Milestone",0,F38-E38+1) -> 3 | E38: 46321 | F38: 46323 | G38: Not Started | H38: =IF(G38="Complete",1,IF(OR(G38="Not Started",K38="Milestone",AsOf<E38),0,MIN(0.9,MAX(0,(AsOf-E38+1)/(F38-E38+1))))) -> 0 | I38: 2.5 | J38: 1.09 | K38: Task
A39: 2.9 | B39: Test Sandbox (30 tests) | C39: PwC Functional | D39: =IF(K39="Milestone",0,F39-E39+1) -> 3 | E39: 46321 | F39: 46323 | G39: Not Started | H39: =IF(G39="Complete",1,IF(OR(G39="Not Started",K39="Milestone",AsOf<E39),0,MIN(0.9,MAX(0,(AsOf-E39+1)/(F39-E39+1))))) -> 0 | I39: 2.6 | J39: 1.10 | K39: Task
A40: 2.10 | B40: Confirm upgrade windows with ECS | C40: INTL Basis | D40: =IF(K40="Milestone",0,F40-E40+1) -> 1 | E40: 46323 | F40: 46323 | G40: Not Started | H40: =IF(G40="Complete",1,IF(OR(G40="Not Started",K40="Milestone",AsOf<E40),0,MIN(0.9,MAX(0,(AsOf-E40+1)/(F40-E40+1))))) -> 0 | I40: 2.4 | J40: 1.11 | K40: Task
A41: 2.11 | B41: ◆ G1 Sandbox sign-off | C41: INTL PMO | D41: =IF(K41="Milestone",0,F41-E41+1) -> 0 | E41: 46324 | F41: 46324 | G41: Not Started | H41: =IF(G41="Complete",1,IF(OR(G41="Not Started",K41="Milestone",AsOf<E41),0,MIN(0.9,MAX(0,(AsOf-E41+1)/(F41-E41+1))))) -> 0 | I41: 2.5, 2.6, 2.7, 2.8, 2.9, 2.10 | J41: G1 | K41: Milestone | L41: =IF(L$4=$E41,"◆","") | M41: =IF(M$4=$E41,"◆","") | N41: =IF(N$4=$E41,"◆","") | O41: =IF(O$4=$E41,"◆","") | P41: =IF(P$4=$E41,"◆","") | Q41: =IF(Q$4=$E41,"◆","") | R41: =IF(R$4=$E41,"◆","") | S41: =IF(S$4=$E41,"◆","") | ... CQ41: =IF(CQ$4=$E41,"◆","")
A42: 3 | B42: Development DS4 (+ DS5 copy) | D42: =IF(OR(E42="",F42=""),"",F42-E42+1) -> 18 | E42: =MIN(E43:E53) -> 46322 | F42: =MAX(F43:F53) -> 46339 | G42: =IF(COUNTIF(G43:G53,"Blocked")>0,"Blocked",IF(COUNTIF(G43:G53,"At Risk")>0,"At Risk",IF(COUNTIF(G43:G53,"Complete")=ROWS(G43:G53),"Complete",IF(COUNTIF(G43:G53,"Not Started")=ROWS(G43:G53),"Not Started","On Track")))) -> Not Started | H42: =IFERROR(SUMPRODUCT(D43:D53,H43:H53)/SUM(D43:D53),0) -> 0 | K42: Summary
A43: 3.1 | B43: Copy DS4 to DS5 (fallback) | C43: SAP ECS | D43: =IF(K43="Milestone",0,F43-E43+1) -> 2 | E43: 46322 | F43: 46323 | G43: Not Started | H43: =IF(G43="Complete",1,IF(OR(G43="Not Started",K43="Milestone",AsOf<E43),0,MIN(0.9,MAX(0,(AsOf-E43+1)/(F43-E43+1))))) -> 0 | I43: 1.8 | J43: 2.01 | K43: Task
A44: 3.2 | B44: Open DS5 for fixes | C44: INTL Basis | D44: =IF(K44="Milestone",0,F44-E44+1) -> 2 | E44: 46323 | F44: 46324 | G44: Not Started | H44: =IF(G44="Complete",1,IF(OR(G44="Not Started",K44="Milestone",AsOf<E44),0,MIN(0.9,MAX(0,(AsOf-E44+1)/(F44-E44+1))))) -> 0 | I44: 3.1 | J44: 2.02 | K44: Task
A45: 3.3 | B45: Freeze DS4 transports | C45: PwC Tech | D45: =IF(K45="Milestone",0,F45-E45+1) -> 1 | E45: 46325 | F45: 46325 | G45: Not Started | H45: =IF(G45="Complete",1,IF(OR(G45="Not Started",K45="Milestone",AsOf<E45),0,MIN(0.9,MAX(0,(AsOf-E45+1)/(F45-E45+1))))) -> 0 | I45: 1.17 | J45: 2.03 | K45: Task
A46: 3.4 | B46: Upgrade DS4 (downtime Sat 31 Oct) | C46: SAP ECS | D46: =IF(K46="Milestone",0,F46-E46+1) -> 3 | E46: 46325 | F46: 46327 | G46: Not Started | H46: =IF(G46="Complete",1,IF(OR(G46="Not Started",K46="Milestone",AsOf<E46),0,MIN(0.9,MAX(0,(AsOf-E46+1)/(F46-E46+1))))) -> 0 | I46: 2.11 | J46: 2.04 | K46: Task
A47: 3.5 | B47: Adjust custom code (SPDD/SPAU) | C47: PwC Tech | D47: =IF(K47="Milestone",0,F47-E47+1) -> 3 | E47: 46326 | F47: 46328 | G47: Not Started | H47: =IF(G47="Complete",1,IF(OR(G47="Not Started",K47="Milestone",AsOf<E47),0,MIN(0.9,MAX(0,(AsOf-E47+1)/(F47-E47+1))))) -> 0 | I47: 3.4SS | J47: 2.05 | K47: Task
A48: 3.6 | B48: Run technical checks | C48: INTL Basis | D48: =IF(K48="Milestone",0,F48-E48+1) -> 2 | E48: 46327 | F48: 46328 | G48: Not Started | H48: =IF(G48="Complete",1,IF(OR(G48="Not Started",K48="Milestone",AsOf<E48),0,MIN(0.9,MAX(0,(AsOf-E48+1)/(F48-E48+1))))) -> 0 | I48: 3.4 | J48: 2.06 | K48: Task
A49: 3.7 | B49: Update roles | C49: INTL Security | D49: =IF(K49="Milestone",0,F49-E49+1) -> 2 | E49: 46328 | F49: 46329 | G49: Not Started | H49: =IF(G49="Complete",1,IF(OR(G49="Not Started",K49="Milestone",AsOf<E49),0,MIN(0.9,MAX(0,(AsOf-E49+1)/(F49-E49+1))))) -> 0 | I49: 3.6 | J49: 2.07 | K49: Task
A50: 3.8 | B50: Apply notes and unit test | C50: PwC Tech | D50: =IF(K50="Milestone",0,F50-E50+1) -> 3 | E50: 46328 | F50: 46330 | G50: Not Started | H50: =IF(G50="Complete",1,IF(OR(G50="Not Started",K50="Milestone",AsOf<E50),0,MIN(0.9,MAX(0,(AsOf-E50+1)/(F50-E50+1))))) -> 0 | I50: 3.5 | J50: 2.08 | K50: Task
A51: 3.9 | B51: Test integrations in Dev | C51: PwC Functional | D51: =IF(K51="Milestone",0,F51-E51+1) -> 2 | E51: 46329 | F51: 46330 | G51: Not Started | H51: =IF(G51="Complete",1,IF(OR(G51="Not Started",K51="Milestone",AsOf<E51),0,MIN(0.9,MAX(0,(AsOf-E51+1)/(F51-E51+1))))) -> 0 | I51: 3.6 | J51: 2.09 | K51: Task
A52: 3.10 | B52: Keep DS5 and DS4 in sync | C52: PwC Tech | D52: =IF(K52="Milestone",0,F52-E52+1) -> 15 | E52: 46325 | F52: 46339 | G52: Not Started | H52: =IF(G52="Complete",1,IF(OR(G52="Not Started",K52="Milestone",AsOf<E52),0,MIN(0.9,MAX(0,(AsOf-E52+1)/(F52-E52+1))))) -> 0 | I52: 3.2 | J52: 2.10 | K52: Task
A53: 3.11 | B53: ◆ G2 Dev ready | C53: INTL PMO | D53: =IF(K53="Milestone",0,F53-E53+1) -> 0 | E53: 46330 | F53: 46330 | G53: Not Started | H53: =IF(G53="Complete",1,IF(OR(G53="Not Started",K53="Milestone",AsOf<E53),0,MIN(0.9,MAX(0,(AsOf-E53+1)/(F53-E53+1))))) -> 0 | I53: 3.5, 3.6, 3.7, 3.8, 3.9 | J53: G2 | K53: Milestone | L53: =IF(L$4=$E53,"◆","") | M53: =IF(M$4=$E53,"◆","") | N53: =IF(N$4=$E53,"◆","") | O53: =IF(O$4=$E53,"◆","") | P53: =IF(P$4=$E53,"◆","") | Q53: =IF(Q$4=$E53,"◆","") | R53: =IF(R$4=$E53,"◆","") | S53: =IF(S$4=$E53,"◆","") | ... CQ53: =IF(CQ$4=$E53,"◆","")
A54: 4 | B54: QA QS4 (+ QS5 copy) | D54: =IF(OR(E54="",F54=""),"",F54-E54+1) -> 9 | E54: =MIN(E55:E67) -> 46330 | F54: =MAX(F55:F67) -> 46338 | G54: =IF(COUNTIF(G55:G67,"Blocked")>0,"Blocked",IF(COUNTIF(G55:G67,"At Risk")>0,"At Risk",IF(COUNTIF(G55:G67,"Complete")=ROWS(G55:G67),"Complete",IF(COUNTIF(G55:G67,"Not Started")=ROWS(G55:G67),"Not Started","On Track")))) -> Not Started | H54: =IFERROR(SUMPRODUCT(D55:D67,H55:H67)/SUM(D55:D67),0) -> 0 | K54: Summary
A55: 4.1 | B55: Copy QS4 to QS5 (fallback) | C55: SAP ECS | D55: =IF(K55="Milestone",0,F55-E55+1) -> 2 | E55: 46330 | F55: 46331 | G55: Not Started | H55: =IF(G55="Complete",1,IF(OR(G55="Not Started",K55="Milestone",AsOf<E55),0,MIN(0.9,MAX(0,(AsOf-E55+1)/(F55-E55+1))))) -> 0 | I55: 1.8 | J55: 3.01 | K55: Task
A56: 4.2 | B56: Isolate QS5 | C56: INTL Basis | D56: =IF(K56="Milestone",0,F56-E56+1) -> 2 | E56: 46331 | F56: 46332 | G56: Not Started | H56: =IF(G56="Complete",1,IF(OR(G56="Not Started",K56="Milestone",AsOf<E56),0,MIN(0.9,MAX(0,(AsOf-E56+1)/(F56-E56+1))))) -> 0 | I56: 4.1 | J56: 3.02 | K56: Task
A57: 4.3 | B57: Close SIT2 and freeze results | C57: INTL Testing | D57: =IF(K57="Milestone",0,F57-E57+1) -> 1 | E57: 46332 | F57: 46332 | G57: Not Started | H57: =IF(G57="Complete",1,IF(OR(G57="Not Started",K57="Milestone",AsOf<E57),0,MIN(0.9,MAX(0,(AsOf-E57+1)/(F57-E57+1))))) -> 0 | J57: 3.03 | K57: Task
A58: 4.4 | B58: Pause QS4 interfaces | C58: INTL Basis | D58: =IF(K58="Milestone",0,F58-E58+1) -> 1 | E58: 46332 | F58: 46332 | G58: Not Started | H58: =IF(G58="Complete",1,IF(OR(G58="Not Started",K58="Milestone",AsOf<E58),0,MIN(0.9,MAX(0,(AsOf-E58+1)/(F58-E58+1))))) -> 0 | I58: 1.15 | J58: 3.04 | K58: Task
A59: 4.5 | B59: Upgrade QS4 (downtime Sat 7 Nov) | C59: SAP ECS | D59: =IF(K59="Milestone",0,F59-E59+1) -> 4 | E59: 46331 | F59: 46334 | G59: Not Started | H59: =IF(G59="Complete",1,IF(OR(G59="Not Started",K59="Milestone",AsOf<E59),0,MIN(0.9,MAX(0,(AsOf-E59+1)/(F59-E59+1))))) -> 0 | I59: 3.11 | J59: 3.05 | K59: Task
A60: 4.6 | B60: Run technical checks | C60: INTL Basis | D60: =IF(K60="Milestone",0,F60-E60+1) -> 1 | E60: 46334 | F60: 46334 | G60: Not Started | H60: =IF(G60="Complete",1,IF(OR(G60="Not Started",K60="Milestone",AsOf<E60),0,MIN(0.9,MAX(0,(AsOf-E60+1)/(F60-E60+1))))) -> 0 | I60: 4.5 | J60: 3.06 | K60: Task
A61: 4.7 | B61: Resume CFIN, GTS and BTP links | C61: PwC Functional | D61: =IF(K61="Milestone",0,F61-E61+1) -> 2 | E61: 46334 | F61: 46335 | G61: Not Started | H61: =IF(G61="Complete",1,IF(OR(G61="Not Started",K61="Milestone",AsOf<E61),0,MIN(0.9,MAX(0,(AsOf-E61+1)/(F61-E61+1))))) -> 0 | I61: 4.6 | J61: 3.07 | K61: Task
A62: 4.8 | B62: Run regression (P1 scripts) | C62: PwC Functional | D62: =IF(K62="Milestone",0,F62-E62+1) -> 4 | E62: 46335 | F62: 46338 | G62: Not Started | H62: =IF(G62="Complete",1,IF(OR(G62="Not Started",K62="Milestone",AsOf<E62),0,MIN(0.9,MAX(0,(AsOf-E62+1)/(F62-E62+1))))) -> 0 | I62: 4.7, 4.3 | J62: 3.08 | K62: Task
A63: 4.9 | B63: Test security | C63: INTL Security | D63: =IF(K63="Milestone",0,F63-E63+1) -> 3 | E63: 46335 | F63: 46337 | G63: Not Started | H63: =IF(G63="Complete",1,IF(OR(G63="Not Started",K63="Milestone",AsOf<E63),0,MIN(0.9,MAX(0,(AsOf-E63+1)/(F63-E63+1))))) -> 0 | I63: 4.6 | J63: 3.09 | K63: Task
A64: 4.10 | B64: Validate data loads (Syniti) | C64: PwC Data Migration | D64: =IF(K64="Milestone",0,F64-E64+1) -> 3 | E64: 46335 | F64: 46337 | G64: Not Started | H64: =IF(G64="Complete",1,IF(OR(G64="Not Started",K64="Milestone",AsOf<E64),0,MIN(0.9,MAX(0,(AsOf-E64+1)/(F64-E64+1))))) -> 0 | I64: 4.6 | J64: 3.10 | K64: Task
A65: 4.11 | B65: Ready QS5 as fallback | C65: PwC Functional | D65: =IF(K65="Milestone",0,F65-E65+1) -> 3 | E65: 46335 | F65: 46337 | G65: Not Started | H65: =IF(G65="Complete",1,IF(OR(G65="Not Started",K65="Milestone",AsOf<E65),0,MIN(0.9,MAX(0,(AsOf-E65+1)/(F65-E65+1))))) -> 0 | I65: 4.2 | J65: 3.11 | K65: Task
A66: 4.12 | B66: Fix and retest defects | C66: PwC Functional | D66: =IF(K66="Milestone",0,F66-E66+1) -> 4 | E66: 46335 | F66: 46338 | G66: Not Started | H66: =IF(G66="Complete",1,IF(OR(G66="Not Started",K66="Milestone",AsOf<E66),0,MIN(0.9,MAX(0,(AsOf-E66+1)/(F66-E66+1))))) -> 0 | I66: 4.8SS | J66: 3.12 | K66: Task
A67: 4.13 | B67: ◆ G3 Go for pre-production | C67: INTL PMO | D67: =IF(K67="Milestone",0,F67-E67+1) -> 0 | E67: 46338 | F67: 46338 | G67: Not Started | H67: =IF(G67="Complete",1,IF(OR(G67="Not Started",K67="Milestone",AsOf<E67),0,MIN(0.9,MAX(0,(AsOf-E67+1)/(F67-E67+1))))) -> 0 | I67: 4.5, 4.6, 4.7, 4.8, 4.9, 4.10, 4.11, 4.12 | J67: G3 | K67: Milestone | L67: =IF(L$4=$E67,"◆","") | M67: =IF(M$4=$E67,"◆","") | N67: =IF(N$4=$E67,"◆","") | O67: =IF(O$4=$E67,"◆","") | P67: =IF(P$4=$E67,"◆","") | Q67: =IF(Q$4=$E67,"◆","") | R67: =IF(R$4=$E67,"◆","") | S67: =IF(S$4=$E67,"◆","") | ... CQ67: =IF(CQ$4=$E67,"◆","")
A68: 5 | B68: Pre-production SS4 | D68: =IF(OR(E68="",F68=""),"",F68-E68+1) -> 26 | E68: =MIN(E69:E76) -> 46335 | F68: =MAX(F69:F76) -> 46360 | G68: =IF(COUNTIF(G69:G76,"Blocked")>0,"Blocked",IF(COUNTIF(G69:G76,"At Risk")>0,"At Risk",IF(COUNTIF(G69:G76,"Complete")=ROWS(G69:G76),"Complete",IF(COUNTIF(G69:G76,"Not Started")=ROWS(G69:G76),"Not Started","On Track")))) -> Not Started | H68: =IFERROR(SUMPRODUCT(D69:D76,H69:H76)/SUM(D69:D76),0) -> 0 | K68: Summary
A69: 5.1 | B69: Run UAT week 1 (FPS02) | C69: Business (UAT) | D69: =IF(K69="Milestone",0,F69-E69+1) -> 5 | E69: 46335 | F69: 46339 | G69: Not Started | H69: =IF(G69="Complete",1,IF(OR(G69="Not Started",K69="Milestone",AsOf<E69),0,MIN(0.9,MAX(0,(AsOf-E69+1)/(F69-E69+1))))) -> 0 | J69: 4.01 | K69: Task
A70: 5.2 | B70: Pause SS4 interfaces | C70: INTL Basis | D70: =IF(K70="Milestone",0,F70-E70+1) -> 1 | E70: 46339 | F70: 46339 | G70: Not Started | H70: =IF(G70="Complete",1,IF(OR(G70="Not Started",K70="Milestone",AsOf<E70),0,MIN(0.9,MAX(0,(AsOf-E70+1)/(F70-E70+1))))) -> 0 | I70: 4.13 | J70: 4.02 | K70: Task
A71: 5.3 | B71: Upgrade SS4 (downtime Fri-Sat 13-14 Nov) | C71: SAP ECS | D71: =IF(K71="Milestone",0,F71-E71+1) -> 4 | E71: 46338 | F71: 46341 | G71: Not Started | H71: =IF(G71="Complete",1,IF(OR(G71="Not Started",K71="Milestone",AsOf<E71),0,MIN(0.9,MAX(0,(AsOf-E71+1)/(F71-E71+1))))) -> 0 | I71: 4.13 | J71: 4.03 | K71: Task
A72: 5.4 | B72: Run technical checks | C72: INTL Basis | D72: =IF(K72="Milestone",0,F72-E72+1) -> 2 | E72: 46340 | F72: 46341 | G72: Not Started | H72: =IF(G72="Complete",1,IF(OR(G72="Not Started",K72="Milestone",AsOf<E72),0,MIN(0.9,MAX(0,(AsOf-E72+1)/(F72-E72+1))))) -> 0 | I72: 5.3SS | J72: 4.04 | K72: Task
A73: 5.5 | B73: Resume and verify interfaces | C73: PwC Functional | D73: =IF(K73="Milestone",0,F73-E73+1) -> 1 | E73: 46341 | F73: 46341 | G73: Not Started | H73: =IF(G73="Complete",1,IF(OR(G73="Not Started",K73="Milestone",AsOf<E73),0,MIN(0.9,MAX(0,(AsOf-E73+1)/(F73-E73+1))))) -> 0 | I73: 5.4 | J73: 4.05 | K73: Task
A74: 5.6 | B74: Run UAT weeks 2-4 (SPS06) | C74: Business (UAT) | D74: =IF(K74="Milestone",0,F74-E74+1) -> 19 | E74: 46342 | F74: 46360 | G74: Not Started | H74: =IF(G74="Complete",1,IF(OR(G74="Not Started",K74="Milestone",AsOf<E74),0,MIN(0.9,MAX(0,(AsOf-E74+1)/(F74-E74+1))))) -> 0 | I74: 5.5 | J74: 4.06 | K74: Task
A75: 5.7 | B75: Check performance | C75: INTL Testing | D75: =IF(K75="Milestone",0,F75-E75+1) -> 3 | E75: 46342 | F75: 46344 | G75: Not Started | H75: =IF(G75="Complete",1,IF(OR(G75="Not Started",K75="Milestone",AsOf<E75),0,MIN(0.9,MAX(0,(AsOf-E75+1)/(F75-E75+1))))) -> 0 | I75: 5.5 | J75: 4.07 | K75: Task
A76: 5.8 | B76: ◆ G4 Go for production | C76: INTL PMO | D76: =IF(K76="Milestone",0,F76-E76+1) -> 0 | E76: 46345 | F76: 46345 | G76: Not Started | H76: =IF(G76="Complete",1,IF(OR(G76="Not Started",K76="Milestone",AsOf<E76),0,MIN(0.9,MAX(0,(AsOf-E76+1)/(F76-E76+1))))) -> 0 | I76: 5.4, 5.5, 5.7 | J76: G4 | K76: Milestone | L76: =IF(L$4=$E76,"◆","") | M76: =IF(M$4=$E76,"◆","") | N76: =IF(N$4=$E76,"◆","") | O76: =IF(O$4=$E76,"◆","") | P76: =IF(P$4=$E76,"◆","") | Q76: =IF(Q$4=$E76,"◆","") | R76: =IF(R$4=$E76,"◆","") | S76: =IF(S$4=$E76,"◆","") | ... CQ76: =IF(CQ$4=$E76,"◆","")
A77: 6 | B77: Production PS4 | D77: =IF(OR(E77="",F77=""),"",F77-E77+1) -> 12 | E77: =MIN(E78:E82) -> 46340 | F77: =MAX(F78:F82) -> 46351 | G77: =IF(COUNTIF(G78:G82,"Blocked")>0,"Blocked",IF(COUNTIF(G78:G82,"At Risk")>0,"At Risk",IF(COUNTIF(G78:G82,"Complete")=ROWS(G78:G82),"Complete",IF(COUNTIF(G78:G82,"Not Started")=ROWS(G78:G82),"Not Started","On Track")))) -> Not Started | H77: =IFERROR(SUMPRODUCT(D78:D82,H78:H82)/SUM(D78:D82),0) -> 0 | K77: Summary
A78: 6.1 | B78: Hold PS4 transports | C78: INTL Basis | D78: =IF(K78="Milestone",0,F78-E78+1) -> 9 | E78: 46340 | F78: 46348 | G78: Not Started | H78: =IF(G78="Complete",1,IF(OR(G78="Not Started",K78="Milestone",AsOf<E78),0,MIN(0.9,MAX(0,(AsOf-E78+1)/(F78-E78+1))))) -> 0 | I78: 5.3SS | J78: 5.01 | K78: Task
A79: 6.2 | B79: Upgrade PS4 (downtime Fri-Sat 20-21 Nov) | C79: SAP ECS | D79: =IF(K79="Milestone",0,F79-E79+1) -> 4 | E79: 46345 | F79: 46348 | G79: Not Started | H79: =IF(G79="Complete",1,IF(OR(G79="Not Started",K79="Milestone",AsOf<E79),0,MIN(0.9,MAX(0,(AsOf-E79+1)/(F79-E79+1))))) -> 0 | I79: 5.8 | J79: 5.02 | K79: Task
A80: 6.3 | B80: Run technical checks | C80: INTL Basis | D80: =IF(K80="Milestone",0,F80-E80+1) -> 3 | E80: 46347 | F80: 46349 | G80: Not Started | H80: =IF(G80="Complete",1,IF(OR(G80="Not Started",K80="Milestone",AsOf<E80),0,MIN(0.9,MAX(0,(AsOf-E80+1)/(F80-E80+1))))) -> 0 | I80: 6.2SS | J80: 5.03 | K80: Task
A81: 6.4 | B81: Verify connections | C81: INTL Basis | D81: =IF(K81="Milestone",0,F81-E81+1) -> 1 | E81: 46349 | F81: 46349 | G81: Not Started | H81: =IF(G81="Complete",1,IF(OR(G81="Not Started",K81="Milestone",AsOf<E81),0,MIN(0.9,MAX(0,(AsOf-E81+1)/(F81-E81+1))))) -> 0 | I81: 6.3 | J81: 5.04 | K81: Task
A82: 6.5 | B82: ◆ G5 Upgrade closed | C82: INTL PMO | D82: =IF(K82="Milestone",0,F82-E82+1) -> 0 | E82: 46351 | F82: 46351 | G82: Not Started | H82: =IF(G82="Complete",1,IF(OR(G82="Not Started",K82="Milestone",AsOf<E82),0,MIN(0.9,MAX(0,(AsOf-E82+1)/(F82-E82+1))))) -> 0 | I82: 6.3, 6.4 | J82: G5 | K82: Milestone | L82: =IF(L$4=$E82,"◆","") | M82: =IF(M$4=$E82,"◆","") | N82: =IF(N$4=$E82,"◆","") | O82: =IF(O$4=$E82,"◆","") | P82: =IF(P$4=$E82,"◆","") | Q82: =IF(Q$4=$E82,"◆","") | R82: =IF(R$4=$E82,"◆","") | S82: =IF(S$4=$E82,"◆","") | ... CQ82: =IF(CQ$4=$E82,"◆","")
A83: 7 | B83: N+1 DS5 / QS5 | D83: =IF(OR(E83="",F83=""),"",F83-E83+1) -> 4 | E83: =MIN(E84:E86) -> 46357 | F83: =MAX(F84:F86) -> 46360 | G83: =IF(COUNTIF(G84:G86,"Blocked")>0,"Blocked",IF(COUNTIF(G84:G86,"At Risk")>0,"At Risk",IF(COUNTIF(G84:G86,"Complete")=ROWS(G84:G86),"Complete",IF(COUNTIF(G84:G86,"Not Started")=ROWS(G84:G86),"Not Started","On Track")))) -> Not Started | H83: =IFERROR(SUMPRODUCT(D84:D86,H84:H86)/SUM(D84:D86),0) -> 0 | K83: Summary
A84: 7.1 | B84: Upgrade DS5 | C84: SAP ECS | D84: =IF(K84="Milestone",0,F84-E84+1) -> 1 | E84: 46357 | F84: 46357 | G84: Not Started | H84: =IF(G84="Complete",1,IF(OR(G84="Not Started",K84="Milestone",AsOf<E84),0,MIN(0.9,MAX(0,(AsOf-E84+1)/(F84-E84+1))))) -> 0 | I84: 5.8 | J84: 6.01 | K84: Task
A85: 7.2 | B85: Upgrade QS5 | C85: SAP ECS | D85: =IF(K85="Milestone",0,F85-E85+1) -> 1 | E85: 46359 | F85: 46359 | G85: Not Started | H85: =IF(G85="Complete",1,IF(OR(G85="Not Started",K85="Milestone",AsOf<E85),0,MIN(0.9,MAX(0,(AsOf-E85+1)/(F85-E85+1))))) -> 0 | I85: 7.1 | J85: 6.02 | K85: Task
A86: 7.3 | B86: Retrofit and reconnect N+1 | C86: INTL Basis | D86: =IF(K86="Milestone",0,F86-E86+1) -> 4 | E86: 46357 | F86: 46360 | G86: Not Started | H86: =IF(G86="Complete",1,IF(OR(G86="Not Started",K86="Milestone",AsOf<E86),0,MIN(0.9,MAX(0,(AsOf-E86+1)/(F86-E86+1))))) -> 0 | I86: 7.1 | J86: 6.03 | K86: Task
A87: 8 | B87: Close-out | D87: =IF(OR(E87="",F87=""),"",F87-E87+1) -> 40 | E87: =MIN(E88:E92) -> 46349 | F87: =MAX(F88:F92) -> 46388 | G87: =IF(COUNTIF(G88:G92,"Blocked")>0,"Blocked",IF(COUNTIF(G88:G92,"At Risk")>0,"At Risk",IF(COUNTIF(G88:G92,"Complete")=ROWS(G88:G92),"Complete",IF(COUNTIF(G88:G92,"Not Started")=ROWS(G88:G92),"Not Started","On Track")))) -> Not Started | H87: =IFERROR(SUMPRODUCT(D88:D92,H88:H92)/SUM(D88:D92),0) -> 0 | K87: Summary
A88: 8.1 | B88: Confirm data migrations finished (SDMI) | C88: INTL Basis | D88: =IF(K88="Milestone",0,F88-E88+1) -> 12 | E88: 46349 | F88: 46360 | G88: Not Started | H88: =IF(G88="Complete",1,IF(OR(G88="Not Started",K88="Milestone",AsOf<E88),0,MIN(0.9,MAX(0,(AsOf-E88+1)/(F88-E88+1))))) -> 0 | I88: 6.2 | J88: 7.03 | K88: Task
A89: 8.2 | B89: Close out the upgrade | C89: INTL Basis | D89: =IF(K89="Milestone",0,F89-E89+1) -> 5 | E89: 46356 | F89: 46360 | G89: Not Started | H89: =IF(G89="Complete",1,IF(OR(G89="Not Started",K89="Milestone",AsOf<E89),0,MIN(0.9,MAX(0,(AsOf-E89+1)/(F89-E89+1))))) -> 0 | I89: 6.5 | J89: 7.04 | K89: Task
A90: 8.3 | B90: Watch new side-effect notes weekly | C90: PwC Tech | D90: =IF(K90="Milestone",0,F90-E90+1) -> 40 | E90: 46349 | F90: 46388 | G90: Not Started | H90: =IF(G90="Complete",1,IF(OR(G90="Not Started",K90="Milestone",AsOf<E90),0,MIN(0.9,MAX(0,(AsOf-E90+1)/(F90-E90+1))))) -> 0 | I90: 6.3 | J90: 7.01 | K90: Task
A91: 8.4 | B91: Support cutover on SPS06 | C91: INTL PMO | D91: =IF(K91="Milestone",0,F91-E91+1) -> 25 | E91: 46363 | F91: 46387 | G91: Not Started | H91: =IF(G91="Complete",1,IF(OR(G91="Not Started",K91="Milestone",AsOf<E91),0,MIN(0.9,MAX(0,(AsOf-E91+1)/(F91-E91+1))))) -> 0 | I91: 6.5 | J91: 7.02 | K91: Task
A92: 8.5 | B92: Decide obsolete-data handling | C92: INTL Basis | D92: =IF(K92="Milestone",0,F92-E92+1) -> 1 | E92: 46388 | F92: 46388 | G92: Not Started | H92: =IF(G92="Complete",1,IF(OR(G92="Not Started",K92="Milestone",AsOf<E92),0,MIN(0.9,MAX(0,(AsOf-E92+1)/(F92-E92+1))))) -> 0 | J92: 7.05 | K92: Task
B94: How to read the bars
B95: Phase
B96: Complete
B97: In progress: elapsed
B98: In progress: remaining
B99: Planned
B100: At risk
B101: Blocked
...

Sheet Exec Summary
A1: Executive summary
A2: Edit the yellow cells daily, save, then load this file in the dashboard ("Update data"). The dashboard headline comes from here.
A4: Item | B4: Value
A5: As of | B5: 46313
A6: Overall status | B6: On Track
A7: Headline | B7: Sandbox preparation is completing on plan. XS4 is copied from DS4 on Wed 21 - Thu 22 Oct and upgraded on Sat 24 Oct.
A8: Key message 1 | B8: Done: SAP Notes in DS4, ECS copy request raised, Maintenance Planner plans for every system.
A9: Key message 2 | B9: PwC Tech team aligned; PwC Functional team reviewing the plan before Steering on Tue 20 Oct.
A10: Key message 3 | B10: Production upgrade Sat 21 Nov, before cutover (7 Dec) and go-live (1 Jan 2027).
A11: History note | B11: Thu 15 Oct: approach changed - the Sandbox (XS4) is rebuilt as a copy of DS4 before its upgrade.
A12: Project | B12: Project NorthStar
A13: Upgrade | B13: SAP S/4HANA 2023 FPS02 to SPS06 (RISE with SAP, Private Cloud)
A14: Plan version | B14: v4.0 (18 Oct 2026)
A15: Plan owner | B15: Girish Ogirala (INTL Basis)
A16: Go-live | B16: 46388
A18: Team alignment
A19: Team | B19: Plan alignment | C19: Status | D19: Next step
A20: INTL Basis | B20: Plan owner | C20: On Track | D20: SI-check in DS4 and QS4; isolation checklist; remaining ECS requests Mon 19 Oct
A21: PwC Tech | B21: Aligned | C21: On Track | D21: Custom code check (ATC) and Fiori impact from Mon 19 Oct
A22: PwC Functional | B22: Reviewing | C22: On Track | D22: Review complete Mon 19 Oct; CFIN/SLT and GTS runbooks
A23: SAP ECS | B23: Copy request raised | C23: On Track | D23: Copy DS4 to XS4 Wed 21 - Thu 22 Oct; XS4 upgrade Sat 24 Oct
A25: Asks of leadership
A26: Ask | B26: Detail | C26: By | D26: From
A27: Approve the upgrade plan | B27: Copy approach, five weekend upgrade windows (24 Oct - 21 Nov), gates G0-G5, Plan B/C | C27: 46315 | D27: Steering
A28: Confirm weekend cover | B28: SAP MaxAttention, ECS and the on-call rota for the weekends 24 Oct - 22 Nov | C28: 46317 | D28: Steering / INTL Basis
A30: Plan numbers (calculated from Schedule)
A31: Tasks and gates | B31: =COUNTIFS(Schedule!$K$5:$K$300,"<>Summary",Schedule!$K$5:$K$300,"<>") -> 79
A32: Complete | B32: =COUNTIFS(Schedule!$K$5:$K$300,"<>Summary",Schedule!$G$5:$G$300,"Complete") -> 8
A33: On Track | B33: =COUNTIFS(Schedule!$K$5:$K$300,"<>Summary",Schedule!$G$5:$G$300,"On Track") -> 2
A34: Not Started | B34: =COUNTIFS(Schedule!$K$5:$K$300,"<>Summary",Schedule!$G$5:$G$300,"Not Started") -> 69
A35: At Risk | B35: =COUNTIFS(Schedule!$K$5:$K$300,"<>Summary",Schedule!$G$5:$G$300,"At Risk") -> 0
A36: Blocked | B36: =COUNTIFS(Schedule!$K$5:$K$300,"<>Summary",Schedule!$G$5:$G$300,"Blocked") -> 0
A37: Overdue | B37: =SUMPRODUCT((Schedule!$K$5:$K$300<>"Summary")*(Schedule!$K$5:$K$300<>"")*(Schedule!$G$5:$G$300<>"Complete")*(Schedule!$F$5:$F$300<AsOf)) -> 0
A38: Next gate date | B38: =_xlfn.MINIFS(Schedule!$E$5:$E$300,Schedule!$K$5:$K$300,"Milestone",Schedule!$G$5:$G$300,"<>Complete",Schedule!$E$5:$E$300,">="&AsOf) -> 46317
A39: Next gate | B39: =IFERROR(INDEX(Schedule!$B$5:$B$300,MATCH(1,INDEX((Schedule!$E$5:$E$300=B38)*(Schedule!$K$5:$K$300="Milestone"),0),0)),"") -> ◆ G0 Ready for Sandbox

Sheet Milestones
A1: Milestones and gates
A2: Gate and upgrade rows take their status from the Schedule (column H). Project rows are context from the Plan on a Page.
A4: ID | B4: Date | C4: Milestone | D4: Type | E4: Criteria / notes | F4: Decision owner | G4: Status | H4: Schedule ID
A5: G0 | B5: 46317 | C5: Ready for Sandbox | D5: Gate | E5: Notes 2399707/2502552 in DS4 and transported; SI-check RC < 8 in DS4 and QS4; SRs accepted with windows; MPID per system; copy isolation checklist signed | F5: INTL PMO (Steering) | G5: =IFERROR(INDEX(Schedule!$G$5:$G$300,MATCH($H5,Schedule!$A$5:$A$300,0)),"Not Started") -> Not Started | H5: 1.19
A6: XS4 | B6: 46319 | C6: Sandbox XS4 on SPS06 | D6: Upgrade | E6: Downtime Sat 24 Oct, Sun 25 contingency | F6: SAP ECS / INTL Basis | G6: =IFERROR(INDEX(Schedule!$G$5:$G$300,MATCH($H6,Schedule!$A$5:$A$300,0)),"Not Started") -> Not Started | H6: 2.4
A7: G1 | B7: 46324 | C7: Sandbox sign-off | D7: Gate | E7: XS4 upgrade clean; Sandbox Test Plan "Yes" items passed; SPDD/SPAU and note effort sized; downtime measured; vendor answers received or tracked | F7: INTL PMO (Steering) | G7: =IFERROR(INDEX(Schedule!$G$5:$G$300,MATCH($H7,Schedule!$A$5:$A$300,0)),"Not Started") -> Not Started | H7: 2.11
A8: DS4 | B8: 46326 | C8: Development DS4 on SPS06 | D8: Upgrade | E8: Downtime Sat 31 Oct, Sun 1 Nov contingency; DS5 live as temporary Dev | F8: SAP ECS / INTL Basis | G8: =IFERROR(INDEX(Schedule!$G$5:$G$300,MATCH($H8,Schedule!$A$5:$A$300,0)),"Not Started") -> Not Started | H8: 3.4
A9: G2 | B9: 46330 | C9: Dev ready | D9: Gate | E9: SPDD/SPAU, note and role transports released; no blocking unit-test failure; zero priority-1 ATC findings | F9: INTL PMO (Steering) | G9: =IFERROR(INDEX(Schedule!$G$5:$G$300,MATCH($H9,Schedule!$A$5:$A$300,0)),"Not Started") -> Not Started | H9: 3.11
A10: SIT2 | B10: 46332 | C10: SIT2 ends (QS4-200) | D10: Project | E10: Plan on a Page | F10: Project | G10: Not Started | H10: -
A11: QS4 | B11: 46333 | C11: QA QS4 on SPS06 | D11: Upgrade | E11: Downtime Sat 7 Nov, Sun 8 contingency | F11: SAP ECS / INTL Basis | G11: =IFERROR(INDEX(Schedule!$G$5:$G$300,MATCH($H11,Schedule!$A$5:$A$300,0)),"Not Started") -> Not Started | H11: 4.5
A12: G3 | B12: 46338 | C12: Go for pre-production | D12: Gate | E12: P1 re-run >= 95% pass; zero open Sev1/Sev2 upgrade defects; CFIN, GTS, BTP integrations green; security passed; migration objects load on SPS06 | F12: INTL PMO (Steering) | G12: =IFERROR(INDEX(Schedule!$G$5:$G$300,MATCH($H12,Schedule!$A$5:$A$300,0)),"Not Started") -> Not Started | H12: 4.13
A13: SS4 | B13: 46340 | C13: Pre-production SS4 on SPS06 | D13: Upgrade | E13: Downtime Fri night 13 - Sat 14 Nov, Sun 15 contingency | F13: SAP ECS / INTL Basis | G13: =IFERROR(INDEX(Schedule!$G$5:$G$300,MATCH($H13,Schedule!$A$5:$A$300,0)),"Not Started") -> Not Started | H13: 5.3
A14: G4 | B14: 46345 | C14: Go for production | D14: Gate | E14: SS4 stable; UAT running on SPS06 without upgrade blockers; performance delta acceptable; legacy end-to-end OK | F14: INTL PMO (Steering) | G14: =IFERROR(INDEX(Schedule!$G$5:$G$300,MATCH($H14,Schedule!$A$5:$A$300,0)),"Not Started") -> Not Started | H14: 5.8
A15: PS4 | B15: 46347 | C15: Production PS4 on SPS06 | D15: Upgrade | E15: Downtime Fri night 20 - Sat 21 Nov, Sun 22 contingency | F15: SAP ECS / INTL Basis | G15: =IFERROR(INDEX(Schedule!$G$5:$G$300,MATCH($H15,Schedule!$A$5:$A$300,0)),"Not Started") -> Not Started | H15: 6.2
A16: G5 | B16: 46351 | C16: Upgrade closed | D16: Gate | E16: PS4 technical verification signed; UAT clean on SPS06; open items handed to Go/No-Go | F16: INTL PMO -> Go/No-Go board | G16: =IFERROR(INDEX(Schedule!$G$5:$G$300,MATCH($H16,Schedule!$A$5:$A$300,0)),"Not Started") -> Not Started | H16: 6.5
A17: GNG | B17: 46356 | C17: Go / No-Go (30 Nov - 4 Dec) | D17: Project | E17: Plan on a Page (at UAT end) | F17: Project | G17: Not Started | H17: -
A18: N+1 | B18: 46359 | C18: DS5 / QS5 on SPS06 | D18: Upgrade | E18: DS5 Tue 1 Dec, QS5 Thu 3 Dec | F18: SAP ECS / INTL Basis | G18: =IFERROR(INDEX(Schedule!$G$5:$G$300,MATCH($H18,Schedule!$A$5:$A$300,0)),"Not Started") -> Not Started | H18: 7.2
A19: CUT | B19: 46363 | C19: Cutover starts (7 - 31 Dec) | D19: Project | E19: Plan on a Page | F19: Project | G19: Not Started | H19: -
A20: GL | B20: 46388 | C20: Go-live | D20: Project | E20: Plan on a Page | F20: Project | G20: Not Started | H20: -
A22: Plan B | C22: Plan B (ECS cannot meet a window, or G1 fails): shift the chain by one week - XS4 31 Oct, DS4 7 Nov (after SIT2, so DS5 is not needed for SIT2 fixes), QS4 14 Nov, SS4 21 Nov, PS4 28 Nov (Thanksgiving weekend). G5 moves to Wed 2 Dec, inside the Go/No-Go week; UAT weeks 1-2 run on FPS02 and weeks 3-4 on SPS06.
A23: Plan C | C23: Plan C (G3 fails): SS4 and PS4 stay on FPS02 and go live on FPS02. DS5 and QS5 (FPS02 copies) become the delivery line for fixes to SS4 and PS4; DS4 and QS4 stay on SPS06 as the post-go-live upgrade line. Remaining systems are upgraded after hypercare.

Sheet Detail Plan
A1: Detail plan
A2: Reference detail behind each Schedule row. Status follows the Schedule (column B = Schedule ID). R = Responsible, A = Accountable, C = Consulted. Days = calendar days.
A4: ID | B4: Schedule ID | C4: Phase | D4: Workstream | E4: Task | F4: System(s) | G4: Start | H4: End | I4: Responsible | J4: Accountable | K4: Consulted | L4: Depends on | M4: Deliverable / exit | N4: Source | O4: Status | P4: Notes | Q4: Days | R4: Overdue | S4: BPMN node
A5: H.1 | B5: 0.2 | C5: P0 Prepare Sandbox & prerequisites | D5: TEC - Technical upgrade (Basis / ECS) | E5: Maintenance Planner transaction 1002693650 for XS4 (target SAP S/4HANA 2023 SPS06, SUM 2.0 SP26) | F5: XS4 | G5: 46298 | H5: 46299 | I5: INTL Basis | J5: INTL Basis | K5: SAP ECS | L5: - | M5: Stack file attached to SR 31018471 | N5: MP plan.pdf | O5: =IFERROR(INDEX(Schedule!$G$5:$G$300,MATCH($B5,Schedule!$A$5:$A$300,0)),"Not Started") -> Complete | P5: Plan status Completed; created 3 Oct, modified 4 Oct 2026 | Q5: =IF(AND(ISNUMBER(G5),ISNUMBER(H5)),H5-G5+1,"") -> 2 | R5: =IF(AND(ISNUMBER(H5),O5<>"Complete",H5<AsOf),"Overdue","") | S5: -
A6: H.2 | B6: 0.2 | C6: P0 Prepare Sandbox & prerequisites | D6: TEC - Technical upgrade (Basis / ECS) | E6: SR 31018471 raised: Update Software Version of Application (BASIC_1.5.09), XS4, window 9 Oct 02:45-10:45 UTC | F6: XS4 | G6: 46298 | H6: 46298 | I6: INTL Basis | J6: INTL Basis | K6: SAP ECS | L6: - | M6: SR validated by ECS 5 Oct | N6: SR log | O6: =IFERROR(INDEX(Schedule!$G$5:$G$300,MATCH($B6,Schedule!$A$5:$A$300,0)),"Not Started") -> Complete | P6: SAP for Me also shows Request ID 31018481 for this SR | Q6: =IF(AND(ISNUMBER(G6),ISNUMBER(H6)),H6-G6+1,"") -> 1 | R6: =IF(AND(ISNUMBER(H6),O6<>"Complete",H6<AsOf),"Overdue","") | S6: -
A7: H.3 | B7: 0.3 | C7: P0 Prepare Sandbox & prerequisites | D7: TEC - Technical upgrade (Basis / ECS) | E7: First XS4 update run (SR 31018471) paused at Configuration (12%) by the SI-check: latest version of SAP Note 2502552 needed first; ECS reset SUM on 14 Oct | F7: XS4 | G7: 46302 | H7: 46309 | I7: SAP ECS | J7: INTL Basis | K7: INTL Basis | L7: H.2 | M7: SUM reset; SR 31018471 kept for the rerun after the copy (1.03) | N7: SR log | O7: =IFERROR(INDEX(Schedule!$G$5:$G$300,MATCH($B7,Schedule!$A$5:$A$300,0)),"Not Started") -> Complete | P7: Lesson applied: notes go into DS4 first (0.02), then XS4 is copied from DS4 (H.5) | Q7: =IF(AND(ISNUMBER(G7),ISNUMBER(H7)),H7-G7+1,"") -> 8 | R7: =IF(AND(ISNUMBER(H7),O7<>"Complete",H7<AsOf),"Overdue","") | S7: -
A8: H.4 | B8: 0.1 | C8: P0 Prepare Sandbox & prerequisites | D8: CODE - Custom code, notes, SPDD/SPAU | E8: Side-effect report for MP 1002693650 triaged: 135 in-scope notes (2 HotNews: 3777415, 3563542), 178 conditional | F8: All | G8: 46297 | H8: 46301 | I8: PwC Technical | J8: INTL Basis | K8: PwC Functional | L8: - | M8: SAP_Notes_Side_Effect_Register_SPS06.xlsx | N8: SER | O8: =IFERROR(INDEX(Schedule!$G$5:$G$300,MATCH($B8,Schedule!$A$5:$A$300,0)),"Not Started") -> Complete | P8: Register delivered 6 Oct | Q8: =IF(AND(ISNUMBER(G8),ISNUMBER(H8)),H8-G8+1,"") -> 5 | R8: =IF(AND(ISNUMBER(H8),O8<>"Complete",H8<AsOf),"Overdue","") | S8: -
A9: H.5 | B9: 0.4 | C9: P0 Prepare Sandbox & prerequisites | D9: GOV - Governance & SAP engagement | E9: Approach changed: rebuild the Sandbox XS4 as a copy of DS4, then rerun SUM, so the rehearsal runs on Development code and configuration (decision D1) | F9: DS4 > XS4 | G9: 46310 | H9: 46310 | I9: INTL Basis | J9: INTL Basis | K9: PwC Technical; SAP ECS | L9: H.3 | M9: Sandbox preparation started | N9: USER | O9: =IFERROR(INDEX(Schedule!$G$5:$G$300,MATCH($B9,Schedule!$A$5:$A$300,0)),"Not Started") -> Complete | P9: Sandbox preparation runs from Thu 15 Oct | Q9: =IF(AND(ISNUMBER(G9),ISNUMBER(H9)),H9-G9+1,"") -> 1 | R9: =IF(AND(ISNUMBER(H9),O9<>"Complete",H9<AsOf),"Overdue","") | S9: -
A10: 0.01a | B10: 1.1 | C10: P0 Prepare Sandbox & prerequisites | D10: GOV - Governance & SAP engagement | E10: Align the upgrade plan with the PwC Technical team (copy strategy, SPDD/SPAU, notes, ATC, weekend windows) | F10: - | G10: 46310 | H10: 46311 | I10: INTL Basis | J10: INTL Basis | K10: PwC Technical | L10: H.5 | M10: PwC Technical aligned | N10: USER | O10: =IFERROR(INDEX(Schedule!$G$5:$G$300,MATCH($B10,Schedule!$A$5:$A$300,0)),"Not Started") -> Complete | P10: PwC Technical team aligned (USER, 18 Oct) | Q10: =IF(AND(ISNUMBER(G10),ISNUMBER(H10)),H10-G10+1,"") -> 2 | R10: =IF(AND(ISNUMBER(H10),O10<>"Complete",H10<AsOf),"Overdue","") | S10: -
A11: 0.01b | B11: 1.2 | C11: P0 Prepare Sandbox & prerequisites | D11: GOV - Governance & SAP engagement | E11: PwC Functional teams review the plan: stream impacts, regression scope, CFIN/SLT and GTS runbooks, Sandbox test plan | F11: - | G11: 46311 | H11: 46314 | I11: PwC Functional | J11: INTL Basis | K11: PwC Technical; INTL Test Lead | L11: 0.01a | M11: Review comments closed | N11: USER | O11: =IFERROR(INDEX(Schedule!$G$5:$G$300,MATCH($B11,Schedule!$A$5:$A$300,0)),"Not Started") -> On Track | P11: Review in progress (USER, 18 Oct) | Q11: =IF(AND(ISNUMBER(G11),ISNUMBER(H11)),H11-G11+1,"") -> 4 | R11: =IF(AND(ISNUMBER(H11),O11<>"Complete",H11<AsOf),"Overdue","") | S11: -
A12: 0.01 | B12: 1.7 | C12: P0 Prepare Sandbox & prerequisites | D12: GOV - Governance & SAP engagement | E12: Approve plan v4 at Steering: copy strategy (XS4, DS5, QS5), weekend windows, gates G0-G5, Plan B/C | F12: - | G12: 46315 | H12: 46315 | I12: INTL Basis | J12: INTL PMO | K12: PwC Technical; PwC Functional | L12: 0.01b | M12: Plan v4 baselined; owners named | N12: USER | O12: =IFERROR(INDEX(Schedule!$G$5:$G$300,MATCH($B12,Schedule!$A$5:$A$300,0)),"Not Started") -> Not Started | Q12: =IF(AND(ISNUMBER(G12),ISNUMBER(H12)),H12-G12+1,"") -> 1 | R12: =IF(AND(ISNUMBER(H12),O12<>"Complete",H12<AsOf),"Overdue","") | S12: -
A13: 0.02 | B13: 1.3 | C13: P0 Prepare Sandbox & prerequisites | D13: TEC - Technical upgrade (Basis / ECS) | E13: Implement the latest versions of SAP Notes 2399707 and 2502552 (TCI) in DS4; release the transport to QS4, SS4, PS4 before each SUM. Check the number: 2502552 (the 12 Oct attempt used 2502662) | F13: DS4 > QS4/SS4/PS4 | G13: 46310 | H13: 46311 | I13: INTL Basis | J13: INTL Basis | K13: PwC Technical | L13: H.5 | M13: Notes at latest version in DS4; transport in import queues | N13: UG 2.1, 4.4; SR log | O13: =IFERROR(INDEX(Schedule!$G$5:$G$300,MATCH($B13,Schedule!$A$5:$A$300,0)),"Not Started") -> Complete | P13: UG 2.1: a shared transport must be imported into the next system before its upgrade starts | Q13: =IF(AND(ISNUMBER(G13),ISNUMBER(H13)),H13-G13+1,"") -> 2 | R13: =IF(AND(ISNUMBER(H13),O13<>"Complete",H13<AsOf),"Overdue","") | S13: 1, C2
A14: 0.03 | B14: 1.6 | C14: P0 Prepare Sandbox & prerequisites | D14: TEC - Technical upgrade (Basis / ECS) | E14: Run SI-check /SDF/RC_START_CHECK (target 2023 SPS06) with "Check Consistency for All" in DS4 and QS4; fix RC 8/12; record RC 7 exemptions | F14: DS4, QS4 | G14: 46311 | H14: 46316 | I14: INTL Basis | J14: INTL Basis | K14: PwC Functional | L14: 0.02 | M14: No RC >= 8 open; exemption log | N14: UG 4.4 | O14: =IFERROR(INDEX(Schedule!$G$5:$G$300,MATCH($B14,Schedule!$A$5:$A$300,0)),"Not Started") -> On Track | P14: SUM stops at start on RC 12 and before downtime on RC >= 8 | Q14: =IF(AND(ISNUMBER(G14),ISNUMBER(H14)),H14-G14+1,"") -> 6 | R14: =IF(AND(ISNUMBER(H14),O14<>"Complete",H14<AsOf),"Overdue","") | S14: 1, C2
A15: 0.04a | B15: 1.4 | C15: P0 Prepare Sandbox & prerequisites | D15: GOV - Governance & SAP engagement | E15: Raise the ECS SR for the system copy DS4 > XS4 (copy Wed 21 - Thu 22 Oct) | F15: DS4 > XS4 | G15: 46310 | H15: 46311 | I15: INTL Basis | J15: INTL Basis | K15: SAP ECS | L15: H.5 | M15: Copy SR raised (number in SR Tracker) | N15: USER | O15: =IFERROR(INDEX(Schedule!$G$5:$G$300,MATCH($B15,Schedule!$A$5:$A$300,0)),"Not Started") -> Complete | P15: Raised (USER, 18 Oct) | Q15: =IF(AND(ISNUMBER(G15),ISNUMBER(H15)),H15-G15+1,"") -> 2 | R15: =IF(AND(ISNUMBER(H15),O15<>"Complete",H15<AsOf),"Overdue","") | S15: -
A16: 0.04 | B16: 1.8 | C16: P0 Prepare Sandbox & prerequisites | D16: GOV - Governance & SAP engagement | E16: Raise the remaining ECS SRs with weekend windows: copies DS4>DS5, QS4>QS5; updates DS4, QS4, SS4, PS4, DS5, QS5 (see SR Tracker); request uptime start time explicitly | F16: All | G16: 46314 | H16: 46314 | I16: INTL Basis | J16: INTL Basis | K16: SAP ECS; INTL PMO | L16: 0.05 | M16: SR numbers and confirmed windows in SR Tracker | N16: UG 5; SR log | O16: =IFERROR(INDEX(Schedule!$G$5:$G$300,MATCH($B16,Schedule!$A$5:$A$300,0)),"Not Started") -> Not Started | P16: ECS validated SR 31018471 within 2 days and preparation started 36 h before downtime | Q16: =IF(AND(ISNUMBER(G16),ISNUMBER(H16)),H16-G16+1,"") -> 1 | R16: =IF(AND(ISNUMBER(H16),O16<>"Complete",H16<AsOf),"Overdue","") | S16: 2, C1
A17: 0.05 | B17: 1.5 | C17: P0 Prepare Sandbox & prerequisites | D17: TEC - Technical upgrade (Basis / ECS) | E17: Maintenance Planner: one transaction per system (DS4, QS4, SS4, PS4, DS5, QS5) with the same target stack as 1002693650; attach each MPID to its SR | F17: All | G17: 46310 | H17: 46311 | I17: INTL Basis | J17: INTL Basis | K17: SAP ECS | L17: - | M17: MPID per system; identical target levels | N17: UG 4.2; MP | O17: =IFERROR(INDEX(Schedule!$G$5:$G$300,MATCH($B17,Schedule!$A$5:$A$300,0)),"Not Started") -> Complete | P17: Created (USER, 18 Oct); MP 1002693650 covered XS4 only | Q17: =IF(AND(ISNUMBER(G17),ISNUMBER(H17)),H17-G17+1,"") -> 2 | R17: =IF(AND(ISNUMBER(H17),O17<>"Complete",H17<AsOf),"Overdue","") | S17: 2
A18: 0.06 | B18: 1.8 | C18: P0 Prepare Sandbox & prerequisites | D18: TEC - Technical upgrade (Basis / ECS) | E18: Ask ECS: are HANA 2.00.089.5 (SPS08) and kernel 916 (in the MP download list) applied inside each SUM window, or do they need DB/OS SRs (DB_1.1.11/12, INFRA_1.6.12) with separate downtime? | F18: All | G18: 46314 | H18: 46316 | I18: INTL Basis | J18: INTL Basis | K18: SAP ECS | L18: - | M18: Written ECS answer; windows adjusted if needed | N18: UG 4.3; MP download list | O18: =IFERROR(INDEX(Schedule!$G$5:$G$300,MATCH($B18,Schedule!$A$5:$A$300,0)),"Not Started") -> Not Started | P18: UG 4.3: OS and DB patching need a separate downtime | Q18: =IF(AND(ISNUMBER(G18),ISNUMBER(H18)),H18-G18+1,"") -> 3 | R18: =IF(AND(ISNUMBER(H18),O18<>"Complete",H18<AsOf),"Overdue","") | S18: 2, 9
A19: 0.07 | B19: 1.10 | C19: P0 Prepare Sandbox & prerequisites | D19: GOV - Governance & SAP engagement | E19: SAP MaxAttention: plan safeguarding review, SI-check and side-effect review, escalation path and weekend coverage for 24 Oct - 22 Nov | F19: - | G19: 46314 | H19: 46318 | I19: INTL Basis | J19: INTL Basis | K19: SAP MaxAttention | L19: 0.01b | M19: Review notes; named contacts per weekend | N19: USER | O19: =IFERROR(INDEX(Schedule!$G$5:$G$300,MATCH($B19,Schedule!$A$5:$A$300,0)),"Not Started") -> Not Started | Q19: =IF(AND(ISNUMBER(G19),ISNUMBER(H19)),H19-G19+1,"") -> 5 | R19: =IF(AND(ISNUMBER(H19),O19<>"Complete",H19<AsOf),"Overdue","") | S19: -
A20: 0.08 | B20: 1.10 | C20: P0 Prepare Sandbox & prerequisites | D20: GOV - Governance & SAP engagement | E20: SAP BTP team: confirm actions for AFC, MBC, DRC (Mexico) and Work Zone around each S/4 window; tenant maintenance dates; copies stay disconnected | F20: - | G20: 46314 | H20: 46318 | I20: INTL Basis | J20: INTL Basis | K20: SAP BTP team; PwC Functional | L20: 0.01b | M20: BTP checklist per window | N20: USER | O20: =IFERROR(INDEX(Schedule!$G$5:$G$300,MATCH($B20,Schedule!$A$5:$A$300,0)),"Not Started") -> Not Started | Q20: =IF(AND(ISNUMBER(G20),ISNUMBER(H20)),H20-G20+1,"") -> 5 | R20: =IF(AND(ISNUMBER(H20),O20<>"Complete",H20<AsOf),"Overdue","") | S20: -
A21: 0.09 | B21: 1.10 | C21: P0 Prepare Sandbox & prerequisites | D21: GOV - Governance & SAP engagement | E21: Incident and escalation protocol: SAP for Me priorities, ECS SR contacts, weekend on-call rota (Basis onsite/offshore, PwC, ECS, MaxAttention) | F21: - | G21: 46314 | H21: 46316 | I21: INTL Basis | J21: INTL Basis | K21: INTL PMO; SAP MaxAttention | L21: - | M21: Rota and contact sheet published | N21: USER | O21: =IFERROR(INDEX(Schedule!$G$5:$G$300,MATCH($B21,Schedule!$A$5:$A$300,0)),"Not Started") -> Not Started | P21: Five consecutive weekend windows (24 Oct - 22 Nov) | Q21: =IF(AND(ISNUMBER(G21),ISNUMBER(H21)),H21-G21+1,"") -> 3 | R21: =IF(AND(ISNUMBER(H21),O21<>"Complete",H21<AsOf),"Overdue","") | S21: -
A22: 0.10 | B22: 1.9 | C22: P0 Prepare Sandbox & prerequisites | D22: GOV - Governance & SAP engagement | E22: Copy isolation checklist for XS4, DS5, QS5: GTS, SLT/CFIN, AFC, MBC/banks, DRC/PAC, Work Zone, Ariba, OneSource, OpenText, SailPoint, Syniti, e-mail, printers, jobs | F22: XS4, DS5, QS5 | G22: 46314 | H22: 46316 | I22: INTL Basis | J22: INTL Basis | K22: PwC Functional; PwC Data Migration; INTL SAP Security | L22: - | M22: Checklist with owner per connection | N22: USER | O22: =IFERROR(INDEX(Schedule!$G$5:$G$300,MATCH($B22,Schedule!$A$5:$A$300,0)),"Not Started") -> Not Started | P22: A copy keeps every RFC, port, certificate and job of its source | Q22: =IF(AND(ISNUMBER(G22),ISNUMBER(H22)),H22-G22+1,"") -> 3 | R22: =IF(AND(ISNUMBER(H22),O22<>"Complete",H22<AsOf),"Overdue","") | S22: 4
A23: 0.11 | B23: 1.11 | C23: P0 Prepare Sandbox & prerequisites | D23: GOV - Governance & SAP engagement | E23: Vendor outreach: send the e-mails in "Vendor Questions" (OpenText, Thomson Reuters, SailPoint, Syniti); answers due Wed 28 Oct | F23: - | G23: 46314 | H23: 46323 | I23: INTL Basis | J23: INTL Basis | K23: PwC Functional; PwC Data Migration; Partner vendors | L23: - | M23: Written answers filed | N23: UG 4.2 | O23: =IFERROR(INDEX(Schedule!$G$5:$G$300,MATCH($B23,Schedule!$A$5:$A$300,0)),"Not Started") -> Not Started | P23: UG 4.2: checking third-party add-ons with their vendors is the customer's responsibility | Q23: =IF(AND(ISNUMBER(G23),ISNUMBER(H23)),H23-G23+1,"") -> 10 | R23: =IF(AND(ISNUMBER(H23),O23<>"Complete",H23<AsOf),"Overdue","") | S23: 3
A24: 0.12 | B24: 1.17 | C24: P0 Prepare Sandbox & prerequisites | D24: GOV - Governance & SAP engagement | E24: Publish transport windows A-E and the DS5 dual-maintenance rule; defect tag UPG-SPS06 in qTest/ADO | F24: All | G24: 46316 | H24: 46318 | I24: INTL Basis | J24: INTL PMO | K24: PwC Technical; INTL Test Lead | L24: 0.01 | M24: Rules briefed to developers and testers | N24: UG 3.1 | O24: =IFERROR(INDEX(Schedule!$G$5:$G$300,MATCH($B24,Schedule!$A$5:$A$300,0)),"Not Started") -> Not Started | P24: Release 2 is paused (USER), so dual maintenance covers SIT2, Mock3 and UAT fixes only | Q24: =IF(AND(ISNUMBER(G24),ISNUMBER(H24)),H24-G24+1,"") -> 3 | R24: =IF(AND(ISNUMBER(H24),O24<>"Complete",H24<AsOf),"Overdue","") | S24: 4
A25: 0.13 | B25: 1.12 | C25: P0 Prepare Sandbox & prerequisites | D25: CODE - Custom code, notes, SPDD/SPAU | E25: Confirm a customer package (Z*) exists in DS4; list objects created by manual note corrections (passive deletion risk, Note 2513585) | F25: DS4 | G25: 46314 | H25: 46317 | I25: PwC Technical | J25: PwC Technical | K25: INTL Basis | L25: - | M25: Package confirmed; objects to rescue listed | N25: UG 3.5 | O25: =IFERROR(INDEX(Schedule!$G$5:$G$300,MATCH($B25,Schedule!$A$5:$A$300,0)),"Not Started") -> Not Started | P25: Packages cannot be created during the update | Q25: =IF(AND(ISNUMBER(G25),ISNUMBER(H25)),H25-G25+1,"") -> 4 | R25: =IF(AND(ISNUMBER(H25),O25<>"Complete",H25<AsOf),"Overdue","") | S25: 5
A26: 0.14 | B26: 1.12 | C26: P0 Prepare Sandbox & prerequisites | D26: CODE - Custom code, notes, SPDD/SPAU | E26: Custom code check: import Simplification DB (CCMSIDB via SYCM, Note 2241080), ATC run with baseline against 2023 SPS06 in DS4 | F26: DS4 | G26: 46314 | H26: 46318 | I26: PwC Technical | J26: PwC Technical | K26: INTL Basis | L26: - | M26: ATC findings list; priority-1 items owned | N26: UG 4.5 | O26: =IFERROR(INDEX(Schedule!$G$5:$G$300,MATCH($B26,Schedule!$A$5:$A$300,0)),"Not Started") -> Not Started | P26: Needs SAP_SATC_ADMIN and S_YCM (UG 4.5.1.1) | Q26: =IF(AND(ISNUMBER(G26),ISNUMBER(H26)),H26-G26+1,"") -> 5 | R26: =IF(AND(ISNUMBER(H26),O26<>"Complete",H26<AsOf),"Overdue","") | S26: 5
A27: 0.15 | B27: 1.14 | C27: P0 Prepare Sandbox & prerequisites | D27: SEC - Security, GRC, SailPoint | E27: SDMI users: create via SDM_USER in every client of DS4, QS4, SS4, PS4 (Notes 2664638, 2850918), or tell ECS to create them in SUM | F27: All | G27: 46314 | H27: 46318 | I27: INTL SAP Security | J27: INTL Basis | K27: SAP ECS | L27: - | M27: SDMI user per client or SR instruction | N27: UG 6.1 | O27: =IFERROR(INDEX(Schedule!$G$5:$G$300,MATCH($B27,Schedule!$A$5:$A$300,0)),"Not Started") -> Not Started | P27: Without the user, SDMIs do not start and data is not migrated | Q27: =IF(AND(ISNUMBER(G27),ISNUMBER(H27)),H27-G27+1,"") -> 5 | R27: =IF(AND(ISNUMBER(H27),O27<>"Complete",H27<AsOf),"Overdue","") | S27: 7
A28: 0.16 | B28: 1.6 | C28: P0 Prepare Sandbox & prerequisites | D28: TEC - Technical upgrade (Basis / ECS) | E28: ODP jobs: check own variants of ODQ_CLEANUP / ODQ_DAEMON vs technical job definitions (Note 2677355) | F28: DS4, QS4 | G28: 46314 | H28: 46317 | I28: INTL Basis | J28: INTL Basis | K28: - | L28: - | M28: Decision recorded | N28: UG 4.7 | O28: =IFERROR(INDEX(Schedule!$G$5:$G$300,MATCH($B28,Schedule!$A$5:$A$300,0)),"Not Started") -> On Track | Q28: =IF(AND(ISNUMBER(G28),ISNUMBER(H28)),H28-G28+1,"") -> 4 | R28: =IF(AND(ISNUMBER(H28),O28<>"Complete",H28<AsOf),"Overdue","") | S28: -
A29: 0.17 | B29: 1.13 | C29: P0 Prepare Sandbox & prerequisites | D29: FIO - Fiori, Work Zone, SAP GUI | E29: Fiori Upgrade Impact Analysis (Fiori apps library) for apps in use: UI content moves FPS02 > FPS03 per MP; list deprecated and successor apps | F29: DS4 | G29: 46314 | H29: 46323 | I29: PwC Technical | J29: PwC Technical | K29: INTL Basis | L29: - | M29: App impact list with owner | N29: UG 3.3; MP | O29: =IFERROR(INDEX(Schedule!$G$5:$G$300,MATCH($B29,Schedule!$A$5:$A$300,0)),"Not Started") -> Not Started | P29: MP: SAP Fiori for S/4HANA 2023 02 > 03 (02/2025) FPS; FES 2023 stays 02 | Q29: =IF(AND(ISNUMBER(G29),ISNUMBER(H29)),H29-G29+1,"") -> 10 | R29: =IF(AND(ISNUMBER(H29),O29<>"Complete",H29<AsOf),"Overdue","") | S29: 6
A30: 0.18 | B30: 1.13 | C30: P0 Prepare Sandbox & prerequisites | D30: FIO - Fiori, Work Zone, SAP GUI | E30: SAP GUI: confirm the deployed GUI version supports the target (Notes 147519, 26417) | F30: - | G30: 46314 | H30: 46317 | I30: INTL Basis | J30: INTL Basis | K30: - | L30: - | M30: Confirmation | N30: UG 3.2 | O30: =IFERROR(INDEX(Schedule!$G$5:$G$300,MATCH($B30,Schedule!$A$5:$A$300,0)),"Not Started") -> Not Started | Q30: =IF(AND(ISNUMBER(G30),ISNUMBER(H30)),H30-G30+1,"") -> 4 | R30: =IF(AND(ISNUMBER(H30),O30<>"Complete",H30<AsOf),"Overdue","") | S30: 6
A31: 0.19 | B31: 1.15 | C31: P0 Prepare Sandbox & prerequisites | D31: INT - Integrations (CFIN, GTS, BTP, partners) | E31: CFIN / SLT runbook: suspend and resume replication on QL4 around QS4 and SS4 windows; QL5 repoint plan for QS5; DMIS compatibility confirmed | F31: QL4, QL5 | G31: 46314 | H31: 46323 | I31: PwC Functional | J31: PwC Functional | K31: INTL Basis; SAP MaxAttention | L31: - | M31: Runbook approved | N31: USER | O31: =IFERROR(INDEX(Schedule!$G$5:$G$300,MATCH($B31,Schedule!$A$5:$A$300,0)),"Not Started") -> Not Started | P31: QL4 = SLT for the N line, QL5 = SLT for N+1 (USER) | Q31: =IF(AND(ISNUMBER(G31),ISNUMBER(H31)),H31-G31+1,"") -> 10 | R31: =IF(AND(ISNUMBER(H31),O31<>"Complete",H31<AsOf),"Overdue","") | S31: 4
A32: 0.20 | B32: 1.15 | C32: P0 Prepare Sandbox & prerequisites | D32: INT - Integrations (CFIN, GTS, BTP, partners) | E32: GTS plan: map S/4 client to GTS client (DS4-DG4, QS4-QG4, SS4-QG4/300); plug-in regression scenarios; QG4-300 UAT pause for the SS4 window | F32: DG4, QG4 | G32: 46314 | H32: 46318 | I32: PwC Functional | J32: PwC Functional | K32: INTL Basis; INTL PO / IT Leads | L32: - | M32: GTS connection map and test list | N32: USER | O32: =IFERROR(INDEX(Schedule!$G$5:$G$300,MATCH($B32,Schedule!$A$5:$A$300,0)),"Not Started") -> Not Started | P32: GTS has no pre-production; QG4 client 300 hosts UAT (USER) | Q32: =IF(AND(ISNUMBER(G32),ISNUMBER(H32)),H32-G32+1,"") -> 5 | R32: =IF(AND(ISNUMBER(H32),O32<>"Complete",H32<AsOf),"Overdue","") | S32: 4
A33: 0.21 | B33: 1.16 | C33: P0 Prepare Sandbox & prerequisites | D33: DM - Data migration (Syniti) | E33: Mock3 protection: Mock3 (SS4-100, 19 Oct - 6 Nov) runs fully on FPS02; no SS4 refresh; Syniti connection unchanged; Mock3 fixes via DS5 after 30 Oct | F33: SS4 | G33: 46314 | H33: 46315 | I33: PwC Data Migration | J33: INTL PMO | K33: INTL Basis; Partner vendors | L33: - | M33: Mock3 change rules agreed with Syniti | N33: POAP | O33: =IFERROR(INDEX(Schedule!$G$5:$G$300,MATCH($B33,Schedule!$A$5:$A$300,0)),"Not Started") -> Not Started | P33: No change to the Mock3 environment is required for the upgrade | Q33: =IF(AND(ISNUMBER(G33),ISNUMBER(H33)),H33-G33+1,"") -> 2 | R33: =IF(AND(ISNUMBER(H33),O33<>"Complete",H33<AsOf),"Overdue","") | S33: -
A34: 0.22 | B34: 1.18 | C34: P0 Prepare Sandbox & prerequisites | D34: TST - Testing | E34: Regression set: SIT2 P1 scripts per stream tagged in qTest for the QS4 re-run; Sandbox test plan owners named | F34: - | G34: 46314 | H34: 46318 | I34: INTL Test Lead | J34: INTL Test Lead | K34: PwC Functional | L34: - | M34: Tagged P1 set; Sandbox test owners | N34: USER | O34: =IFERROR(INDEX(Schedule!$G$5:$G$300,MATCH($B34,Schedule!$A$5:$A$300,0)),"Not Started") -> Not Started | P34: No test automation (USER): all regression is manual | Q34: =IF(AND(ISNUMBER(G34),ISNUMBER(H34)),H34-G34+1,"") -> 5 | R34: =IF(AND(ISNUMBER(H34),O34<>"Complete",H34<AsOf),"Overdue","") | S34: 8
A35: G0 | B35: 1.19 | C35: P0 Prepare Sandbox & prerequisites | D35: GOV - Governance & SAP engagement | E35: GATE G0 - Ready for Sandbox: notes in DS4, SI-check clean, SRs accepted, MPIDs, isolation checklist signed | F35: - | G35: 46317 | H35: 46317 | I35: INTL PMO | J35: INTL PMO | K35: INTL Basis; PwC Technical | L35: 0.01, 0.02, 0.03, 0.04a, 0.04, 0.05, 0.06, 0.09, 0.10 | M35: Go for XS4 SUM | N35: UG 2.2 | O35: =IFERROR(INDEX(Schedule!$G$5:$G$300,MATCH($B35,Schedule!$A$5:$A$300,0)),"Not Started") -> Not Started | Q35: =IF(AND(ISNUMBER(G35),ISNUMBER(H35)),H35-G35+1,"") -> 1 | R35: =IF(AND(ISNUMBER(H35),O35<>"Complete",H35<AsOf),"Overdue","") | S35: G0
A36: 1.01 | B36: 2.1 | C36: P1 Sandbox XS4 (copy of DS4) | D36: TEC - Technical upgrade (Basis / ECS) | E36: ECS system copy DS4 > XS4 (XS4 overwritten; SR 31018471 waits for the rerun) | F36: DS4 > XS4 | G36: 46316 | H36: 46317 | I36: SAP ECS | J36: INTL Basis | K36: INTL Basis | L36: 0.02, 0.04a | M36: XS4 = DS4 code and configuration | N36: USER | O36: =IFERROR(INDEX(Schedule!$G$5:$G$300,MATCH($B36,Schedule!$A$5:$A$300,0)),"Not Started") -> Not Started | P36: Taken from a DS4 backup: no DS4 downtime expected (confirm with ECS) | Q36: =IF(AND(ISNUMBER(G36),ISNUMBER(H36)),H36-G36+1,"") -> 2 | R36: =IF(AND(ISNUMBER(H36),O36<>"Complete",H36<AsOf),"Overdue","") | S36: 10
A37: 1.02 | B37: 2.2 | C37: P1 Sandbox XS4 (copy of DS4) | D37: TEC - Technical upgrade (Basis / ECS) | E37: XS4 post-copy: BDLS, disable RFC/ports/certificates per isolation checklist, SCOT, suspend jobs (BTCTRNS1), STMS, lock users | F37: XS4 | G37: 46317 | H37: 46317 | I37: INTL Basis | J37: INTL Basis | K37: PwC Functional | L37: 1.01, 0.10 | M37: Isolation evidence | N37: USER | O37: =IFERROR(INDEX(Schedule!$G$5:$G$300,MATCH($B37,Schedule!$A$5:$A$300,0)),"Not Started") -> Not Started | Q37: =IF(AND(ISNUMBER(G37),ISNUMBER(H37)),H37-G37+1,"") -> 1 | R37: =IF(AND(ISNUMBER(H37),O37<>"Complete",H37<AsOf),"Overdue","") | S37: 10
A38: 1.03 | B38: 2.3 | C38: P1 Sandbox XS4 (copy of DS4) | D38: TEC - Technical upgrade (Basis / ECS) | E38: XS4: confirm 2399707 / 2502552 at latest version, SI-check RC < 8, check modifications (SE95) and update the SPDD/SPAU answers in SR 31018471 (were "No"); send the SR back | F38: XS4 | G38: 46317 | H38: 46317 | I38: INTL Basis | J38: INTL Basis | K38: PwC Technical | L38: 1.02 | M38: SR 31018471 back with ECS | N38: SR log; UG 3.5, 4.4 | O38: =IFERROR(INDEX(Schedule!$G$5:$G$300,MATCH($B38,Schedule!$A$5:$A$300,0)),"Not Started") -> Not Started | P38: The copy brings DS4 modifications into XS4 | Q38: =IF(AND(ISNUMBER(G38),ISNUMBER(H38)),H38-G38+1,"") -> 1 | R38: =IF(AND(ISNUMBER(H38),O38<>"Complete",H38<AsOf),"Overdue","") | S38: 11, C1, C2
A39: 1.04 | B39: 2.4 | C39: P1 Sandbox XS4 (copy of DS4) | D39: TEC - Technical upgrade (Basis / ECS) | E39: ECS SUM on XS4: uptime Thu 22 - Fri 23 Oct (dev lock set automatically); downtime Sat 24 Oct (Sun 25 contingency) | F39: XS4 | G39: 46317 | H39: 46320 | I39: SAP ECS | J39: INTL Basis | K39: INTL Basis | L39: 1.03, G0 | M39: XS4 on SPS06; runtime and downtime measured | N39: UG 5; SR log | O39: =IFERROR(INDEX(Schedule!$G$5:$G$300,MATCH($B39,Schedule!$A$5:$A$300,0)),"Not Started") -> Not Started | P39: First run planned 8 h downtime (SR window) | Q39: =IF(AND(ISNUMBER(G39),ISNUMBER(H39)),H39-G39+1,"") -> 4 | R39: =IF(AND(ISNUMBER(H39),O39<>"Complete",H39<AsOf),"Overdue","") | S39: 11, C3, C7
A40: 1.05 | B40: 2.5 | C40: P1 Sandbox XS4 (copy of DS4) | D40: CODE - Custom code, notes, SPDD/SPAU | E40: XS4 SPDD (during SUM), SPAU, then SPAU_ENH: prototype and size the DS4 adjustment | F40: XS4 | G40: 46319 | H40: 46321 | I40: PwC Technical | J40: PwC Technical | K40: INTL Basis | L40: 1.04 SS | M40: Worklist and effort for DS4 | N40: UG 3.5 | O40: =IFERROR(INDEX(Schedule!$G$5:$G$300,MATCH($B40,Schedule!$A$5:$A$300,0)),"Not Started") -> Not Started | P40: SPAU_ENH only after SPDD/SPAU (UG 3.5) | Q40: =IF(AND(ISNUMBER(G40),ISNUMBER(H40)),H40-G40+1,"") -> 3 | R40: =IF(AND(ISNUMBER(H40),O40<>"Complete",H40<AsOf),"Overdue","") | S40: 11, C5, C8
A41: 1.06 | B41: 2.6 | C41: P1 Sandbox XS4 (copy of DS4) | D41: TEC - Technical upgrade (Basis / ECS) | E41: XS4 technical checks: SICK, SM21, ST22, SM37, SM59, STMS, SMICM, SGEN, component levels vs MP, SDM_MON | F41: XS4 | G41: 46320 | H41: 46321 | I41: INTL Basis | J41: INTL Basis | K41: SAP ECS | L41: 1.04 | M41: Checklist signed | N41: UG 6.1 | O41: =IFERROR(INDEX(Schedule!$G$5:$G$300,MATCH($B41,Schedule!$A$5:$A$300,0)),"Not Started") -> Not Started | Q41: =IF(AND(ISNUMBER(G41),ISNUMBER(H41)),H41-G41+1,"") -> 2 | R41: =IF(AND(ISNUMBER(H41),O41<>"Complete",H41<AsOf),"Overdue","") | S41: 11, C9
A42: 1.07 | B42: 2.6 | C42: P1 Sandbox XS4 (copy of DS4) | D42: FIO - Fiori, Work Zone, SAP GUI | E42: XS4 Fiori follow-ups: Notes 3336823 and 2902673, /UI2/INVALIDATE_CLIENT_CACHES, /UI2/INVALIDATE_GLOBAL_CACHES, app descriptors if BEC catalogs, SICF /sap/public/bc/its | F42: XS4 | G42: 46321 | H42: 46321 | I42: INTL Basis | J42: INTL Basis | K42: PwC Technical | L42: 1.06 | M42: Launchpad and key apps load | N42: UG 6.3 | O42: =IFERROR(INDEX(Schedule!$G$5:$G$300,MATCH($B42,Schedule!$A$5:$A$300,0)),"Not Started") -> Not Started | P42: Not in the ECS standard subscription (UG 6.3) | Q42: =IF(AND(ISNUMBER(G42),ISNUMBER(H42)),H42-G42+1,"") -> 1 | R42: =IF(AND(ISNUMBER(H42),O42<>"Complete",H42<AsOf),"Overdue","") | S42: 11, C10
A43: 1.08 | B43: 2.7 | C43: P1 Sandbox XS4 (copy of DS4) | D43: SEC - Security, GRC, SailPoint | E43: XS4 SU25 steps 2a/2b, SU24 and role delta; GRC AC 12.0 SP32 post-steps (sync jobs, risk analysis) | F43: XS4 | G43: 46321 | H43: 46322 | I43: INTL SAP Security | J43: INTL SAP Security | K43: INTL Basis | L43: 1.06 | M43: Role delta list sized for DS4 | N43: UG 6.4; MP | O43: =IFERROR(INDEX(Schedule!$G$5:$G$300,MATCH($B43,Schedule!$A$5:$A$300,0)),"Not Started") -> Not Started | P43: Notes 3809657 and 3782096 (SU25) are in the SER in-scope list | Q43: =IF(AND(ISNUMBER(G43),ISNUMBER(H43)),H43-G43+1,"") -> 2 | R43: =IF(AND(ISNUMBER(H43),O43<>"Complete",H43<AsOf),"Overdue","") | S43: 11, C11
A44: 1.09 | B44: 2.8 | C44: P1 Sandbox XS4 (copy of DS4) | D44: CODE - Custom code, notes, SPDD/SPAU | E44: XS4 note bundle trial: HotNews 3777415 and 3563542 first, then High, then Medium in-scope notes | F44: XS4 | G44: 46321 | H44: 46323 | I44: PwC Technical | J44: PwC Technical | K44: PwC Functional | L44: 1.05 | M44: Bundle sequence and effort for DS4 | N44: SER | O44: =IFERROR(INDEX(Schedule!$G$5:$G$300,MATCH($B44,Schedule!$A$5:$A$300,0)),"Not Started") -> Not Started | Q44: =IF(AND(ISNUMBER(G44),ISNUMBER(H44)),H44-G44+1,"") -> 3 | R44: =IF(AND(ISNUMBER(H44),O44<>"Complete",H44<AsOf),"Overdue","") | S44: 11, C8
A45: 1.10 | B45: 2.9 | C45: P1 Sandbox XS4 (copy of DS4) | D45: TST - Testing | E45: Execute the Sandbox Test Plan (30 tests; see sheet); log defects UPG-SPS06 | F45: XS4 | G45: 46321 | H45: 46323 | I45: PwC Functional | J45: INTL Test Lead | K45: INTL Basis; INTL SAP Security | L45: 1.06, 1.07 | M45: All "Yes" tests passed; each "Partial" has a named follow-up | N45: USER | O45: =IFERROR(INDEX(Schedule!$G$5:$G$300,MATCH($B45,Schedule!$A$5:$A$300,0)),"Not Started") -> Not Started | Q45: =IF(AND(ISNUMBER(G45),ISNUMBER(H45)),H45-G45+1,"") -> 3 | R45: =IF(AND(ISNUMBER(H45),O45<>"Complete",H45<AsOf),"Overdue","") | S45: 12, C13
A46: 1.11 | B46: 2.10 | C46: P1 Sandbox XS4 (copy of DS4) | D46: TEC - Technical upgrade (Basis / ECS) | E46: Lessons learned; confirm downtime per system with ECS (DS4, QS4, SS4, PS4 windows) | F46: XS4 | G46: 46323 | H46: 46323 | I46: INTL Basis | J46: INTL Basis | K46: SAP ECS | L46: 1.04 | M46: Windows reconfirmed | N46: USER | O46: =IFERROR(INDEX(Schedule!$G$5:$G$300,MATCH($B46,Schedule!$A$5:$A$300,0)),"Not Started") -> Not Started | Q46: =IF(AND(ISNUMBER(G46),ISNUMBER(H46)),H46-G46+1,"") -> 1 | R46: =IF(AND(ISNUMBER(H46),O46<>"Complete",H46<AsOf),"Overdue","") | S46: 11
A47: G1 | B47: 2.11 | C47: P1 Sandbox XS4 (copy of DS4) | D47: GOV - Governance & SAP engagement | E47: GATE G1 - Sandbox sign-off: go for DS4 (Thu 29 Oct 12:00 CT, before DS4 uptime starts) | F47: - | G47: 46324 | H47: 46324 | I47: INTL PMO | J47: INTL PMO | K47: INTL Basis; PwC Technical; INTL Test Lead | L47: 1.05-1.11 | M47: Go for DS4 or Plan B | N47: USER | O47: =IFERROR(INDEX(Schedule!$G$5:$G$300,MATCH($B47,Schedule!$A$5:$A$300,0)),"Not Started") -> Not Started | Q47: =IF(AND(ISNUMBER(G47),ISNUMBER(H47)),H47-G47+1,"") -> 1 | R47: =IF(AND(ISNUMBER(H47),O47<>"Complete",H47<AsOf),"Overdue","") | S47: G1
A48: 2.01 | B48: 3.1 | C48: P2 Development DS4 + DS5 copy | D48: TEC - Technical upgrade (Basis / ECS) | E48: ECS system copy DS4 > DS5 (temporary Dev on FPS02 = fallback) | F48: DS4 > DS5 | G48: 46322 | H48: 46323 | I48: SAP ECS | J48: INTL Basis | K48: INTL Basis | L48: 0.04 | M48: DS5 = DS4 at copy time | N48: UG 3.1 | O48: =IFERROR(INDEX(Schedule!$G$5:$G$300,MATCH($B48,Schedule!$A$5:$A$300,0)),"Not Started") -> Not Started | P48: SAP temporary-landscape pattern (UG 3.1) | Q48: =IF(AND(ISNUMBER(G48),ISNUMBER(H48)),H48-G48+1,"") -> 2 | R48: =IF(AND(ISNUMBER(H48),O48<>"Complete",H48<AsOf),"Overdue","") | S48: 13
A49: 2.02 | B49: 3.2 | C49: P2 Development DS4 + DS5 copy | D49: TEC - Technical upgrade (Basis / ECS) | E49: DS5 post-copy: BDLS, isolation (no DG4, no SLT, no BTP), add to TMS with routes DS5 > QS4/SS4 (FPS02 fixes) and DS5 > QS5; re-import DS4 transports released after the copy point | F49: DS5 | G49: 46323 | H49: 46324 | I49: INTL Basis | J49: INTL Basis | K49: PwC Technical | L49: 2.01 | M49: DS5 open for fixes Fri 30 Oct | N49: UG 3.1 | O49: =IFERROR(INDEX(Schedule!$G$5:$G$300,MATCH($B49,Schedule!$A$5:$A$300,0)),"Not Started") -> Not Started | Q49: =IF(AND(ISNUMBER(G49),ISNUMBER(H49)),H49-G49+1,"") -> 2 | R49: =IF(AND(ISNUMBER(H49),O49<>"Complete",H49<AsOf),"Overdue","") | S49: 13
A50: 2.03 | B50: 3.3 | C50: P2 Development DS4 + DS5 copy | D50: GOV - Governance & SAP engagement | E50: DS4 release cut-off: SIT2 fixes released and imported to QS4 by Fri 30 Oct 12:00 CT | F50: DS4 > QS4 | G50: 46325 | H50: 46325 | I50: PwC Technical | J50: INTL PMO | K50: INTL Basis | L50: 0.12 | M50: Nothing open in DS4 | N50: UG 3.1 | O50: =IFERROR(INDEX(Schedule!$G$5:$G$300,MATCH($B50,Schedule!$A$5:$A$300,0)),"Not Started") -> Not Started | Q50: =IF(AND(ISNUMBER(G50),ISNUMBER(H50)),H50-G50+1,"") -> 1 | R50: =IF(AND(ISNUMBER(H50),O50<>"Complete",H50<AsOf),"Overdue","") | S50: 14
A51: 2.04 | B51: 3.4 | C51: P2 Development DS4 + DS5 copy | D51: TEC - Technical upgrade (Basis / ECS) | E51: ECS SUM on DS4: uptime Fri 30 Oct (dev lock); downtime Sat 31 Oct (Sun 1 Nov contingency) | F51: DS4 | G51: 46325 | H51: 46327 | I51: SAP ECS | J51: INTL Basis | K51: INTL Basis | L51: G1 | M51: DS4 on SPS06 | N51: UG 5 | O51: =IFERROR(INDEX(Schedule!$G$5:$G$300,MATCH($B51,Schedule!$A$5:$A$300,0)),"Not Started") -> Not Started | P51: Weekend window (USER) | Q51: =IF(AND(ISNUMBER(G51),ISNUMBER(H51)),H51-G51+1,"") -> 3 | R51: =IF(AND(ISNUMBER(H51),O51<>"Complete",H51<AsOf),"Overdue","") | S51: 14, C3, C7
A52: 2.05 | B52: 3.5 | C52: P2 Development DS4 + DS5 copy | D52: CODE - Custom code, notes, SPDD/SPAU | E52: DS4 SPDD during SUM (transport ID <SID>K9xxxxx into SR), then SPAU and SPAU_ENH; release both adjustment transports for reuse | F52: DS4 | G52: 46326 | H52: 46328 | I52: PwC Technical | J52: PwC Technical | K52: INTL Basis; SAP ECS | L52: 2.04 SS | M52: SPDD + SPAU transports for QS4, SS4, PS4, DS5, QS5 | N52: UG 3.5; SR form | O52: =IFERROR(INDEX(Schedule!$G$5:$G$300,MATCH($B52,Schedule!$A$5:$A$300,0)),"Not Started") -> Not Started | P52: Subsequent systems reuse them in phase ADJUSTPRP | Q52: =IF(AND(ISNUMBER(G52),ISNUMBER(H52)),H52-G52+1,"") -> 3 | R52: =IF(AND(ISNUMBER(H52),O52<>"Complete",H52<AsOf),"Overdue","") | S52: 14, C5, C8
A53: 2.06 | B53: 3.6 | C53: P2 Development DS4 + DS5 copy | D53: TEC - Technical upgrade (Basis / ECS) | E53: DS4 post-processing: technical checks, Fiori follow-ups, SDM_MON, Work Zone dev content | F53: DS4 | G53: 46327 | H53: 46328 | I53: INTL Basis | J53: INTL Basis | K53: PwC Technical | L53: 2.04 | M53: Checklist signed | N53: UG 6.1, 6.3 | O53: =IFERROR(INDEX(Schedule!$G$5:$G$300,MATCH($B53,Schedule!$A$5:$A$300,0)),"Not Started") -> Not Started | Q53: =IF(AND(ISNUMBER(G53),ISNUMBER(H53)),H53-G53+1,"") -> 2 | R53: =IF(AND(ISNUMBER(H53),O53<>"Complete",H53<AsOf),"Overdue","") | S53: 14, C9, C10
A54: 2.07 | B54: 3.7 | C54: P2 Development DS4 + DS5 copy | D54: SEC - Security, GRC, SailPoint | E54: DS4 SU25 2a/2b, SU24, PFCG roles, GRC post-steps; role transports released | F54: DS4 | G54: 46328 | H54: 46329 | I54: INTL SAP Security | J54: INTL SAP Security | K54: INTL Basis | L54: 2.06 | M54: Role transports | N54: UG 6.4 | O54: =IFERROR(INDEX(Schedule!$G$5:$G$300,MATCH($B54,Schedule!$A$5:$A$300,0)),"Not Started") -> Not Started | Q54: =IF(AND(ISNUMBER(G54),ISNUMBER(H54)),H54-G54+1,"") -> 2 | R54: =IF(AND(ISNUMBER(H54),O54<>"Complete",H54<AsOf),"Overdue","") | S54: 14, C11
A55: 2.08 | B55: 3.8 | C55: P2 Development DS4 + DS5 copy | D55: CODE - Custom code, notes, SPDD/SPAU | E55: DS4 note bundle (SNOTE) in transports; ATC re-run on SPS06; RICEFW unit tests (interfaces, enhancements, forms, workflows, custom Fiori) | F55: DS4 | G55: 46328 | H55: 46330 | I55: PwC Technical | J55: PwC Technical | K55: PwC Functional | L55: 2.05 | M55: Note transports; unit-test evidence; zero priority-1 ATC findings | N55: SER; UG 4.5 | O55: =IFERROR(INDEX(Schedule!$G$5:$G$300,MATCH($B55,Schedule!$A$5:$A$300,0)),"Not Started") -> Not Started | Q55: =IF(AND(ISNUMBER(G55),ISNUMBER(H55)),H55-G55+1,"") -> 3 | R55: =IF(AND(ISNUMBER(H55),O55<>"Complete",H55<AsOf),"Overdue","") | S55: 14, C8
A56: 2.09 | B56: 3.9 | C56: P2 Development DS4 + DS5 copy | D56: INT - Integrations (CFIN, GTS, BTP, partners) | E56: DS4 integration unit checks with dev endpoints: DG4, AFC, MBC, DRC, Work Zone, SailPoint (dev), OpenText | F56: DS4 | G56: 46329 | H56: 46330 | I56: PwC Functional | J56: PwC Functional | K56: INTL Basis; SAP BTP team | L56: 2.06 | M56: Connections tested | N56: USER | O56: =IFERROR(INDEX(Schedule!$G$5:$G$300,MATCH($B56,Schedule!$A$5:$A$300,0)),"Not Started") -> Not Started | Q56: =IF(AND(ISNUMBER(G56),ISNUMBER(H56)),H56-G56+1,"") -> 2 | R56: =IF(AND(ISNUMBER(H56),O56<>"Complete",H56<AsOf),"Overdue","") | S56: 14, C12
A57: 2.10 | B57: 3.10 | C57: P2 Development DS4 + DS5 copy | D57: GOV - Governance & SAP engagement | E57: Dual maintenance: SIT2, Mock3 and UAT fixes built in DS5 (FPS02) for QS4/SS4, and re-applied in DS4 (SPS06); retrofit log reconciled daily | F57: DS5, DS4 | G57: 46325 | H57: 46339 | I57: PwC Technical | J57: PwC Technical | K57: INTL Basis | L57: 2.02 | M57: Retrofit log: every DS5 change also in DS4 | N57: UG 3.1 | O57: =IFERROR(INDEX(Schedule!$G$5:$G$300,MATCH($B57,Schedule!$A$5:$A$300,0)),"Not Started") -> Not Started | P57: Ends when SS4 is on SPS06 (14 Nov) | Q57: =IF(AND(ISNUMBER(G57),ISNUMBER(H57)),H57-G57+1,"") -> 15 | R57: =IF(AND(ISNUMBER(H57),O57<>"Complete",H57<AsOf),"Overdue","") | S57: 15
A58: G2 | B58: 3.11 | C58: P2 Development DS4 + DS5 copy | D58: GOV - Governance & SAP engagement | E58: GATE G2 - Dev ready: adjustment, note and role transports released; no blocking unit-test failure | F58: - | G58: 46330 | H58: 46330 | I58: INTL PMO | J58: INTL PMO | K58: PwC Technical; INTL Basis | L58: 2.05-2.09 | M58: Go for QS4 | N58: UG 3.5 | O58: =IFERROR(INDEX(Schedule!$G$5:$G$300,MATCH($B58,Schedule!$A$5:$A$300,0)),"Not Started") -> Not Started | Q58: =IF(AND(ISNUMBER(G58),ISNUMBER(H58)),H58-G58+1,"") -> 1 | R58: =IF(AND(ISNUMBER(H58),O58<>"Complete",H58<AsOf),"Overdue","") | S58: G2
A59: 3.01 | B59: 4.1 | C59: P3 QA QS4 + QS5 copy | D59: TEC - Technical upgrade (Basis / ECS) | E59: ECS system copy QS4 > QS5 from backup (QS4 stays in SIT2) | F59: QS4 > QS5 | G59: 46330 | H59: 46331 | I59: SAP ECS | J59: INTL Basis | K59: INTL Basis | L59: 0.04 | M59: QS5 = QS4 (FPS02) = fallback QA | N59: UG 3.1 | O59: =IFERROR(INDEX(Schedule!$G$5:$G$300,MATCH($B59,Schedule!$A$5:$A$300,0)),"Not Started") -> Not Started | Q59: =IF(AND(ISNUMBER(G59),ISNUMBER(H59)),H59-G59+1,"") -> 2 | R59: =IF(AND(ISNUMBER(H59),O59<>"Complete",H59<AsOf),"Overdue","") | S59: 16
A60: 3.02 | B60: 4.2 | C60: P3 QA QS4 + QS5 copy | D60: TEC - Technical upgrade (Basis / ECS) | E60: QS5 post-copy: BDLS, isolation (no QG4, no QL4, no BTP, no PAC/banks), TMS route DS5 > QS5 | F60: QS5 | G60: 46331 | H60: 46332 | I60: INTL Basis | J60: INTL Basis | K60: PwC Functional | L60: 3.01 | M60: Isolation evidence | N60: USER | O60: =IFERROR(INDEX(Schedule!$G$5:$G$300,MATCH($B60,Schedule!$A$5:$A$300,0)),"Not Started") -> Not Started | Q60: =IF(AND(ISNUMBER(G60),ISNUMBER(H60)),H60-G60+1,"") -> 2 | R60: =IF(AND(ISNUMBER(H60),O60<>"Complete",H60<AsOf),"Overdue","") | S60: 16
A61: 3.03 | B61: 4.3 | C61: P3 QA QS4 + QS5 copy | D61: TST - Testing | E61: SIT2 exit (6 Nov); FPS02 results frozen in qTest as the baseline for the SPS06 re-run | F61: QS4-200 | G61: 46332 | H61: 46332 | I61: INTL Test Lead | J61: INTL Test Lead | K61: PwC Functional | L61: - | M61: Baseline frozen | N61: POAP | O61: =IFERROR(INDEX(Schedule!$G$5:$G$300,MATCH($B61,Schedule!$A$5:$A$300,0)),"Not Started") -> Not Started | P61: Transport imports into QS4 end Thu 5 Nov (SUM uptime) | Q61: =IF(AND(ISNUMBER(G61),ISNUMBER(H61)),H61-G61+1,"") -> 1 | R61: =IF(AND(ISNUMBER(H61),O61<>"Complete",H61<AsOf),"Overdue","") | S61: 18
A62: 3.04 | B62: 4.4 | C62: P3 QA QS4 + QS5 copy | D62: INT - Integrations (CFIN, GTS, BTP, partners) | E62: QS4 ramp-down Fri 6 Nov: suspend SLT (QL4), drain qRFC/AIF/IDoc, pause GTS transfers, SailPoint, AFC tasks; stop jobs, lock users, clear update errors | F62: QS4, QL4, QG4 | G62: 46332 | H62: 46332 | I62: INTL Basis | J62: INTL Basis | K62: PwC Functional; INTL SAP Security | L62: 0.19, 0.20 | M62: Hand-over to ECS before the downtime (Sat 7 Nov) | N62: UG 5 | O62: =IFERROR(INDEX(Schedule!$G$5:$G$300,MATCH($B62,Schedule!$A$5:$A$300,0)),"Not Started") -> Not Started | P62: Runs during SUM uptime, before the downtime | Q62: =IF(AND(ISNUMBER(G62),ISNUMBER(H62)),H62-G62+1,"") -> 1 | R62: =IF(AND(ISNUMBER(H62),O62<>"Complete",H62<AsOf),"Overdue","") | S62: 17, C6
A63: 3.05 | B63: 4.5 | C63: P3 QA QS4 + QS5 copy | D63: TEC - Technical upgrade (Basis / ECS) | E63: ECS SUM on QS4 (clients 100, 200): uptime Thu 5 - Fri 6 Nov; downtime Sat 7 Nov (Sun 8 contingency); adjustment transports via ADJUSTPRP | F63: QS4 | G63: 46331 | H63: 46334 | I63: SAP ECS | J63: INTL Basis | K63: INTL Basis | L63: G2 | M63: QS4 on SPS06 | N63: UG 3.5, 5 | O63: =IFERROR(INDEX(Schedule!$G$5:$G$300,MATCH($B63,Schedule!$A$5:$A$300,0)),"Not Started") -> Not Started | P63: Straight after SIT2 (USER option 1) | Q63: =IF(AND(ISNUMBER(G63),ISNUMBER(H63)),H63-G63+1,"") -> 4 | R63: =IF(AND(ISNUMBER(H63),O63<>"Complete",H63<AsOf),"Overdue","") | S63: 17, C3, C7
A64: 3.06 | B64: 4.6 | C64: P3 QA QS4 + QS5 copy | D64: TEC - Technical upgrade (Basis / ECS) | E64: QS4 post-processing: checks, note and role transports, Fiori follow-ups, SDM_MON, Work Zone content re-sync | F64: QS4 | G64: 46334 | H64: 46334 | I64: INTL Basis | J64: INTL Basis | K64: INTL SAP Security; PwC Technical | L64: 3.05 | M64: Checklist signed | N64: UG 6 | O64: =IFERROR(INDEX(Schedule!$G$5:$G$300,MATCH($B64,Schedule!$A$5:$A$300,0)),"Not Started") -> Not Started | Q64: =IF(AND(ISNUMBER(G64),ISNUMBER(H64)),H64-G64+1,"") -> 1 | R64: =IF(AND(ISNUMBER(H64),O64<>"Complete",H64<AsOf),"Overdue","") | S64: 17, C9, C10, C11
A65: 3.07 | B65: 4.7 | C65: P3 QA QS4 + QS5 copy | D65: INT - Integrations (CFIN, GTS, BTP, partners) | E65: QS4 resume: SLT replication from QL4 and CFIN reconciliation (AIF); GTS retransfer check; SailPoint aggregation; BTP connections | F65: QS4, QL4, QG4 | G65: 46334 | H65: 46335 | I65: PwC Functional | J65: PwC Functional | K65: INTL Basis; SAP BTP team | L65: 3.06 | M65: Replication and integrations healthy | N65: USER | O65: =IFERROR(INDEX(Schedule!$G$5:$G$300,MATCH($B65,Schedule!$A$5:$A$300,0)),"Not Started") -> Not Started | Q65: =IF(AND(ISNUMBER(G65),ISNUMBER(H65)),H65-G65+1,"") -> 2 | R65: =IF(AND(ISNUMBER(H65),O65<>"Complete",H65<AsOf),"Overdue","") | S65: 17, C12
A66: 3.08 | B66: 4.8 | C66: P3 QA QS4 + QS5 copy | D66: TST - Testing | E66: QS4-200 SPS06 regression: re-run P1 scripts per stream (STP/Ariba, OTC, RTR, ITD, CFIN, GTS, VIM, AFC, DRC MX, MBC, OneSource with TR onsite w/c 9 Nov) | F66: QS4-200 | G66: 46335 | H66: 46338 | I66: PwC Functional | J66: INTL Test Lead | K66: INTL PO / IT Leads; Partner vendors | L66: 3.07, 3.03 | M66: P1 pass >= 95%, no open Sev1/Sev2 | N66: USER | O66: =IFERROR(INDEX(Schedule!$G$5:$G$300,MATCH($B66,Schedule!$A$5:$A$300,0)),"Not Started") -> Not Started | P66: TR is onsite w/c 9 Nov (POAP) | Q66: =IF(AND(ISNUMBER(G66),ISNUMBER(H66)),H66-G66+1,"") -> 4 | R66: =IF(AND(ISNUMBER(H66),O66<>"Complete",H66<AsOf),"Overdue","") | S66: 18, C13
A67: 3.09 | B67: 4.9 | C67: P3 QA QS4 + QS5 copy | D67: SEC - Security, GRC, SailPoint | E67: QS4 security regression: negative tests, GRC AC checks, SailPoint provisioning, Work Zone role collections | F67: QS4 | G67: 46335 | H67: 46337 | I67: INTL SAP Security | J67: INTL SAP Security | K67: INTL Basis | L67: 3.06 | M67: Role test evidence | N67: UG 6.4 | O67: =IFERROR(INDEX(Schedule!$G$5:$G$300,MATCH($B67,Schedule!$A$5:$A$300,0)),"Not Started") -> Not Started | Q67: =IF(AND(ISNUMBER(G67),ISNUMBER(H67)),H67-G67+1,"") -> 3 | R67: =IF(AND(ISNUMBER(H67),O67<>"Complete",H67<AsOf),"Overdue","") | S67: 18, C13
A68: 3.10 | B68: 4.10 | C68: P3 QA QS4 + QS5 copy | D68: DM - Data migration (Syniti) | E68: Migration validation on SPS06: Syniti sample loads per object into QS4-100; migration notes 3805046, 3791609, 3789840 checked | F68: QS4-100 | G68: 46335 | H68: 46337 | I68: PwC Data Migration | J68: PwC Data Migration | K68: Partner vendors; INTL Basis | L68: 3.06 | M68: Objects load on SPS06 | N68: SER | O68: =IFERROR(INDEX(Schedule!$G$5:$G$300,MATCH($B68,Schedule!$A$5:$A$300,0)),"Not Started") -> Not Started | P68: Cutover loads (7 Dec) run on SPS06 | Q68: =IF(AND(ISNUMBER(G68),ISNUMBER(H68)),H68-G68+1,"") -> 3 | R68: =IF(AND(ISNUMBER(H68),O68<>"Complete",H68<AsOf),"Overdue","") | S68: 18
A69: 3.11 | B69: 4.11 | C69: P3 QA QS4 + QS5 copy | D69: INT - Integrations (CFIN, GTS, BTP, partners) | E69: QS5 fallback readiness: QL5 repointed to QS5; CFIN smoke on QS5 (only needed for Plan C) | F69: QS5, QL5 | G69: 46335 | H69: 46337 | I69: PwC Functional | J69: PwC Functional | K69: INTL Basis | L69: 3.02 | M69: QS5 usable as fallback QA | N69: USER | O69: =IFERROR(INDEX(Schedule!$G$5:$G$300,MATCH($B69,Schedule!$A$5:$A$300,0)),"Not Started") -> Not Started | Q69: =IF(AND(ISNUMBER(G69),ISNUMBER(H69)),H69-G69+1,"") -> 3 | R69: =IF(AND(ISNUMBER(H69),O69<>"Complete",H69<AsOf),"Overdue","") | S69: 16
A70: 3.12 | B70: 4.12 | C70: P3 QA QS4 + QS5 copy | D70: TST - Testing | E70: Defect triage against the FPS02 baseline; fix and retest UPG-SPS06 defects (fixes in DS4 now that DS4 and QS4 are both SPS06) | F70: DS4 > QS4 | G70: 46335 | H70: 46338 | I70: PwC Functional | J70: INTL Test Lead | K70: PwC Technical | L70: 3.08 SS | M70: Defect log closed or accepted | N70: UG 3.1 | O70: =IFERROR(INDEX(Schedule!$G$5:$G$300,MATCH($B70,Schedule!$A$5:$A$300,0)),"Not Started") -> Not Started | Q70: =IF(AND(ISNUMBER(G70),ISNUMBER(H70)),H70-G70+1,"") -> 4 | R70: =IF(AND(ISNUMBER(H70),O70<>"Complete",H70<AsOf),"Overdue","") | S70: 18, C14
A71: G3 | B71: 4.13 | C71: P3 QA QS4 + QS5 copy | D71: GOV - Governance & SAP engagement | E71: GATE G3 - Go for SS4: P1 >= 95%, zero open Sev1/Sev2 upgrade defects, CFIN/GTS/BTP green, security passed; otherwise Plan C | F71: - | G71: 46338 | H71: 46338 | I71: INTL PMO | J71: INTL PMO | K71: INTL Basis; INTL Test Lead; PwC Functional | L71: 3.05-3.12 | M71: Go / Plan C | N71: USER | O71: =IFERROR(INDEX(Schedule!$G$5:$G$300,MATCH($B71,Schedule!$A$5:$A$300,0)),"Not Started") -> Not Started | Q71: =IF(AND(ISNUMBER(G71),ISNUMBER(H71)),H71-G71+1,"") -> 1 | R71: =IF(AND(ISNUMBER(H71),O71<>"Complete",H71<AsOf),"Overdue","") | S71: G3
A72: 4.01 | B72: 5.1 | C72: P4 Pre-production SS4 | D72: TST - Testing | E72: UAT week 1 on SS4 (FPS02) as planned; UAT fixes for SS4 via DS5 until SS4 is upgraded; SS4 imports end Thu 12 Nov | F72: SS4-100 | G72: 46335 | H72: 46339 | I72: INTL PO / IT Leads | J72: INTL Test Lead | K72: PwC Functional | L72: - | M72: UAT week 1 results | N72: POAP | O72: =IFERROR(INDEX(Schedule!$G$5:$G$300,MATCH($B72,Schedule!$A$5:$A$300,0)),"Not Started") -> Not Started | Q72: =IF(AND(ISNUMBER(G72),ISNUMBER(H72)),H72-G72+1,"") -> 5 | R72: =IF(AND(ISNUMBER(H72),O72<>"Complete",H72<AsOf),"Overdue","") | S72: 20
A73: 4.02 | B73: 5.2 | C73: P4 Pre-production SS4 | D73: INT - Integrations (CFIN, GTS, BTP, partners) | E73: SS4 ramp-down Fri 13 Nov: SLT, GTS QG4-300, SailPoint, AFC, MBC, DRC queues, OneSource, jobs, users | F73: SS4, QG4-300 | G73: 46339 | H73: 46339 | I73: INTL Basis | J73: INTL Basis | K73: PwC Functional; INTL SAP Security | L73: G3 | M73: Hand-over to ECS | N73: UG 5 | O73: =IFERROR(INDEX(Schedule!$G$5:$G$300,MATCH($B73,Schedule!$A$5:$A$300,0)),"Not Started") -> Not Started | Q73: =IF(AND(ISNUMBER(G73),ISNUMBER(H73)),H73-G73+1,"") -> 1 | R73: =IF(AND(ISNUMBER(H73),O73<>"Complete",H73<AsOf),"Overdue","") | S73: 19, C6
A74: 4.03 | B74: 5.3 | C74: P4 Pre-production SS4 | D74: TEC - Technical upgrade (Basis / ECS) | E74: ECS SUM on SS4: uptime Thu 12 - Fri 13 Nov; downtime Fri night 13 - Sat 14 Nov (Sun 15 contingency) | F74: SS4 | G74: 46338 | H74: 46341 | I74: SAP ECS | J74: INTL Basis | K74: INTL Basis | L74: G3 | M74: SS4 on SPS06 | N74: UG 5 | O74: =IFERROR(INDEX(Schedule!$G$5:$G$300,MATCH($B74,Schedule!$A$5:$A$300,0)),"Not Started") -> Not Started | P74: Weekend window, no UAT weekday lost (USER) | Q74: =IF(AND(ISNUMBER(G74),ISNUMBER(H74)),H74-G74+1,"") -> 4 | R74: =IF(AND(ISNUMBER(H74),O74<>"Complete",H74<AsOf),"Overdue","") | S74: 19, C3, C7
A75: 4.04 | B75: 5.4 | C75: P4 Pre-production SS4 | D75: TEC - Technical upgrade (Basis / ECS) | E75: SS4 post-processing: checks, transports, Fiori follow-ups, SDM_MON, Work Zone UAT content, roles | F75: SS4 | G75: 46340 | H75: 46341 | I75: INTL Basis | J75: INTL Basis | K75: INTL SAP Security; PwC Technical | L75: 4.03 SS | M75: Checklist signed | N75: UG 6 | O75: =IFERROR(INDEX(Schedule!$G$5:$G$300,MATCH($B75,Schedule!$A$5:$A$300,0)),"Not Started") -> Not Started | Q75: =IF(AND(ISNUMBER(G75),ISNUMBER(H75)),H75-G75+1,"") -> 2 | R75: =IF(AND(ISNUMBER(H75),O75<>"Complete",H75<AsOf),"Overdue","") | S75: 19, C9, C10, C11
A76: 4.05 | B76: 5.5 | C76: P4 Pre-production SS4 | D76: INT - Integrations (CFIN, GTS, BTP, partners) | E76: SS4 resume and verify: SLT/CFIN, GTS QG4-300 end-to-end, AFC, MBC, DRC, OneSource, SailPoint, legacy interfaces | F76: SS4, QG4-300 | G76: 46341 | H76: 46341 | I76: PwC Functional | J76: PwC Functional | K76: INTL Basis; SAP BTP team | L76: 4.04 | M76: Integrations green before testers return | N76: USER | O76: =IFERROR(INDEX(Schedule!$G$5:$G$300,MATCH($B76,Schedule!$A$5:$A$300,0)),"Not Started") -> Not Started | Q76: =IF(AND(ISNUMBER(G76),ISNUMBER(H76)),H76-G76+1,"") -> 1 | R76: =IF(AND(ISNUMBER(H76),O76<>"Complete",H76<AsOf),"Overdue","") | S76: 19, C12
A77: 4.06 | B77: 5.6 | C77: P4 Pre-production SS4 | D77: TST - Testing | E77: Technical smoke Mon 16 Nov 08:00; UAT weeks 2-4 continue on SPS06 (16 Nov - 4 Dec) | F77: SS4-100 | G77: 46342 | H77: 46360 | I77: INTL PO / IT Leads | J77: INTL Test Lead | K77: PwC Functional | L77: 4.05 | M77: UAT exit (4 Dec) | N77: POAP | O77: =IFERROR(INDEX(Schedule!$G$5:$G$300,MATCH($B77,Schedule!$A$5:$A$300,0)),"Not Started") -> Not Started | Q77: =IF(AND(ISNUMBER(G77),ISNUMBER(H77)),H77-G77+1,"") -> 19 | R77: =IF(AND(ISNUMBER(H77),O77<>"Complete",H77<AsOf),"Overdue","") | S77: 20, C13
A78: 4.07 | B78: 5.7 | C78: P4 Pre-production SS4 | D78: TST - Testing | E78: Performance delta check on SS4 SPS06: key scenarios from the FPS02 performance test (14 Oct - 6 Nov) | F78: SS4-100 | G78: 46342 | H78: 46344 | I78: INTL Test Lead | J78: INTL Test Lead | K78: INTL Basis; SAP MaxAttention | L78: 4.05 | M78: No material degradation | N78: POAP | O78: =IFERROR(INDEX(Schedule!$G$5:$G$300,MATCH($B78,Schedule!$A$5:$A$300,0)),"Not Started") -> Not Started | Q78: =IF(AND(ISNUMBER(G78),ISNUMBER(H78)),H78-G78+1,"") -> 3 | R78: =IF(AND(ISNUMBER(H78),O78<>"Complete",H78<AsOf),"Overdue","") | S78: 20
A79: G4 | B79: 5.8 | C79: P4 Pre-production SS4 | D79: GOV - Governance & SAP engagement | E79: GATE G4 - Go for PS4: SS4 stable, performance delta acceptable, no upgrade blockers; start DS5/QS5 realignment | F79: - | G79: 46345 | H79: 46345 | I79: INTL PMO | J79: INTL PMO | K79: INTL Basis; INTL Test Lead | L79: 4.04, 4.05, 4.07 | M79: Go for PS4 | N79: USER | O79: =IFERROR(INDEX(Schedule!$G$5:$G$300,MATCH($B79,Schedule!$A$5:$A$300,0)),"Not Started") -> Not Started | Q79: =IF(AND(ISNUMBER(G79),ISNUMBER(H79)),H79-G79+1,"") -> 1 | R79: =IF(AND(ISNUMBER(H79),O79<>"Complete",H79<AsOf),"Overdue","") | S79: G4
A80: 5.01 | B80: 6.1 | C80: P5 Production PS4 | D80: TEC - Technical upgrade (Basis / ECS) | E80: PS4 import hold while PS4 is FPS02 (from 14 Nov until PS4 post-processing) | F80: PS4 | G80: 46340 | H80: 46348 | I80: INTL Basis | J80: INTL Basis | K80: INTL PMO | L80: 4.03 SS | M80: Queue held, then released | N80: UG 3.1 | O80: =IFERROR(INDEX(Schedule!$G$5:$G$300,MATCH($B80,Schedule!$A$5:$A$300,0)),"Not Started") -> Not Started | Q80: =IF(AND(ISNUMBER(G80),ISNUMBER(H80)),H80-G80+1,"") -> 9 | R80: =IF(AND(ISNUMBER(H80),O80<>"Complete",H80<AsOf),"Overdue","") | S80: 21
A81: 5.02 | B81: 6.2 | C81: P5 Production PS4 | D81: TEC - Technical upgrade (Basis / ECS) | E81: ECS SUM on PS4: uptime Thu 19 - Fri 20 Nov; downtime Fri night 20 - Sat 21 Nov (Sun 22 contingency); pre-upgrade backup | F81: PS4 | G81: 46345 | H81: 46348 | I81: SAP ECS | J81: INTL Basis | K81: INTL Basis; SAP MaxAttention | L81: G4 | M81: PS4 on SPS06 | N81: UG 5 | O81: =IFERROR(INDEX(Schedule!$G$5:$G$300,MATCH($B81,Schedule!$A$5:$A$300,0)),"Not Started") -> Not Started | P81: Before cutover starts (7 Dec) | Q81: =IF(AND(ISNUMBER(G81),ISNUMBER(H81)),H81-G81+1,"") -> 4 | R81: =IF(AND(ISNUMBER(H81),O81<>"Complete",H81<AsOf),"Overdue","") | S81: 21, C3, C7
A82: 5.03 | B82: 6.3 | C82: P5 Production PS4 | D82: TEC - Technical upgrade (Basis / ECS) | E82: PS4 post-processing: checks, release queued transports, roles, Fiori follow-ups, Work Zone production content, SDM_MON | F82: PS4 | G82: 46347 | H82: 46349 | I82: INTL Basis | J82: INTL Basis | K82: INTL SAP Security | L82: 5.02 SS | M82: Technical verification signed | N82: UG 6 | O82: =IFERROR(INDEX(Schedule!$G$5:$G$300,MATCH($B82,Schedule!$A$5:$A$300,0)),"Not Started") -> Not Started | Q82: =IF(AND(ISNUMBER(G82),ISNUMBER(H82)),H82-G82+1,"") -> 3 | R82: =IF(AND(ISNUMBER(H82),O82<>"Complete",H82<AsOf),"Overdue","") | S82: 21, C9, C10, C11
A83: 5.04 | B83: 6.4 | C83: P5 Production PS4 | D83: INT - Integrations (CFIN, GTS, BTP, partners) | E83: PS4 connection checks for integrations already configured (BTP production tenants, Cloud Connector, SLT, GTS) - no business data before cutover | F83: PS4 | G83: 46349 | H83: 46349 | I83: INTL Basis | J83: INTL Basis | K83: PwC Functional; SAP BTP team | L83: 5.03 | M83: Connections verified | N83: POAP | O83: =IFERROR(INDEX(Schedule!$G$5:$G$300,MATCH($B83,Schedule!$A$5:$A$300,0)),"Not Started") -> Not Started | Q83: =IF(AND(ISNUMBER(G83),ISNUMBER(H83)),H83-G83+1,"") -> 1 | R83: =IF(AND(ISNUMBER(H83),O83<>"Complete",H83<AsOf),"Overdue","") | S83: 21, C12
A84: G5 | B84: 6.5 | C84: P5 Production PS4 | D84: GOV - Governance & SAP engagement | E84: GATE G5 - Upgrade closed: PS4 verified, UAT clean on SPS06; feeds Go/No-Go (30 Nov - 4 Dec) | F84: - | G84: 46351 | H84: 46351 | I84: INTL PMO | J84: INTL PMO | K84: INTL Basis; INTL Test Lead | L84: 5.03, 5.04 | M84: Upgrade closed | N84: POAP | O84: =IFERROR(INDEX(Schedule!$G$5:$G$300,MATCH($B84,Schedule!$A$5:$A$300,0)),"Not Started") -> Not Started | P84: Thanksgiving is Thu 26 Nov | Q84: =IF(AND(ISNUMBER(G84),ISNUMBER(H84)),H84-G84+1,"") -> 1 | R84: =IF(AND(ISNUMBER(H84),O84<>"Complete",H84<AsOf),"Overdue","") | S84: G5
A85: 6.01 | B85: 7.1 | C85: P6 N+1 realign DS5 / QS5 | D85: TEC - Technical upgrade (Basis / ECS) | E85: ECS SUM on DS5 (adjustment transports reused) | F85: DS5 | G85: 46357 | H85: 46357 | I85: SAP ECS | J85: INTL Basis | K85: INTL Basis | L85: G4 | M85: DS5 on SPS06 | N85: USER | O85: =IFERROR(INDEX(Schedule!$G$5:$G$300,MATCH($B85,Schedule!$A$5:$A$300,0)),"Not Started") -> Not Started | P85: DS5/QS5 kept as fallback until G4 (USER) | Q85: =IF(AND(ISNUMBER(G85),ISNUMBER(H85)),H85-G85+1,"") -> 1 | R85: =IF(AND(ISNUMBER(H85),O85<>"Complete",H85<AsOf),"Overdue","") | S85: 22, C3, C7
A86: 6.02 | B86: 7.2 | C86: P6 N+1 realign DS5 / QS5 | D86: TEC - Technical upgrade (Basis / ECS) | E86: ECS SUM on QS5 | F86: QS5 | G86: 46359 | H86: 46359 | I86: SAP ECS | J86: INTL Basis | K86: INTL Basis | L86: 6.01 | M86: QS5 on SPS06 | N86: USER | O86: =IFERROR(INDEX(Schedule!$G$5:$G$300,MATCH($B86,Schedule!$A$5:$A$300,0)),"Not Started") -> Not Started | Q86: =IF(AND(ISNUMBER(G86),ISNUMBER(H86)),H86-G86+1,"") -> 1 | R86: =IF(AND(ISNUMBER(H86),O86<>"Complete",H86<AsOf),"Overdue","") | S86: 22, C3, C7
A87: 6.03 | B87: 7.3 | C87: P6 N+1 realign DS5 / QS5 | D87: TEC - Technical upgrade (Basis / ECS) | E87: DS5/QS5 post-processing; retrofit DS4 changes since the copy; reconnect N+1 integrations (QL5 etc.) per N+1 design | F87: DS5, QS5 | G87: 46357 | H87: 46360 | I87: INTL Basis | J87: INTL Basis | K87: PwC Technical; PwC Functional | L87: 6.01 | M87: N+1 line equals PS4 level | N87: UG 3.1 | O87: =IFERROR(INDEX(Schedule!$G$5:$G$300,MATCH($B87,Schedule!$A$5:$A$300,0)),"Not Started") -> Not Started | P87: Release 2 paused (USER) | Q87: =IF(AND(ISNUMBER(G87),ISNUMBER(H87)),H87-G87+1,"") -> 4 | R87: =IF(AND(ISNUMBER(H87),O87<>"Complete",H87<AsOf),"Overdue","") | S87: 22
A88: 7.01 | B88: 8.3 | C88: P7 Stabilize to go-live | D88: CODE - Custom code, notes, SPDD/SPAU | E88: Side-effect watch: re-run the side-effect report weekly until go-live | F88: All | G88: 46349 | H88: 46388 | I88: PwC Technical | J88: INTL Basis | K88: SAP MaxAttention | L88: 5.03 | M88: Watch log | N88: SER | O88: =IFERROR(INDEX(Schedule!$G$5:$G$300,MATCH($B88,Schedule!$A$5:$A$300,0)),"Not Started") -> Not Started | Q88: =IF(AND(ISNUMBER(G88),ISNUMBER(H88)),H88-G88+1,"") -> 40 | R88: =IF(AND(ISNUMBER(H88),O88<>"Complete",H88<AsOf),"Overdue","") | S88: 23
A89: 7.02 | B89: 8.4 | C89: P7 Stabilize to go-live | D89: TST - Testing | E89: Cutover on SPS06 (7 - 31 Dec): SPS06 items in the cutover checklist | F89: PS4 | G89: 46363 | H89: 46387 | I89: INTL PMO | J89: INTL PMO | K89: PwC Data Migration; INTL Basis | L89: G5 | M89: Checklist | N89: POAP | O89: =IFERROR(INDEX(Schedule!$G$5:$G$300,MATCH($B89,Schedule!$A$5:$A$300,0)),"Not Started") -> Not Started | Q89: =IF(AND(ISNUMBER(G89),ISNUMBER(H89)),H89-G89+1,"") -> 25 | R89: =IF(AND(ISNUMBER(H89),O89<>"Complete",H89<AsOf),"Overdue","") | S89: -
A90: 7.03 | B90: 8.1 | C90: P7 Stabilize to go-live | D90: TEC - Technical upgrade (Basis / ECS) | E90: SDMI completion: SDM_MON shows all SDMIs finished in all clients of every upgraded system | F90: All | G90: 46349 | H90: 46360 | I90: INTL Basis | J90: INTL Basis | K90: SAP ECS | L90: 5.02 | M90: Screenshot per system | N90: UG 6.1 | O90: =IFERROR(INDEX(Schedule!$G$5:$G$300,MATCH($B90,Schedule!$A$5:$A$300,0)),"Not Started") -> Not Started | P90: All SDMIs must finish before the next upgrade | Q90: =IF(AND(ISNUMBER(G90),ISNUMBER(H90)),H90-G90+1,"") -> 12 | R90: =IF(AND(ISNUMBER(H90),O90<>"Complete",H90<AsOf),"Overdue","") | S90: 23, C9
A91: 7.04 | B91: 8.2 | C91: P7 Stabilize to go-live | D91: GOV - Governance & SAP engagement | E91: Upgrade close-out: lessons learned, SR closure, MaxAttention summary | F91: - | G91: 46356 | H91: 46360 | I91: INTL Basis | J91: INTL PMO | K91: SAP MaxAttention; PwC Technical | L91: G5 | M91: Close-out report | N91: USER | O91: =IFERROR(INDEX(Schedule!$G$5:$G$300,MATCH($B91,Schedule!$A$5:$A$300,0)),"Not Started") -> Not Started | Q91: =IF(AND(ISNUMBER(G91),ISNUMBER(H91)),H91-G91+1,"") -> 5 | R91: =IF(AND(ISNUMBER(H91),O91<>"Complete",H91<AsOf),"Overdue","") | S91: -
A92: 7.05 | B92: 8.5 | C92: P7 Stabilize to go-live | D92: TEC - Technical upgrade (Basis / ECS) | E92: Obsolete data handling (SODH, Note 3335020): not before go-live; plan after hypercare | F92: PS4 | G92: 46388 | H92: 46388 | I92: INTL Basis | J92: INTL Basis | K92: PwC Functional | L92: - | M92: Decision recorded | N92: UG 6.2 | O92: =IFERROR(INDEX(Schedule!$G$5:$G$300,MATCH($B92,Schedule!$A$5:$A$300,0)),"Not Started") -> Not Started | P92: PS4 holds no business data before cutover | Q92: =IF(AND(ISNUMBER(G92),ISNUMBER(H92)),H92-G92+1,"") -> 1 | R92: =IF(AND(ISNUMBER(H92),O92<>"Complete",H92<AsOf),"Overdue","") | S92: -

Sheet Systems
A1: System landscape
A2: N = go-live line, N+1 = DS5/QS5 copies (fallback until G4). Update "Current level" to SPS06 when a system is done.
A4: SID | B4: Role | C4: Line | D4: Clients | E4: Current level | F4: Target level | G4: Copy | H4: Upgrade window | I4: SR | J4: Connected to | K4: Status | L4: Notes | M4: Copy date | N4: Downtime date
A5: XS4 | B5: Sandbox (rehearsal) | C5: Sandbox | D5: tbc | E5: FPS02 | F5: SPS06 | G5: Copy of DS4, 21-22 Oct | H5: Sat 24 Oct | I5: SR 31018471 | J5: Isolated after copy | K5: On Track | L5: Prep on track since 15 Oct; copy SR raised; SR 31018471 reused for the SUM rerun | M5: 46316 | N5: 46319
A6: DS4 | B6: Development | C6: N (go-live line) | D6: 110 | E6: FPS02 | F6: SPS06 | G6: - | H6: Sat 31 Oct | I6: tbc | J6: DG4; dev BTP tenants | K6: Not Started | L6: Dev lock from Fri 30 Oct (SUM uptime) | N6: 46326
A7: DS5 | B7: Temporary Dev / N+1 Dev | C7: N+1 (fallback) | D7: tbc | E7: FPS02 | F7: SPS06 (1 Dec) | G7: Copy of DS4, 27-28 Oct | H7: Tue 1 Dec | I7: tbc | J7: Isolated; TMS to QS4/SS4 (FPS02 fixes) and QS5 | K7: Not Started | L7: Fallback until G4 | M7: 46322 | N7: 46357
A8: QS4 | B8: QA (SIT) | C8: N (go-live line) | D8: 100, 200 | E8: FPS02 | F8: SPS06 | G8: - | H8: Sat 7 Nov | I8: tbc | J8: QG4; QL4 (SLT); QA BTP tenants; legacy | K8: Not Started | L8: SIT2 in client 200 until 6 Nov | N8: 46333
A9: QS5 | B9: Temporary QA / N+1 QA | C9: N+1 (fallback) | D9: tbc | E9: FPS02 | F9: SPS06 (3 Dec) | G9: Copy of QS4, 4-5 Nov | H9: Thu 3 Dec | I9: tbc | J9: Isolated; QL5 (SLT) repoint | K9: Not Started | L9: Fallback until G4 | M9: 46330 | N9: 46359
A10: SS4 | B10: Pre-production (UAT) | C10: N (go-live line) | D10: 100 | E10: FPS02 | F10: SPS06 | G10: - | H10: Fri-Sat 13-14 Nov | I10: tbc | J10: QG4-300 (GTS UAT); SLT; BTP; legacy | K10: Not Started | L10: Mock3 + performance test to 6 Nov; UAT from 9 Nov | N10: 46340
A11: PS4 | B11: Production | C11: N (go-live line) | D11: tbc | E11: FPS02 | F11: SPS06 | G11: - | H11: Fri-Sat 20-21 Nov | I11: tbc | J11: Production endpoints (pre-cutover) | K11: Not Started | L11: Cutover 7-31 Dec; go-live 1 Jan 2027 | N11: 46347
A12: QL4 | B12: SLT server for Central Finance | C12: N | D12: - | E12: not changed | F12: not changed | G12: - | H12: Suspend/resume around QS4 and SS4 | I12: - | J12: QS4 (CFIN) | K12: Not Started | L12: Confirm DMIS compatibility
A13: QL5 | B13: SLT server for Central Finance | C13: N+1 | D13: - | E13: not changed | F13: not changed | G13: - | H13: Repoint to QS5 after copy | I13: - | J13: QS5 (CFIN) | K13: Not Started
A14: DG4 | B14: SAP GTS Development | C14: GTS | D14: tbc | E14: not changed | F14: not changed | G14: - | H14: Paused during DS4 window | I14: - | J14: DS4 | K14: Not Started | L14: GTS release to confirm
A15: QG4 | B15: SAP GTS QA (client 300 = UAT) | C15: GTS | D15: 300 (UAT) + SIT client tbc | E15: not changed | F15: not changed | G15: - | H15: Paused during QS4 and SS4 windows | I15: - | J15: QS4; SS4 (client 300) | K15: Not Started | L15: No GTS pre-production exists
A16: BTP | B16: AFC, MBC, DRC (MX), Work Zone Standard | C16: SaaS | D16: - | E16: SAP-managed | F16: SAP-managed | G16: - | H16: Connection checks after each window | I16: - | J16: DS4, QS4, SS4, PS4 | K16: Not Started | L16: Copies stay disconnected

Sheet SR Tracker
A1: SAP ECS service requests
A2: Service identifiers from the SR form and the Upgrade Guide (UG 2.1, 3.5, 4.2, 4.3). Copy SR identifiers to be confirmed from the ECS catalog.
A4: SR number | B4: System | C4: Service identifier | D4: Purpose | E4: Window | F4: SAP status | G4: Status | H4: Owner | I4: Next action | J4: Raised on
A5: 31018471 | B5: XS4 | C5: BASIC_1.5.09 Update Software Version of Application (non-chargeable) | D5: XS4 FPS02 > SPS06, MP 1002693650 | E5: New: uptime Thu 22 - Fri 23 Oct, downtime Sat 24 Oct (first window was 9 Oct 02:45-10:45 UTC) | F5: Customer Action (14 Oct) | G5: On Track | H5: INTL Basis | I5: After copy (1.01) and note check (1.03): update SPDD/SPAU answers and new window; send back to ECS | J5: 46298
A6: raised (add no.) | B6: DS4 > XS4 | C6: System copy (identifier per ECS catalog) | D6: Sandbox equal to current DS4 scope | E6: Wed 21 - Thu 22 Oct | F6: - | G6: On Track | H6: INTL Basis | I6: Confirm the copy start time with ECS
A7: to raise | B7: DS4 > DS5 | C7: System copy (per ECS catalog) | D7: Temporary Dev on FPS02 (fallback) | E7: Tue 27 - Wed 28 Oct | F7: - | G7: Not Started | H7: INTL Basis | I7: Raise Mon 19 Oct
A8: to raise | B8: QS4 > QS5 | C8: System copy (per ECS catalog) | D8: Temporary QA on FPS02 (fallback) | E8: Wed 4 - Thu 5 Nov | F8: - | G8: Not Started | H8: INTL Basis | I8: Raise Mon 19 Oct
A9: to raise | B9: DS4 | C9: BASIC_1.5.09 | D9: DS4 FPS02 > SPS06 (SPDD/SPAU here) | E9: Uptime Fri 30 Oct; downtime Sat 31 Oct | F9: - | G9: Not Started | H9: INTL Basis | I9: Raise Mon 19 Oct with DS4 MPID
A10: to raise | B10: QS4 | C10: BASIC_1.5.09 | D10: QS4 FPS02 > SPS06 (reuse DS4 transports) | E10: Downtime Sat 7 Nov | F10: - | G10: Not Started | H10: INTL Basis | I10: Raise Mon 19 Oct; add SPDD/SPAU transport IDs after DS4
A11: to raise | B11: SS4 | C11: BASIC_1.5.09 | D11: SS4 FPS02 > SPS06 | E11: Downtime Fri night 13 - Sat 14 Nov | F11: - | G11: Not Started | H11: INTL Basis | I11: Raise Mon 19 Oct
A12: to raise | B12: PS4 | C12: BASIC_1.5.09 | D12: PS4 FPS02 > SPS06 | E12: Downtime Fri night 20 - Sat 21 Nov | F12: - | G12: Not Started | H12: INTL Basis | I12: Raise Mon 19 Oct
A13: to raise | B13: DS5 | C13: BASIC_1.5.09 | D13: DS5 FPS02 > SPS06 after G4 | E13: Tue 1 Dec | F13: - | G13: Not Started | H13: INTL Basis | I13: Raise after G4 (19 Nov)
A14: to raise | B14: QS5 | C14: BASIC_1.5.09 | D14: QS5 FPS02 > SPS06 after G4 | E14: Thu 3 Dec | F14: - | G14: Not Started | H14: INTL Basis | I14: Raise after G4 (19 Nov)
A15: if needed | B15: All | C15: DB_1.1.11 / DB_1.1.12 (HANA), INFRA_1.6.12 (OS) | D15: Only if ECS requires separate DB/OS updates (task 0.06) | E15: Separate downtime (UG 4.3) | F15: - | G15: Not Started | H15: INTL Basis | I15: Decide on ECS answer
A16: optional | B16: All | C16: TO_NWABAP_1.5.08 (billable upgrade package) | D16: ECS performs SPDD/SPAU steps | E16: - | F16: - | G16: Not Started | H16: INTL Basis | I16: Decision D-O5
A17: optional | B17: All | C17: BASIC_1.5.03 (billable CAS) | D17: ECS performs application notes or Fiori follow-ups | E17: - | F17: - | G17: Not Started | H17: INTL Basis | I17: Decision D-O4

Sheet RAID
A1: Risks, assumptions, issues, decisions
A2: Rating: High / Medium / Low. Status: Open / Closed.
A4: ID | B4: Type | C4: Description | D4: Impact | E4: Rating | F4: Mitigation / response | G4: Owner | H4: Due | I4: Status
A5: I1 | B5: Issue | C5: First XS4 update run paused by the SI-check (latest version of Note 2502552 needed); ECS reset SUM 14 Oct | D5: Sandbox rehearsal rescheduled to Sat 24 Oct | E5: Low | F5: Closed by the approach change on 15 Oct (D1): notes in DS4 (0.02, done), copy DS4 to XS4 (1.01), SI-check, SR 31018471 back to ECS (1.03) | G5: INTL Basis | H5: 46310 | I5: Closed
A6: I2 | B6: Issue | C6: Maintenance Plan 1002693650 covered XS4 only | D6: No stack file for other systems | E6: Low | F6: Closed: MP transaction per system created (0.05, done) | G6: INTL Basis | H6: 46311 | I6: Closed
A7: I3 | B7: Issue | C7: Note number check in SR updates (2502662 was entered instead of 2502552 on 12 Oct) | D7: Wrong note attempted | E7: Low | F7: Closed: four-eyes check of note numbers in every SR update | G7: INTL Basis | H7: 46310 | I7: Closed
A8: R1 | B8: Risk | C8: ECS cannot schedule three copies and six SUM runs on the requested dates | D8: Chain slips | E8: High | F8: Copy SR for XS4 raised; remaining SRs Mon 19 Oct; MaxAttention escalation; Plan B (+1 week) | G8: INTL Basis | H8: 46318 | I8: Open
A9: R2 | B9: Risk | C9: SAP updates Note 2502552 between systems and the SI-check pauses SUM | D9: Window lost | E9: High | F9: Check the note version 48 h before each window; re-run SI-check | G9: INTL Basis | H9: 46346 | I9: Open
A10: R3 | B10: Risk | C10: Copies (XS4, DS5, QS5) send data to GTS, SLT, MBC/banks, DRC/PAC, Ariba, OneSource, SailPoint | D10: Duplicate or false business messages | E10: High | F10: Isolation checklist (0.10) executed and evidenced before any user logs on | G10: INTL Basis | H10: 46332 | I10: Open
A11: R4 | B11: Risk | C11: Five consecutive weekend windows (24 Oct - 22 Nov) for a 3-person Basis team | D11: Fatigue, errors | E11: High | F11: Rota across onsite/offshore; ECS + MaxAttention cover; no Basis change work on weekdays after a window | G11: INTL Basis | H11: 46316 | I11: Open
A12: R5 | B12: Risk | C12: Dual maintenance DS5/DS4: a fix applied in one system only | D12: Regression at cutover | E12: Medium | F12: Retrofit log reconciled daily (2.10); Release 2 paused | G12: PwC Technical | H12: 46339 | I12: Open
A13: R6 | B13: Risk | C13: QS4 regression window is 4 days (9-12 Nov) | D13: Defects reach SS4 | E13: High | F13: P1 scripts only; FPS02 baseline; TR onsite the same week; Sandbox evidence first | G13: INTL Test Lead | H13: 46338 | I13: Open
A14: R7 | B14: Risk | C14: UAT week 1 on FPS02, weeks 2-4 on SPS06 | D14: Defect attribution | E14: Medium | F14: Tag UPG-SPS06; compare against QS4 results | G14: INTL Test Lead | H14: 46342 | I14: Open
A15: R8 | B15: Risk | C15: Mock3 runs on FPS02; cutover loads run on SPS06 | D15: Load failures at cutover | E15: Medium | F15: Syniti sample loads on SPS06 in QS4-100 (3.10); Syniti questions | G15: PwC Data Migration | H15: 46337 | I15: Open
A16: R9 | B16: Risk | C16: Partner confirmations (OpenText, SailPoint, Syniti, TR) not received before G1 / G3 | D16: Unsupported combination | E16: High | F16: E-mails sent 19-20 Oct; answers due 28 Oct; hold at G3 if open | G16: INTL Basis | H16: 46323 | I16: Open
... A21: R14 | B21: Risk | C21: New side effects published after SPS06 is installed | D21: Unexpected defects | E21: Low | F21: Weekly side-effect watch (7.01) | G21: PwC Technical | H21: 46388 | I21: Open
A22: A1 | B22: Assumption | C22: Project dates per Plan on a Page (9/21) and user updates: SIT2 28 Sep - 6 Nov (QS4-200); Mock3 19 Oct - 6 Nov and performance test 14 Oct - 6 Nov (SS4-100); UAT 9 Nov - 4 Dec (SS4-100); Go/No-Go at UAT end; cutover 7 - 31 Dec; go-live 1 Jan 2027 | D22: - | E22: - | F22: - | G22: INTL PMO | I22: Open
A23: A2 | B23: Assumption | C23: Downtime per system is about 8 h (XS4 SR window); actual duration is measured in XS4 (1.11) | D23: - | E23: - | F23: - | G23: INTL Basis | I23: Open
A24: A3 | B24: Assumption | C24: Copies are taken from backups, so DS4 and QS4 stay available during the copy (ECS to confirm) | D24: - | E24: - | F24: - | G24: INTL Basis | I24: Open
A25: A4 | B25: Assumption | C25: No test automation; all regression is manual (USER) | D25: - | E25: - | F25: - | G25: INTL Test Lead | I25: Open
A26: A5 | B26: Assumption | C26: Release 2 is paused (USER); N+1 activity is limited to fallback and fixes | D26: - | E26: - | F26: - | G26: INTL PMO | I26: Open
A27: A6 | B27: Assumption | C27: PS4 holds no business data before cutover (7 Dec) | D27: - | E27: - | F27: - | G27: INTL PMO | I27: Open
A28: A7 | B28: Assumption | C28: Times are US Central (SR log shows America/Chicago); ECS windows are agreed in UTC | D28: - | E28: - | F28: - | G28: INTL Basis | I28: Open
A29: D1 | B29: Decision | C29: Copy DS4 to XS4, then rerun SUM on XS4; Sandbox preparation from Thu 15 Oct (USER) | D29: - | E29: - | F29: - | G29: Girish Ogirala | H29: 46310 | I29: Closed
A30: D2 | B30: Decision | C30: Copy DS4 > DS5 and QS4 > QS5, then upgrade DS4 and QS4 (SAP temporary landscape, UG 3.1) (USER) | D30: - | E30: - | F30: - | G30: Girish Ogirala | H30: 46312 | I30: Closed
A31: D3 | B31: Decision | C31: Weekend windows: DS4 31 Oct, QS4 7 Nov, SS4 13-14 Nov, PS4 20-21 Nov (USER option 1 + weekend) | D31: - | E31: - | F31: - | G31: Girish Ogirala | H31: 46312 | I31: Closed
A32: D4 | B32: Decision | C32: DS5/QS5 stay FPS02 as fallback until G4, then upgrade w/c 30 Nov (USER) | D32: - | E32: - | F32: - | G32: Girish Ogirala | H32: 46312 | I32: Closed
A33: D5 | B33: Decision | C33: No test automation (USER) | D33: - | E33: - | F33: - | G33: Girish Ogirala | H33: 46312 | I33: Closed
A34: D-O1 | B34: Decision | C34: OPEN: SDMI in uptime (default, recommended) or forced in downtime (must be stated in the SR, UG 6.1) | D34: - | E34: Medium | F34: Recommend default uptime | G34: INTL Basis | H34: 46317 | I34: Open
A35: D-O2 | B35: Decision | C35: OPEN: connect XS4 to DG4 for GTS tests? Recommend no; prove GTS in QS4 + QG4 | D35: - | E35: Low | F35: Recommend no | G35: PwC Functional (GTS) | H35: 46317 | I35: Open
A36: D-O3 | B36: Decision | C36: OPEN: use Data Transition Validation (Note 3117879) for QS4-200 finance reports? Optional | D36: - | E36: Low | F36: Optional | G36: INTL Test Lead | H36: 46318 | I36: Open
A37: D-O4 | B37: Decision | C37: OPEN: Fiori follow-ups by INTL Basis or ECS CAS (BASIC_1.5.03, billable) | D37: - | E37: Low | F37: Recommend INTL Basis | G37: INTL Basis | H37: 46317 | I37: Open
A38: D-O5 | B38: Decision | C38: OPEN: SPDD/SPAU by PwC Technical or ECS billable package (TO_NWABAP_1.5.08) | D38: - | E38: Low | F38: Recommend PwC unless XS4 shows high volume | G38: INTL Basis | H38: 46323 | I38: Open

Sheet Sandbox Test Plan
A1: Sandbox (XS4) test plan - definition of done before G1
A2: XS4 is isolated after the copy, so connected scenarios are proven in QS4 / SS4 (column F).
A4: Test ID | B4: Area | C4: Test | D4: Done when | E4: Can run in XS4? | F4: Otherwise proven in | G4: Owner | H4: Status | I4: Evidence / defect
A5: SBX-01 | B5: Technical | C5: SUM finished; component levels equal MP 1002693650 target | D5: System status shows S4CORE 108 SP06, SAP_BASIS 758 SP06, add-on SPs as MP | E5: Yes | F5: - | G5: INTL Basis | H5: Not Started
A6: SBX-02 | B6: Technical | C6: Downtime and runtime measured | D6: Actual vs 8 h window recorded; windows confirmed (1.11) | E6: Yes | F6: - | G6: INTL Basis | H6: Not Started
A7: SBX-03 | B7: Technical | C7: SI-check before downtime | D7: No RC >= 8; RC 7 exemptions logged | E7: Yes | F7: - | G7: INTL Basis | H7: Not Started
A8: SBX-04 | B8: Code | C8: SPDD, SPAU, SPAU_ENH worklist | D8: Object count and effort for DS4 | E8: Yes | F8: - | G8: PwC Technical | H8: Not Started
A9: SBX-05 | B9: Technical | C9: System health: SICK, SM21, ST22, SM37, SM59, STMS, SMICM, SGEN | D9: No new dumps or errors vs DS4 baseline | E9: Yes | F9: - | G9: INTL Basis | H9: Not Started
A10: SBX-06 | B10: Technical | C10: Silent data migration | D10: SDM_MON complete in all clients; SDM_USER present | E10: Yes | F10: - | G10: INTL Basis | H10: Not Started
A11: SBX-07 | B11: Fiori | C11: Embedded launchpad and top apps per stream | D11: Tiles open; caches invalidated; SICF nodes active | E11: Yes | F11: - | G11: INTL Basis + PwC Technical | H11: Not Started
A12: SBX-08 | B12: Fiori | C12: Work Zone tiles | D12: Tiles open from Work Zone | E12: No | F12: DS4 2 Nov; QS4 8-12 Nov | G12: INTL Basis | H12: Not Started
A13: SBX-09 | B13: Code | C13: ATC on SPS06; critical custom programs, enhancements, forms, workflows | D13: Zero priority-1 ATC findings; smoke list passed | E13: Yes | F13: - | G13: PwC Technical | H13: Not Started
A14: SBX-10 | B14: Security | C14: SU25 2a/2b; role delta; stream test users log on | D14: Role delta list; users work | E14: Yes | F14: - | G14: INTL SAP Security | H14: Not Started
A15: SBX-11 | B15: Security | C15: GRC AC 12.0 SP32 post-steps and risk analysis | D15: Sync jobs and analysis run | E15: Partial | F15: Connected systems: QS4 9-11 Nov | G15: INTL SAP Security | H15: Not Started
A16: SBX-12 | B16: Code | C16: Side-effect notes: HotNews 3777415, 3563542, then High | D16: Implemented and tested; bundle order fixed | E16: Yes | F16: - | G16: PwC Technical | H16: Not Started
... A34: SBX-30 | B34: Front end | C34: SAP GUI version in use logs on and runs key transactions | D34: Works | E34: Yes | F34: - | G34: INTL Basis | H34: Not Started
A36: Definition of done (G1)
C37: 1. Every "Yes" test passed with evidence in qTest.
C38: 2. Every "Partial" or "No" test has a named follow-up test, system and date (column F).
C39: 3. All UPG-SPS06 defects from XS4 triaged; none Sev1/Sev2 open.
C40: 4. SPDD/SPAU and note effort sized for DS4; downtime confirmed with ECS.
C41: 5. G1 signed by INTL PMO with INTL Basis, PwC Technical and INTL Test Lead.

Sheet Integrations
A1: Integration impact and plan
A2: One row per connected application. Copy isolation applies to XS4, DS5 and QS5.
A4: Application | B4: Systems | C4: What SPS06 changes | D4: Copy isolation (XS4, DS5, QS5) | E4: During upgrade windows | F4: Test where / when | G4: Owner | H4: Status
A5: Central Finance + SLT | B5: S/4 (CFIN in same system); QL4 (N), QL5 (N+1) | C5: CFIN application code (incl. AIF) changes inside the stack; SER in-scope AIF note 3767655. SLT servers are not upgraded. | D5: XS4 and DS5 have no SLT; QS5 copies QS4 settings: block QL4 links and repoint to QL5 (task 3.11) | E5: Suspend replication on QL4 before QS4 (6 Nov) and SS4 (13 Nov); drain AIF; resume and reconcile after | F5: QS4 9-12 Nov (P1 CFIN); SS4 UAT from 16 Nov | G5: PwC Functional (CFIN) + INTL Basis | H5: Not Started
A6: SAP GTS | B6: DG4 (Dev), QG4 (QA; client 300 = UAT) | C6: GTS is not upgraded. The S/4 side of the integration (plug-in in the S/4 core) changes with the stack. | D6: XS4, DS5, QS5 must not reach DG4/QG4 (they would send under the source logical system) | E6: Pause transfers for DS4, QS4 and SS4 windows; retransfer check after | F6: QS4-200 with QG4 9-12 Nov; QG4-300 with SS4 UAT from 16 Nov (no GTS pre-prod) | G6: PwC Functional (GTS) + INTL Basis | H6: Not Started
A7: SAP AFC (BTP) | B7: AFC tenant(s); S/4 via Cloud Connector | C7: AFC itself is SaaS. S/4 programs and variants scheduled by AFC run on the new stack. | D7: Copies are not registered in AFC; do not add them | E7: Pause AFC task runs against the system in its window | F7: Connection + one closing task in DS4 (3-4 Nov) and QS4 (9-12 Nov) | G7: PwC Functional (AFC) + SAP BTP team | H7: Not Started
A8: SAP MBC (BTP) | B8: MBC tenant; S/4 payment and bank-statement interfaces | C8: Payment medium and bank-statement processing run on the new stack; SER in-scope notes per stream test focus. | D8: High risk: a copy keeps the MBC certificate and destination. Disable in XS4, DS5, QS5 | E8: Hold payment file transmission during windows | F8: F110 file creation in XS4 (no send); end-to-end in QS4 9-12 Nov | G8: PwC Functional (MBC) + INTL Basis | H8: Not Started
A9: SAP DRC - Mexico | B9: eDocument framework in S/4; submission via BTP to the PAC | C9: eDocument and legal-change code ships in the stack; the Mexico deployment (21 Sep - 3 Oct) was built on FPS02. SER in-scope DRC note 3830404 (US). | D9: Disable eDocument submission in copies (risk of test folios at the PAC) | E9: Hold submissions during windows; resubmit from the eDocument cockpit | F9: Create in XS4 (no submission); submit in QS4 9-12 Nov; UAT from 16 Nov | G9: PwC Functional (DRC) + SAP BTP team | H9: Not Started
A10: SAP Build Work Zone Standard | B10: Work Zone tenant; S/4 content exposure | C10: Launchpad content (UI content FPS02 > FPS03, SAP_UI 758 SP06) is re-exposed after each upgrade. | D10: Copies are not content providers | E10: Re-expose and re-sync the content channel after each window | F10: Embedded launchpad in XS4; Work Zone in DS4, QS4, SS4, PS4 | G10: INTL Basis + PwC Technical | H10: Not Started
A11: SAP GRC Access Control 12.0 | B11: Embedded in S/4 (GRCFND_A V8100, GRCPINW, UIGRAC01) | C11: Upgraded inside the same SUM: AC 12.0 for S/4HANA SP29 > SP32; Fiori for AC 2.0 SP02 > SP03 (MP). | D11: Copies keep GRC connectors to other systems: deactivate | E11: No separate window | F11: Post-steps and ARA in XS4; regression in QS4 9-11 Nov | G11: INTL SAP Security | H11: Not Started
A12: SailPoint | B12: SailPoint identity platform; SAP connector via RFC | C12: SailPoint objects in S/4 are customer/partner transports; SU25 role changes can affect the connector user. | D12: Do not aggregate or provision copies (unless defined as new applications) | E12: Pause aggregation and provisioning for the target system | F12: Objects active in XS4; aggregation and provisioning in QS4 9-11 Nov | G12: INTL SAP Security + SailPoint | H12: Not Started
A13: Syniti (data migration) | B13: Syniti platform; RFC to S/4; Mock3 on SS4-100 | C13: Load programs and SAP APIs used by Syniti run on the new stack from SS4 (14 Nov) and PS4 (21 Nov). SER in-scope migration notes 3805046, 3791609, 3789840. | D13: No Syniti connection to copies | E13: No loads into a system in its window | F13: Mock3 on FPS02 (no change); sample loads on SPS06 in QS4-100 9-11 Nov | G13: PwC Data Migration + Syniti | H13: Not Started
A14: OpenText VIM 23.4 + ADA 23.4 | B14: In S/4 (OTVIM* 02023_001); archive and capture outside S/4 | C14: Partner add-on SPs move inside the stack: FND/INV SP03 > SP04, O2C/P2P SP01 > SP02; ADA stays at initial shipment (MP). The SER lists no OpenText components. | D14: Disable archive, capture and e-mail connections in copies | E14: Stop inbound capture during windows | F14: VIM flow in XS4 without capture; end-to-end in QS4 9-12 Nov | G14: PwC Functional (VIM) + INTL Basis + OpenText | H14: Not Started
A15: Thomson Reuters OneSource | B15: OneSource tax engine; S/4 tax interface | C15: Tax interface code in the stack; SER in-scope notes in OTC/STP stream focus. | D15: Disconnect copies from OneSource | E15: No impact beyond the window | F15: QS4 9-12 Nov with TR onsite (w/c 9 Nov) | G15: PwC Functional (OneSource) + TR | H15: Not Started
... A17: Legacy interfaces | B17: Non-SAP systems connected to QS4 / SS4 | C17: Interface code on the S/4 side runs on the new stack. | D17: Disable in copies | E17: Notify interface owners of each window | F17: QS4 9-12 Nov; SS4 UAT from 16 Nov | G17: INTL Legacy teams + INTL Basis | H17: Not Started

Sheet Vendor Questions
A1: Vendor questions and e-mail drafts
A2: Send the e-mails on Mon 19 Oct; answers due Wed 28 Oct. Record answers in the yellow cells.
A4: Vendor | B4: ID | C4: Question | D4: Asked on | E4: Answer | F4: Answered on | G4: Status
A5: OpenText | B5: OT-1 | C5: Confirm VIM 23.4 (FND and INV SP04, O2C and P2P SP02, Fiori OTVIMFUI) and ADA 23.4 (initial shipment) are released for SAP S/4HANA 2023 SPS06 (S4CORE 108 SP06, SAP_BASIS / SAP_UI 758 SP06) on RISE Private Cloud. | G5: Not Started
A6: OpenText | B6: OT-2 | C6: Are there known issues, hotfixes or mandatory patches for these SPs on 2023 SPS06? | G6: Not Started
A7: OpenText | B7: OT-3 | C7: Which post-update steps are required after the SP move (configuration checks, BC sets, workflow or BRF+ regeneration, Fiori caches and catalogs)? | G7: Not Started
A8: OpenText | B8: OT-4 | C8: Do the SPs run conversion reports or data changes during import? Are they safe if SUM is restarted? | G8: Not Started
A9: OpenText | B9: OT-5 | C9: Any version dependency with components outside S/4 (capture, archive server, ArchiveLink)? | G9: Not Started
A10: OpenText | B10: OT-6 | C10: Which connections must be disabled after a homogeneous system copy (Sandbox and N+1 copies), and how are they re-registered? | G10: Not Started
A11: OpenText | B11: OT-7 | C11: Recommended regression scope after the SP update, and weekend support for 31 Oct, 7, 14 and 21 Nov. | G11: Not Started
A12: Thomson Reuters | B12: TR-1 | C12: Confirm the OneSource Indirect Tax integration in use is supported on SAP S/4HANA 2023 SPS06. | G12: Not Started
A13: Thomson Reuters | B13: TR-2 | C13: Is any SAP-side transport or configuration change needed for SPS06? | G13: Not Started
A14: Thomson Reuters | B14: TR-3 | C14: Can the onsite team (w/c 9 Nov) validate tax determination on QS4 client 200 (SPS06) during 9-12 Nov? | G14: Not Started
A15: Thomson Reuters | B15: TR-4 | C15: How should copied systems (Sandbox, N+1) be disconnected from OneSource? | G15: Not Started
A16: SailPoint | B16: SP-1 | C16: Confirm the SailPoint SAP connector and SailPoint-delivered SAP transports in use support SAP S/4HANA 2023 SPS06 (SAP_BASIS 758 SP06). | G16: Not Started
... A26: Syniti | B26: SY-6 | C26: Confirm Syniti will not connect to copied systems (Sandbox XS4, N+1 DS5/QS5). | G26: Not Started
A28: E-mail drafts
A29: OpenText | C29: Subject: Project NorthStar - SAP S/4HANA 2023 SPS06 update: VIM 23.4 / ADA 23.4 confirmation
C30: Hello OpenText team, International Motors (Project NorthStar) is updating SAP S/4HANA 2023 on RISE Private Cloud from FPS02 to SPS06 (Maintenance Plan 1002693650). The stack moves our OpenText components as follows: VIM 23.4 FND and INV SP03 to SP04, O2C and P2P SP01 to SP02; ADA 23.4 stays at initial shipment. Planned windows: Sandbox 24 Oct, Development 31 Oct, QA 7 Nov, pre-production 14 Nov, production 21 Nov 2026. Please answer the questions below by Wed 28 Oct 2026; the release confirmation for SPS06 and any required patches or post-update steps matter most. OT-1. Confirm VIM 23.4 (FND and INV SP04, O2C and P2P SP02, Fiori OTVIMFUI) and ADA 23.4 (initial shipment) are released for SAP S/4HANA 2023 SPS06 (S4CORE 108 SP06, SAP_BASIS / SAP_UI 758 SP06) on RISE Private Cloud. OT-2. Are there known issues, hotfixes or mandatory patches for these SPs on 2023 SPS06? OT-3. Which post-update steps are required after the SP move (configuration checks, BC sets, workflow or BRF+ regeneration, Fiori caches and catalogs)? OT-4. Do the SPs run conversion reports or data changes during import? Are they safe if SUM is restarted? OT-5. Any version dependency with components outside S/4 (capture, archive server, ArchiveLink)? OT-6. Which connections must be disabled after a homogeneous system copy (Sandbox and N+1 copies), and how are they re-registered? OT-7. Recommended regression scope after the SP update, and weekend support for 31 Oct, 7, 14 and 21 Nov. Thank you, Girish Ogirala SAP Basis, International Motors
A32: Thomson Reuters | C32: Subject: Project NorthStar - SAP S/4HANA 2023 SPS06 update: OneSource confirmation
C33: Hello Thomson Reuters team, We are updating SAP S/4HANA 2023 from FPS02 to SPS06. QA (QS4) moves on 7 Nov, pre-production (SS4) on 14 Nov and production on 21 Nov 2026. Your onsite week starting 9 Nov falls in our QA regression (9-12 Nov) on SPS06. Please answer the questions below by Wed 28 Oct 2026. TR-1. Confirm the OneSource Indirect Tax integration in use is supported on SAP S/4HANA 2023 SPS06. TR-2. Is any SAP-side transport or configuration change needed for SPS06? TR-3. Can the onsite team (w/c 9 Nov) validate tax determination on QS4 client 200 (SPS06) during 9-12 Nov? TR-4. How should copied systems (Sandbox, N+1) be disconnected from OneSource? Thank you, Girish Ogirala
A35: SailPoint | C35: Subject: Project NorthStar - SAP S/4HANA 2023 SPS06 update: SailPoint connector confirmation
C36: Hello SailPoint team, We are updating SAP S/4HANA 2023 from FPS02 to SPS06 (SAP_BASIS 758 SP06; GRC AC 12.0 SP32). Windows: Development 31 Oct, QA 7 Nov, pre-production 14 Nov, production 21 Nov 2026. Please answer the questions below by Wed 28 Oct 2026. SP-1. Confirm the SailPoint SAP connector and SailPoint-delivered SAP transports in use support SAP S/4HANA 2023 SPS06 (SAP_BASIS 758 SP06). SP-2. Is a new transport version or connector configuration change needed? SP-3. How should aggregation and provisioning be paused for a system during its upgrade window, and how are failed operations replayed? SP-4. Recommended regression tests (aggregation, create, modify, lock, unlock, role assignment, password reset), and any dependency on GRC AC 12.0 SP32. SP-5. Confirm copied systems will not be aggregated unless defined as new applications. Thank you, Girish Ogirala
A38: Syniti | C38: Subject: Project NorthStar - SAP S/4HANA 2023 SPS06 update: impact on Mock3 and cutover loads
C39: Hello Syniti team, Mock Load 3 starts 19 Oct on SS4 client 100 and runs on FPS02 until 6 Nov. SS4 moves to SPS06 on 14 Nov and production on 21 Nov, so cutover loads (from 7 Dec) will run on SPS06. Please answer the questions below by Wed 28 Oct 2026. SY-1. Mock3 runs on SS4 client 100 on FPS02 (19 Oct - 6 Nov); SS4 moves to SPS06 on 14 Nov and production on 21 Nov. Is any Syniti-side change needed? SY-2. Are the Syniti SAP-side components (RFC function modules or transports) compatible with SAP S/4HANA 2023 SPS06? Is a new version needed? SY-3. Which load methods are used per object (BAPI, IDoc, Migration Cockpit staging, custom)? Which objects should be revalidated on SPS06? SY-4. If the Migration Cockpit is used: do migration objects need an update after the stack change before cutover loads? SY-5. Can Syniti run sample loads on QS4 client 100 (SPS06) on 9-11 Nov to prove cutover readiness? SY-6. Confirm Syniti will not connect to copied systems (Sandbox XS4, N+1 DS5/QS5). Thank you, Girish Ogirala

Sheet Transport Windows
A1: Transport windows and rules
A2: Which transports may move while the landscape is on mixed levels.
A4: Window | B4: Dates | C4: System levels | D4: Rule
A5: A | B5: until Thu 29 Oct | C5: All systems FPS02 | D5: Normal DS4 > QS4 > SS4 (> PS4). DS5 exists from 28 Oct but is not used yet.
A6: B | B6: Fri 30 Oct - Sun 8 Nov | C6: DS4 SPS06 (locked from 30 Oct); QS4, SS4, PS4 FPS02 | D6: SIT2 week-6 and Mock3 fixes built in DS5 > QS4 / SS4 (FPS02 to FPS02) and re-applied in DS4. DS4 > QS4 imports held. QS4 imports end Thu 5 Nov.
A7: C | B7: Mon 9 - Sun 15 Nov | C7: DS4, QS4 SPS06; SS4, PS4 FPS02 | D7: DS4 > QS4 normal (both SPS06). UAT week-1 fixes for SS4 from DS5, re-applied in DS4. SS4 imports end Thu 12 Nov. PS4 held.
A8: D | B8: Mon 16 - Sun 22 Nov | C8: DS4, QS4, SS4 SPS06; PS4 FPS02 until 21 Nov | D8: Normal DS4 > QS4 > SS4. PS4 queue held until PS4 post-processing. DS5 frozen (Plan C only).
A9: E | B9: from Mon 23 Nov | C9: Go-live line SPS06; DS5/QS5 FPS02 until 1 / 3 Dec | D9: Normal flow to PS4. DS5/QS5 receive nothing until upgraded, then retrofit per N+1 design.
B10: Rules
B11: 1. Transport only between systems on the same level; never from SPS06 into an FPS02 system (UG 3.1: transports between systems with different software levels may cause errors and inconsistencies).
B12: 2. Dual maintenance (UG 3.1): a fix made in DS5 for an FPS02 system is re-applied in DS4; the retrofit log is reconciled daily (task 2.10).
B13: 3. SUM reuses the DS4 SPDD and SPAU transports in QS4, SS4, PS4, DS5 and QS5 (phase ADJUSTPRP, UG 3.5). Keep the same target stack everywhere.
B14: 4. Imports into a system stop when its SUM uptime starts (repository locked); schedule the last import the day before.
B15: 5. Copies (XS4, DS5, QS5) never send data to connected systems unless a connection is deliberately rebuilt for testing.

Sheet SAP Teams
A1: How SAP ECS, MaxAttention and the BTP team support the upgrade
A2: Relationship owner for all SAP teams: Girish Ogirala (INTL Basis).
A4: SAP team | B4: Role in this upgrade | C4: Tasks | D4: How engaged | E4: When
A5: SAP ECS | B5: Runs the technical work on request (SRs) | C5: System copies DS4>XS4, DS4>DS5, QS4>QS5; SUM runs on XS4, DS4, QS4, SS4, PS4, DS5, QS5; HANA/kernel per MP; backups; technical FES upgrade; SDMI users if requested; hands the SR back at SPDD and for ramp-down | D5: SRs in SAP for Me; TSM for scheduling | E5: Windows confirmed by Fri 23 Oct; copies and SUM per SR Tracker
A6: SAP MaxAttention | B6: Safeguards the plan and escalates | C6: Review plan v4 and the runbook; review SI-check results and the side-effect note bundle; named weekend contacts; escalation of SR delays and incidents; performance comparison FPS02 vs SPS06 on SS4; PS4 window support | D6: Engagement architect / TQM; incident escalation | E6: Review by G0 (22 Oct); on call 24 Oct - 22 Nov
A7: SAP BTP team | B7: Keeps BTP services aligned with each S/4 window | C7: Confirm no AFC, MBC, DRC or Work Zone action is needed for the stack; tenant maintenance dates vs windows; Cloud Connector and destinations; guidance to keep copies disconnected; DRC submission checks | D7: BTP account team; BTP incidents | E7: Checklist by G0; support on each Sunday check (1, 8, 15, 22 Nov)
A8: SAP Support (incidents) | B8: Product incidents during the upgrade | C8: Incidents for SUM, application and note issues; priority per business impact; INTL Basis raises and tracks | D8: SAP for Me incidents (INTL Basis) | E8: As needed

Sheet Guide Checklist
A1: Upgrade Guide (UPGR_PE2023 v6.0) - every recommendation mapped
A2: BPMN node = number in the NorthStar process diagram.
A4: # | B4: Guide section | C4: Recommendation (UPGR_PE2023 v6.0) | D4: NorthStar action | E4: Task(s) | F4: BPMN node | G4: Status
A5: UG-01 | B5: 2.1 | C5: Use the required documents: Simplification Item Catalog, SUM 2.0 guide, Maintenance Planner guide, and Notes 3307222, 3351047, 3348949, 2214409, 3279787, 2399707, 2502552, 3340515, 3340526, 3306766, 3336823, 2217489, 3346290, 3247591 | D5: Reference list in this workbook; 2399707/2502552 implemented first | E5: 0.02 | F5: 1 | G5: Not Started
A6: UG-02 | B6: 2.1 | C6: SAP Readiness Check is relevant for release upgrades, not for FPS/SPS updates | D6: Not required (FPS02 > SPS06 is an SPS update); SI-check and side-effect report used | E6: H.4 | F6: - | G6: Complete
A7: UG-03 | B7: 2.1 | C7: Technical notes via ECS (BASIC_1.5.04); application notes by customer or billable CAS (BASIC_1.5.03); a shared transport must be imported before the next system is upgraded | D7: Note transports from DS4; imported before each SUM | E7: 0.02, 2.08 | F7: 5, C8 | G7: Not Started
A8: UG-04 | B8: 2.2 | C8: Follow the sequence Plan > Prepare > Realize > Follow-up | D8: Phases P0-P7 and BPMN flow | E8: all | F8: all | G8: Not Started
A9: UG-05 | B9: 3.1 | C9: Update in transport order (Dev > QA > Prod) with the same software packages | D9: XS4 > DS4 > QS4 > SS4 > PS4, one target stack | E9: 0.05 | F9: 10-22 | G9: Not Started
A10: UG-06 | B10: 3.1 | C10: Transport only between systems on the same level | D10: Transport windows A-E | E10: 0.12 | F10: 4 | G10: Not Started
A11: UG-07 | B11: 3.1 | C11: Keep the development system; do not copy production to development | D11: DS4 is upgraded in place; copies only go DS4 > XS4/DS5 and QS4 > QS5 | E11: 1.01, 2.01, 3.01 | F11: 10, 13, 16 | G11: Not Started
A12: UG-08 | B12: 3.1 | C12: Plan for the development freeze (dev lock) and inform developers | D12: DS4 lock from Fri 30 Oct; cut-off 30 Oct 12:00 CT | E12: 2.03, 2.04 | F12: C3 | G12: Not Started
A13: UG-09 | B13: 3.1 | C13: Add a temporary Dev (and QA) copy for emergency fixes; dual maintenance with notification | D13: DS5 and QS5 copies; dual-maintenance rule and retrofit log | E13: 2.01, 3.01, 2.10 | F13: 13, 15, 16 | G13: Not Started
A14: UG-10 | B14: 3.2 | C14: Check SAP GUI compatibility before downtime (Notes 147519, 26417, 178788) | D14: GUI check | E14: 0.18 | F14: 6 | G14: Not Started
A15: UG-11 | B15: 3.3 | C15: FES technical upgrade by ECS; check Note 2217489; run the Fiori Upgrade Impact Analysis | D15: MP shows Fiori UI FPS03 and FES 2023 SP02; impact analysis | E15: 0.17 | F15: 6, C7 | G15: Not Started
... A44: UG-40 | B44: 2.1 | C44: Additional notes: 2344014 (SPAU), 2836302 (TCI/digitally signed notes), 2351294 (downtime reduction), 2781530, 2834255 | D44: Reviewed by PwC Technical with the SPAU plan | E44: 1.05 | F44: C8 | G44: Not Started

Sheet RACI
A1: RACI
A2: R = Responsible, A = Accountable, C = Consulted, I = Informed. INTL Basis = Girish Ogirala (lead) + 1 onsite + 2 offshore.
A4: Activity | B4: SAP ECS | C4: SAP MaxAttention | D4: SAP BTP team | E4: INTL Basis | F4: INTL SAP Security | G4: INTL PMO | H4: INTL Test Lead | I4: INTL PO / IT | J4: PwC Technical | K4: PwC Functional | L4: PwC Data Migration | M4: Vendors
A5: Service requests, ECS scheduling, incidents | B5: R | C5: C | D5: I | E5: A/R | F5: I | G5: C | H5: I | I5: I | J5: I | K5: I | L5: I | M5: I
A6: System copies and isolation | B6: R | C6: I | D6: C | E6: A | F6: C | G6: I | H6: I | I6: I | J6: I | K6: C | L6: C | M6: I
A7: SUM runs, HANA, kernel | B7: R | C7: C | D7: I | E7: A | F7: I | G7: I | H7: I | I7: I | J7: C | K7: I | L7: I | M7: I
A8: SI-check and note 2502552 | B8: C | C8: C | D8: I | E8: A/R | F8: I | G8: I | H8: I | I8: I | J8: C | K8: R | L8: I | M8: I
A9: SPDD, SPAU, note bundle, ATC | B9: C | C9: C | D9: I | E9: C | F9: I | G9: I | H9: I | I9: I | J9: A/R | K9: C | L9: I | M9: I
A10: SU25, roles, GRC, SailPoint | B10: I | C10: I | D10: I | E10: C | F10: A/R | G10: I | H10: I | I10: I | J10: C | K10: C | L10: I | M10: C
A11: Fiori, Work Zone, GUI | B11: C | C11: I | D11: C | E11: A/R | F11: C | G11: I | H11: I | I11: I | J11: R | K11: C | L11: I | M11: I
A12: CFIN/SLT, GTS, BTP integrations | B12: I | C12: C | D12: C | E12: C | F12: I | G12: I | H12: I | I12: C | J12: C | K12: A/R | L12: I | M12: C
A13: Partner add-ons (OpenText, TR, SailPoint, Syniti) | B13: I | C13: C | D13: I | E13: A/R | F13: C | G13: I | H13: I | I13: I | J13: C | K13: R | L13: R | M13: R
A14: Sandbox and QS4 regression | B14: I | C14: I | D14: I | E14: C | F14: C | G14: I | H14: A | I14: C | J14: R | K14: R | L14: C | M14: C
A15: UAT on SPS06 (SS4) | B15: I | C15: I | D15: I | E15: C | F15: C | G15: I | H15: A | I15: R | J15: C | K15: C | L15: I | M15: I
... A18: Gates and steering decisions | B18: C | C18: C | D18: C | E18: R | F18: C | G18: A | H18: C | I18: C | J18: C | K18: C | L18: C | M18: I

Sheet Project Calendar
A1: Project calendar (Plan on a Page, updated 9/21)
A2: Context only: dates owned by the NorthStar PMO.
A4: Event | B4: System / client | C4: Start | D4: End | E4: Note
A5: SIT1 | B5: QS4-100 | C5: 46237 | D5: 46292 | E5: Complete per Plan on a Page
A6: Mock Load 2 | B6: QS4-200 | C6: 46272 | D6: 46306 | E6: Master data, then transactional data
A7: SIT2 | B7: QS4-200 | C7: 46293 | D7: 46332 | E7: Started 28 Sep as planned
A8: Performance testing | B8: SS4-100 | C8: 46309 | D8: 46332 | E8: On FPS02
A9: Mock Load 3 | B9: SS4-100 | C9: 46314 | D9: 46332 | E9: On FPS02
A10: UAT | B10: SS4-100 | C10: 46335 | D10: 46360 | E10: Week 1 on FPS02, weeks 2-4 on SPS06
A11: Go / No-Go | B11: - | C11: 46356 | D11: 46360 | E11: At UAT end
A12: Cutover | B12: PS4 | C12: 46363 | D12: 46387 | E12: On SPS06
A13: TR onsite (OneSource) | B13: - | C13: 46335 | D13: 46339 | E13: Validates OneSource on QS4 SPS06
A14: Go-live | B14: PS4 | C14: 46388 | D14: 46388

Sheet Stream Test Focus
A1: Stream test focus for the SPS06 re-run
A2: Note numbers are from the side-effect report for MP 1002693650 (SER).
A4: Stream | B4: What to re-run | C4: SER notes to watch
A5: STP / Ariba (PwC) | B5: PR -> PO -> Ariba Network via CIG add-on (ARBCI1 SP27), order confirmation, ASN, invoice; Manage Purchase Contracts; Taulia (TAUCI1) if used | C5: 3727222, 3728027, 3563636, 3542666
A6: OTC (PwC) | B6: Order -> delivery -> billing, pricing, credit memo tax with OneSource, BP sync | C6: 3678075, 3666390, 3759214
A7: RTR (PwC) | B7: GL close, FX valuation, allocations, AA depreciation, Margin Analysis, Material Ledger close | C7: 3757119, 3777415 (HotNews), 3749911, 3751266
A8: ITD (PwC) | B8: GR/GI, inventory, deliveries, ML valuation, material master mass changes | C8: 3777415, 3779425, 3528920
A9: Central Finance (PwC) | B9: SLT pause/resume, AIF monitor, replication of parked and reversal documents, mapping | C9: 3794020, 3789234, 3793659, 3767655, 3756339
A10: OpenText VIM (PwC) | B10: Invoice capture -> DP document -> parking (FBV0) -> workflow approval -> posting; ArchiveLink images | C10: 3680992, 3279714, 3777208
A11: SAP AFC (PwC) | B11: AFC (BTP) connection to S/4 via Cloud Connector; scheduled S/4 tasks run from AFC | C11: Backend prerequisites per AFC documentation
A12: SAP DRC (PwC) | B12: Mexico eDocuments just deployed (21 Sep - 3 Oct): CFDI issue, cancel, payment complement; US Sales and Use Tax; CA/US/MX statutory reports | C12: 3830404
A13: SAP MBC (PwC) | B13: F110 -> DMEE(X) payment file -> MBC; bank statement import and reprocessing; status messages | C13: 3779613, 3614271, 3735645
A14: OneSource Indirect Tax (PwC + TR) | B14: Tax calculation SO/billing/credit memo, PO/MIRO, Mexico VAT cash basis (RFUMSV50); TR onsite w/c 12 Oct (Sandbox/statement) and w/c 9 Nov (UAT on SPS06) | C14: 3678075, 3613556
A15: Basis / Work Zone (INTL) | B15: Launchpad and Work Zone content federation, tiles, custom apps, spool, qRFC | C15: 3563542 (HotNews), 3534823, 3795313
... A19: Data migration / Syniti (PwC) | B19: Sample loads per object on SPS06 (QS4-100) | C19: 3805046, 3791609, 3789840

Sheet SAP Notes (In-Scope)
A1: Side-effect notes in scope: 135 notes (146 rows)
A2: From the SER for MP 1002693650; full triage in SAP_Notes_Side_Effect_Register_SPS06.xlsx.
A4: Side-effect note | B4: Priority | C4: Title | D4: Component | E4: Caused by note | F4: Owner | G4: Action
A5: 3563542 | B5: 01 HotNews | C5: RSPO1043 detects false inconsistencies and deletes spool requests | D5: BC-CCM-PRN | E5: 0002926979 | F5: INTL Basis | G5: SNOTE after upgrade (no SP assignment in report - check validity in SAP for Me)
A6: 3777415 | B6: 01 HotNews | C6: MBEW-KALN1 overwritten by OBEW-KALN1 | D6: CO-PC-ACT | E6: 0003641556 | F6: PwC RTR / ITD | G6: SNOTE after upgrade (fix ships in S4CORE SP07; target is SP06)
A7: 3279714 | B7: 02 High | C7: Commit Work not triggered by SWZ_AI_CREATE | D7: BC-BMT-WFM | E7: 0003169078 | F7: PwC STP / VIM | G7: SNOTE after upgrade (no SP assignment in report - check validity in SAP for Me)
A8: 3528920 | B8: 02 High | C8: Incorrect function module call due to SAP Note 3505510 | D8: LO-MD-MM | E8: 0003505510 | F8: PwC ITD | G8: SNOTE after upgrade (no SP assignment in report - check validity in SAP for Me)
A9: 3534823 | B9: 02 High | C9: ARFC_END_VB is not for update anymore | D9: BC-MID-RFC-QT | E9: 0003525039 | F9: INTL Basis | G9: SNOTE after upgrade (no SP assignment in report - check validity in SAP for Me)
A10: 3542666 | B10: 02 High | C10: F2229 - Material group missing | D10: MM-FIO-PUR-REQ-PRF | E10: 0003319706 | F10: PwC STP | G10: SNOTE after upgrade (no SP assignment in report - check validity in SAP for Me)
A11: 3563636 | B11: 02 High | C11: [F1048A] Create PO button doesn't launch Create PO application | D11: MM-FIO-PUR-REQ-SOC | E11: 0003539973 | F11: PwC STP | G11: SNOTE after upgrade (fix ships in UIS4HOP1 SP04; target is SP03)
A12: 3613556 | B12: 02 High | C12: RFUMSV50: tax transfer posted with FB01 is not updated in DEFTAX_ITEM | D12: FI-GL-GL-F1 | E12: 0003402197 | F12: PwC RTR / OneSource | G12: SNOTE after upgrade (no SP assignment in report - check validity in SAP for Me)
A13: 3614271 | B13: 02 High | C13: DMEEX - syntax error in LDMEE1CIT & LDMEE1I18 | D13: CA-GTF-CSC-DME | E13: 0003444594 | F13: PwC STP / MBC | G13: SNOTE after upgrade (no SP assignment in report - check validity in SAP for Me)
A14: 3662731 | B14: 02 High | C14: No temporary profitability segments in release S/4 HANA 1709 | D14: CO-PA | E14: 0003589823 | F14: PwC RTR | G14: SNOTE after upgrade (no SP assignment in report - check validity in SAP for Me)
A15: 3666390 | B15: 02 High | C15: Updates to Address Comment (ADRCT-REMARK) are not synchronized between the Business Partner, Supplier, and Customer master when remark is maintained in multiple languages | D15: LO-MD-BP-VM | E15: 0003581401 | F15: PwC OTC / STP | G15: SNOTE after upgrade (no SP assignment in report - check validity in SAP for Me)
... A150: 3831697 | B150: 04 Low | C150: F4485 schreibt keine Nachrichten zum Storno ins Protokoll | D150: FI-FIO-AR | E150: 0003724924 | F150: PwC OTC | G150: SNOTE after upgrade (no SP assignment in report - check validity in SAP for Me)

Sheet Roles
A1: Roles used in this plan
A2: Allocation follows INTL guidance: PwC functional and technical; INTL Basis owns Basis and the SAP relationships; INTL Security collaborates.
A4: Code | B4: Role | C4: Who | D4: Scope
A5: INTL-BAS | B5: INTL Basis | C5: Girish Ogirala (lead) + 1 onsite + 2 offshore | D5: Technical owner of the upgrade; SRs, copies, post-processing, transports, weekend coordination
A6: INTL-SEC | B6: INTL SAP Security | C6: Security team (collaborates with Basis) | D6: SU25/SU24, PFCG roles, GRC AC post-steps, SailPoint and SDMI users
A7: INTL-PMO | B7: INTL PMO | C7: Project NorthStar PMO | D7: Plan, gates, steering, communications
A8: INTL-TST | B8: INTL Test Lead | C8: NorthStar test management | D8: Regression scope, qTest/ADO tracking, UAT coordination
A9: INTL-PO | B9: INTL PO / IT Leads | C9: Business product owners and IT leads | D9: UAT execution and business sign-off
A10: PwC-TEC | B10: PwC Technical | C10: PwC technical team | D10: SPDD/SPAU, notes, custom code, ATC, Fiori custom apps, RICEFW unit tests
A11: PwC-FUN | B11: PwC Functional | C11: PwC functional streams | D11: SI-check application items, regression testing, integration flows
A12: PwC-DM | B12: PwC Data Migration | C12: PwC data migration (Syniti) | D12: Mock loads, Syniti alignment, migration validation on SPS06
A13: SAP-ECS | B13: SAP ECS | C13: SAP Enterprise Cloud Services (via SRs) | D13: System copies, SUM execution, HANA/kernel, backups, technical FES upgrade
A14: SAP-MAX | B14: SAP MaxAttention | C14: SAP MaxAttention engagement team | D14: Plan safeguarding, issue escalation, weekend/go-live support
A15: SAP-BTP | B15: SAP BTP team | C15: SAP BTP team (from SAP) | D15: AFC, MBC, DRC, Work Zone tenants, Cloud Connector guidance
A16: VENDOR | B16: Partner vendors | C16: OpenText, Thomson Reuters, SailPoint, Syniti | D16: Compatibility statements and partner-specific steps

Sheet Read Me
A1: Read me - how this workbook works
A2: CONFIDENTIAL AND PROPRIETARY TO INTERNATIONAL | Plan v4.0 (18 Oct 2026)
A4: Daily update (3 steps)
A5: 1. Exec Summary | B5: Set "As of" to today. Check Overall status, the headline and the three key messages. Update team alignment and leadership asks.
A6: 2. Schedule | B6: Set Status on each task and gate row (drop-down). Phase rows, % complete, Milestones and the Detail Plan follow automatically. Change Start/Finish only when a date really moves.
A7: 3. Dashboard | B7: Open NorthStar_SPS06_Upgrade_Dashboard.html, choose "Update data" and pick this file (or drop it on the page). The file is read in your browser; nothing is uploaded.
A9: Tabs
A10: Schedule | B10: The plan in MS Project style: one line per step, verb first, with the team that performs it. Click the [-] buttons on the left to collapse to phases.
A11: Exec Summary | B11: What leaders see first on the dashboard: status, headline, key messages, team alignment, asks.
A12: Milestones | B12: Gates G0-G5 with their exit criteria, upgrade weekends and project dates.
A13: Detail Plan | B13: Reference detail behind each Schedule row (what exactly, deliverable, sources, notes). Column B links to the Schedule.
A14: Other tabs | B14: Systems, SR Tracker, RAID, Sandbox Test Plan, Integrations, Vendor Questions (with e-mail drafts), Transport Windows, SAP Teams, Guide Checklist, RACI, Project Calendar, Stream Test Focus, SAP Notes (In-Scope), Roles.
A15: Do not rename | B15: Sheet names and column headers: the dashboard finds data by these names. Insert new Schedule rows inside a phase so the phase roll-up includes them, and give them Type Task or Milestone.
A16: Yellow cells | B16: Cells you are expected to edit.
A18: Status values
A19: Not Started | B19: Gray - Not started yet
A20: On Track | B20: Green - In progress and on plan
A21: Complete | B21: Green - Done and evidenced
A22: At Risk | B22: Yellow - In progress, may miss its date - action needed
A23: Blocked | B23: Red - Cannot proceed - escalation needed
A24: Overdue | B24: Calculated: Finish before "As of" and Status not Complete. The Finish date turns red; the dashboard counts it.
A26: Teams
A27: INTL Basis | B27: INTL Basis: Girish Ogirala (lead) + 1 onsite + 2 offshore. Technical owner of the upgrade; SRs, copies, post-processing, transports, weekend coordination
A28: INTL Security | B28: INTL SAP Security: Security team (collaborates with Basis). SU25/SU24, PFCG roles, GRC AC post-steps, SailPoint and SDMI users
A29: INTL PMO | B29: INTL PMO: Project NorthStar PMO. Plan, gates, steering, communications
A30: INTL Testing | B30: INTL Test Lead: NorthStar test management. Regression scope, qTest/ADO tracking, UAT coordination
A31: Business (UAT) | B31: INTL PO / IT Leads: Business product owners and IT leads. UAT execution and business sign-off
A32: PwC Tech | B32: PwC Technical: PwC technical team. SPDD/SPAU, notes, custom code, ATC, Fiori custom apps, RICEFW unit tests
A33: PwC Functional | B33: PwC Functional: PwC functional streams. SI-check application items, regression testing, integration flows
A34: PwC Data Migration | B34: PwC Data Migration: PwC data migration (Syniti). Mock loads, Syniti alignment, migration validation on SPS06
A35: SAP ECS | B35: SAP ECS: SAP Enterprise Cloud Services (via SRs). System copies, SUM execution, HANA/kernel, backups, technical FES upgrade
A36: SAP MaxAttention | B36: SAP MaxAttention: SAP MaxAttention engagement team. Plan safeguarding, issue escalation, weekend/go-live support
A37: SAP BTP | B37: SAP BTP team: SAP BTP team (from SAP). AFC, MBC, DRC, Work Zone tenants, Cloud Connector guidance
A38: Vendors | B38: Partner vendors: OpenText, Thomson Reuters, SailPoint, Syniti. Compatibility statements and partner-specific steps
A40: Sources
A41: SR | B41: SAP for Me SR 31018471 log (XS4 update), as uploaded
A42: MP | B42: Maintenance Plan 1002693650 (plan PDF, stack file, download list)
A43: UG | B43: Upgrade Guide for SAP S/4HANA Cloud Private Edition 2023, version 6.0 (UPGR_PE2023.pdf); section numbers quoted
A44: SER | B44: Side-effect report for MP 1002693650 (uploaded export) - note numbers quoted
A45: POAP | B45: Project NorthStar Plan on a Page (updated 9/21) and project dates given by INTL
A46: USER | B46: Decisions and facts stated by Girish Ogirala (INTL Basis)
A48: Fallback plans
A49: Plan B | B49: Plan B (ECS cannot meet a window, or G1 fails): shift the chain by one week - XS4 31 Oct, DS4 7 Nov (after SIT2, so DS5 is not needed for SIT2 fixes), QS4 14 Nov, SS4 21 Nov, PS4 28 Nov (Thanksgiving weekend). G5 moves to Wed 2 Dec, inside the Go/No-Go week; UAT weeks 1-2 run on FPS02 and weeks 3-4 on SPS06.
A50: Plan C | B50: Plan C (G3 fails): SS4 and PS4 stay on FPS02 and go live on FPS02. DS5 and QS5 (FPS02 copies) become the delivery line for fixes to SS4 and PS4; DS4 and QS4 stay on SPS06 as the post-go-live upgrade line. Remaining systems are upgraded after hypercare.
A52: Time zone | B52: Dates and times are US Central (the SR log uses America/Chicago). ECS windows are agreed in UTC.

Sheet Lists
A1: Status | B1: Colour | D1: Role code | F1: Workstream | H1: Phase
A2: Not Started | B2: Gray | D2: INTL-BAS | F2: GOV | H2: P0
A3: On Track | B3: Green | D3: INTL-SEC | F3: TEC | H3: P1
A4: Complete | B4: Green | D4: INTL-PMO | F4: CODE | H4: P2
A5: At Risk | B5: Yellow | D5: INTL-TST | F5: SEC | H5: P3
A6: Blocked | B6: Red | D6: INTL-PO | F6: INT | H6: P4
D7: PwC-TEC | F7: FIO | H7: P5
D8: PwC-FUN | F8: TST | H8: P6
D9: PwC-DM | F9: DM | H9: P7
D10: SAP-ECS
D11: SAP-MAX
D12: SAP-BTP
D13: VENDOR
